Workbook

Sheet Overview
A1: LittleStory AI — Jira Board & Delivery Workbook
A2: Little Stories. Big Imagination. · Generated 29 Oct 2026 from the master orchestrator prompt and the Figma Make design pack
A4: Project | B4: LittleStory AI – child-friendly AI storytelling app (ages 3–12) with parent controls
A5: Objective | B5: Production-quality, maintainable, accessible, multilingual native Android app that faithfully implements the approved Figma design, with no hardcoded values.
A6: Platform | B6: Native Android · Kotlin · Jetpack Compose · Material 3 (customised)
A7: Languages | B7: MVP: English (default & fallback) and Kannada (ಕನ್ನಡ). Future languages added via resources + registry only (no feature-code change).
A8: Design source | B8: https://www.figma.com/make/2DYtUW39GtnsDpUd5jSu6x/Mobile-App-UI-Prototype?p=f&t=7bdm57yPvNI3NZ8f-0
A9: Design pack | B9: docs/design/ – 22 screenshots (18 screens), design-tokens.json, LittleStory_Figma_Design_Details.md (see 'Screens' and 'Design Gallery' sheets)
A10: Repository | B10: https://github.com/shivayogih/LittleStory
A11: Dev environment | B11: Windows + macOS · Android Studio · Claude Code CLI · GitHub · GitHub Copilot
A12: MVP scope | B12: 18 designed screens with deterministic local mock data in EN/KN; simulated story generation, narration, downloads and demo subscription (clearly labelled).
A13: Out of scope (MVP) | B13: Real AI provider, backend, auth, cloud sync, analytics, real payments, production TTS/streaming, remote notifications, runtime machine translation, languages beyond EN/KN in the shipped UI.
A14: Architecture principles | B14: Clean layers (UI → ViewModel → use case → repository) · immutable UiState + StateFlow · design tokens only · string resources only (UiText in VMs) · central AppConfig & feature flags · per-language mock JSON · Hilt DI · no circular module deps
A15: No-hardcoding policy | B15: Text → strings.xml (EN + KN) · colours/dims/type → design tokens · limits/timings/options → AppConfig · routes → typed destinations · mock data → assets/mock JSON · versions → libs.versions.toml · languages → SupportedLanguage registry
... A19: Key risks | B19: Old 'LittleKatha' brand in designs · 7 design languages vs EN/KN · fonts lack Kannada glyphs · missing designs (splash, language prefs, privacy, help) · contrast & touch targets · Kannada reviewer availability. See 'Risks & Questions' · cloud workspace cannot build Android (R-21) · default branch misconfigured (R-22).
A21: Progress (live)
A22: Tickets total | B22: =COUNTA(Backlog!$A$2:$A$300)
A23: Done | B23: =COUNTIF(Backlog!$AD$2:$AD$300,"Done")
A24: In progress / in review | B24: =COUNTIF(Backlog!$AD$2:$AD$300,"In Progress")+COUNTIF(Backlog!$AD$2:$AD$300,"In Review")
A25: Blocked / needs clarification | B25: =COUNTIF(Backlog!$AD$2:$AD$300,"Blocked")+COUNTIF(Backlog!$AD$2:$AD$300,"Needs Clarification")
A26: Story points total | B26: =SUM(Backlog!$U$2:$U$300)
A27: Story points done | B27: =SUMIF(Backlog!$AD$2:$AD$300,"Done",Backlog!$U$2:$U$300)
A28: % points complete | B28: =IF(B26=0,0,B27/B26)
A30: How to use
A31: Board | B31: Kanban view – updates automatically when you change Status in 'Backlog'.
A32: Backlog | B32: Edit Status, Assignee, PR Link, Test Evidence, Actual Result, Kannada Translation Status (dropdowns provided). Do not rename Issue Keys.
A33: Screens / Design Gallery | B33: Screenshot thumbnails, full design details, links to the full screenshots in docs/design/screens/ and to Figma.
A34: Translations | B34: Fill the Kannada column; keep status 'Needs native review' until a fluent reviewer approves.
A35: Legend | B35: Editable columns have a cream header note. Grey 'Board Key' column in Backlog is a formula – do not edit.

Sheet Board
A1: Kanban Board
A2: Live view of the Backlog sheet – change a ticket's Status there and it moves here. Columns list 'Key · Summary'.
B4: To Do | C4: In Progress | D4: In Review | E4: Blocked | F4: Done | H4: 'Needs Clarification' tickets appear in Dashboard → By status.
B5: =COUNTIF(Backlog!$AD$2:$AD$300,"To Do")&" tickets · "&SUMIF(Backlog!$AD$2:$AD$300,"To Do",Backlog!$U$2:$U$300)&" pts" | C5: =COUNTIF(Backlog!$AD$2:$AD$300,"In Progress")&" tickets · "&SUMIF(Backlog!$AD$2:$AD$300,"In Progress",Backlog!$U$2:$U$300)&" pts" | D5: =COUNTIF(Backlog!$AD$2:$AD$300,"In Review")&" tickets · "&SUMIF(Backlog!$AD$2:$AD$300,"In Review",Backlog!$U$2:$U$300)&" pts" | E5: =COUNTIF(Backlog!$AD$2:$AD$300,"Blocked")&" tickets · "&SUMIF(Backlog!$AD$2:$AD$300,"Blocked",Backlog!$U$2:$U$300)&" pts" | F5: =COUNTIF(Backlog!$AD$2:$AD$300,"Done")&" tickets · "&SUMIF(Backlog!$AD$2:$AD$300,"Done",Backlog!$U$2:$U$300)&" pts"
B6: =IFERROR(INDEX(Backlog!$A$2:$A$300,MATCH("To Do|1",Backlog!$AL$2:$AL$300,0))&" · "&INDEX(Backlog!$D$2:$D$300,MATCH("To Do|1",Backlog!$AL$2:$AL$300,0)),"") | C6: =IFERROR(INDEX(Backlog!$A$2:$A$300,MATCH("In Progress|1",Backlog!$AL$2:$AL$300,0))&" · "&INDEX(Backlog!$D$2:$D$300,MATCH("In Progress|1",Backlog!$AL$2:$AL$300,0)),"") | D6: =IFERROR(INDEX(Backlog!$A$2:$A$300,MATCH("In Review|1",Backlog!$AL$2:$AL$300,0))&" · "&INDEX(Backlog!$D$2:$D$300,MATCH("In Review|1",Backlog!$AL$2:$AL$300,0)),"") | E6: =IFERROR(INDEX(Backlog!$A$2:$A$300,MATCH("Blocked|1",Backlog!$AL$2:$AL$300,0))&" · "&INDEX(Backlog!$D$2:$D$300,MATCH("Blocked|1",Backlog!$AL$2:$AL$300,0)),"") | F6: =IFERROR(INDEX(Backlog!$A$2:$A$300,MATCH("Done|1",Backlog!$AL$2:$AL$300,0))&" · "&INDEX(Backlog!$D$2:$D$300,MATCH("Done|1",Backlog!$AL$2:$AL$300,0)),"")
B7: =IFERROR(INDEX(Backlog!$A$2:$A$300,MATCH("To Do|2",Backlog!$AL$2:$AL$300,0))&" · "&INDEX(Backlog!$D$2:$D$300,MATCH("To Do|2",Backlog!$AL$2:$AL$300,0)),"") | C7: =IFERROR(INDEX(Backlog!$A$2:$A$300,MATCH("In Progress|2",Backlog!$AL$2:$AL$300,0))&" · "&INDEX(Backlog!$D$2:$D$300,MATCH("In Progress|2",Backlog!$AL$2:$AL$300,0)),"") | D7: =IFERROR(INDEX(Backlog!$A$2:$A$300,MATCH("In Review|2",Backlog!$AL$2:$AL$300,0))&" · "&INDEX(Backlog!$D$2:$D$300,MATCH("In Review|2",Backlog!$AL$2:$AL$300,0)),"") | E7: =IFERROR(INDEX(Backlog!$A$2:$A$300,MATCH("Blocked|2",Backlog!$AL$2:$AL$300,0))&" · "&INDEX(Backlog!$D$2:$D$300,MATCH("Blocked|2",Backlog!$AL$2:$AL$300,0)),"") | F7: =IFERROR(INDEX(Backlog!$A$2:$A$300,MATCH("Done|2",Backlog!$AL$2:$AL$300,0))&" · "&INDEX(Backlog!$D$2:$D$300,MATCH("Done|2",Backlog!$AL$2:$AL$300,0)),"")
B8: =IFERROR(INDEX(Backlog!$A$2:$A$300,MATCH("To Do|3",Backlog!$AL$2:$AL$300,0))&" · "&INDEX(Backlog!$D$2:$D$300,MATCH("To Do|3",Backlog!$AL$2:$AL$300,0)),"") | C8: =IFERROR(INDEX(Backlog!$A$2:$A$300,MATCH("In Progress|3",Backlog!$AL$2:$AL$300,0))&" · "&INDEX(Backlog!$D$2:$D$300,MATCH("In Progress|3",Backlog!$AL$2:$AL$300,0)),"") | D8: =IFERROR(INDEX(Backlog!$A$2:$A$300,MATCH("In Review|3",Backlog!$AL$2:$AL$300,0))&" · "&INDEX(Backlog!$D$2:$D$300,MATCH("In Review|3",Backlog!$AL$2:$AL$300,0)),"") | E8: =IFERROR(INDEX(Backlog!$A$2:$A$300,MATCH("Blocked|3",Backlog!$AL$2:$AL$300,0))&" · "&INDEX(Backlog!$D$2:$D$300,MATCH("Blocked|3",Backlog!$AL$2:$AL$300,0)),"") | F8: =IFERROR(INDEX(Backlog!$A$2:$A$300,MATCH("Done|3",Backlog!$AL$2:$AL$300,0))&" · "&INDEX(Backlog!$D$2:$D$300,MATCH("Done|3",Backlog!$AL$2:$AL$300,0)),"")
B9: =IFERROR(INDEX(Backlog!$A$2:$A$300,MATCH("To Do|4",Backlog!$AL$2:$AL$300,0))&" · "&INDEX(Backlog!$D$2:$D$300,MATCH("To Do|4",Backlog!$AL$2:$AL$300,0)),"") | C9: =IFERROR(INDEX(Backlog!$A$2:$A$300,MATCH("In Progress|4",Backlog!$AL$2:$AL$300,0))&" · "&INDEX(Backlog!$D$2:$D$300,MATCH("In Progress|4",Backlog!$AL$2:$AL$300,0)),"") | D9: =IFERROR(INDEX(Backlog!$A$2:$A$300,MATCH("In Review|4",Backlog!$AL$2:$AL$300,0))&" · "&INDEX(Backlog!$D$2:$D$300,MATCH("In Review|4",Backlog!$AL$2:$AL$300,0)),"") | E9: =IFERROR(INDEX(Backlog!$A$2:$A$300,MATCH("Blocked|4",Backlog!$AL$2:$AL$300,0))&" · "&INDEX(Backlog!$D$2:$D$300,MATCH("Blocked|4",Backlog!$AL$2:$AL$300,0)),"") | F9: =IFERROR(INDEX(Backlog!$A$2:$A$300,MATCH("Done|4",Backlog!$AL$2:$AL$300,0))&" · "&INDEX(Backlog!$D$2:$D$300,MATCH("Done|4",Backlog!$AL$2:$AL$300,0)),"")
B10: =IFERROR(INDEX(Backlog!$A$2:$A$300,MATCH("To Do|5",Backlog!$AL$2:$AL$300,0))&" · "&INDEX(Backlog!$D$2:$D$300,MATCH("To Do|5",Backlog!$AL$2:$AL$300,0)),"") | C10: =IFERROR(INDEX(Backlog!$A$2:$A$300,MATCH("In Progress|5",Backlog!$AL$2:$AL$300,0))&" · "&INDEX(Backlog!$D$2:$D$300,MATCH("In Progress|5",Backlog!$AL$2:$AL$300,0)),"") | D10: =IFERROR(INDEX(Backlog!$A$2:$A$300,MATCH("In Review|5",Backlog!$AL$2:$AL$300,0))&" · "&INDEX(Backlog!$D$2:$D$300,MATCH("In Review|5",Backlog!$AL$2:$AL$300,0)),"") | E10: =IFERROR(INDEX(Backlog!$A$2:$A$300,MATCH("Blocked|5",Backlog!$AL$2:$AL$300,0))&" · "&INDEX(Backlog!$D$2:$D$300,MATCH("Blocked|5",Backlog!$AL$2:$AL$300,0)),"") | F10: =IFERROR(INDEX(Backlog!$A$2:$A$300,MATCH("Done|5",Backlog!$AL$2:$AL$300,0))&" · "&INDEX(Backlog!$D$2:$D$300,MATCH("Done|5",Backlog!$AL$2:$AL$300,0)),"")
B11: =IFERROR(INDEX(Backlog!$A$2:$A$300,MATCH("To Do|6",Backlog!$AL$2:$AL$300,0))&" · "&INDEX(Backlog!$D$2:$D$300,MATCH("To Do|6",Backlog!$AL$2:$AL$300,0)),"") | C11: =IFERROR(INDEX(Backlog!$A$2:$A$300,MATCH("In Progress|6",Backlog!$AL$2:$AL$300,0))&" · "&INDEX(Backlog!$D$2:$D$300,MATCH("In Progress|6",Backlog!$AL$2:$AL$300,0)),"") | D11: =IFERROR(INDEX(Backlog!$A$2:$A$300,MATCH("In Review|6",Backlog!$AL$2:$AL$300,0))&" · "&INDEX(Backlog!$D$2:$D$300,MATCH("In Review|6",Backlog!$AL$2:$AL$300,0)),"") | E11: =IFERROR(INDEX(Backlog!$A$2:$A$300,MATCH("Blocked|6",Backlog!$AL$2:$AL$300,0))&" · "&INDEX(Backlog!$D$2:$D$300,MATCH("Blocked|6",Backlog!$AL$2:$AL$300,0)),"") | F11: =IFERROR(INDEX(Backlog!$A$2:$A$300,MATCH("Done|6",Backlog!$AL$2:$AL$300,0))&" · "&INDEX(Backlog!$D$2:$D$300,MATCH("Done|6",Backlog!$AL$2:$AL$300,0)),"")
B12: =IFERROR(INDEX(Backlog!$A$2:$A$300,MATCH("To Do|7",Backlog!$AL$2:$AL$300,0))&" · "&INDEX(Backlog!$D$2:$D$300,MATCH("To Do|7",Backlog!$AL$2:$AL$300,0)),"") | C12: =IFERROR(INDEX(Backlog!$A$2:$A$300,MATCH("In Progress|7",Backlog!$AL$2:$AL$300,0))&" · "&INDEX(Backlog!$D$2:$D$300,MATCH("In Progress|7",Backlog!$AL$2:$AL$300,0)),"") | D12: =IFERROR(INDEX(Backlog!$A$2:$A$300,MATCH("In Review|7",Backlog!$AL$2:$AL$300,0))&" · "&INDEX(Backlog!$D$2:$D$300,MATCH("In Review|7",Backlog!$AL$2:$AL$300,0)),"") | E12: =IFERROR(INDEX(Backlog!$A$2:$A$300,MATCH("Blocked|7",Backlog!$AL$2:$AL$300,0))&" · "&INDEX(Backlog!$D$2:$D$300,MATCH("Blocked|7",Backlog!$AL$2:$AL$300,0)),"") | F12: =IFERROR(INDEX(Backlog!$A$2:$A$300,MATCH("Done|7",Backlog!$AL$2:$AL$300,0))&" · "&INDEX(Backlog!$D$2:$D$300,MATCH("Done|7",Backlog!$AL$2:$AL$300,0)),"")
B13: =IFERROR(INDEX(Backlog!$A$2:$A$300,MATCH("To Do|8",Backlog!$AL$2:$AL$300,0))&" · "&INDEX(Backlog!$D$2:$D$300,MATCH("To Do|8",Backlog!$AL$2:$AL$300,0)),"") | C13: =IFERROR(INDEX(Backlog!$A$2:$A$300,MATCH("In Progress|8",Backlog!$AL$2:$AL$300,0))&" · "&INDEX(Backlog!$D$2:$D$300,MATCH("In Progress|8",Backlog!$AL$2:$AL$300,0)),"") | D13: =IFERROR(INDEX(Backlog!$A$2:$A$300,MATCH("In Review|8",Backlog!$AL$2:$AL$300,0))&" · "&INDEX(Backlog!$D$2:$D$300,MATCH("In Review|8",Backlog!$AL$2:$AL$300,0)),"") | E13: =IFERROR(INDEX(Backlog!$A$2:$A$300,MATCH("Blocked|8",Backlog!$AL$2:$AL$300,0))&" · "&INDEX(Backlog!$D$2:$D$300,MATCH("Blocked|8",Backlog!$AL$2:$AL$300,0)),"") | F13: =IFERROR(INDEX(Backlog!$A$2:$A$300,MATCH("Done|8",Backlog!$AL$2:$AL$300,0))&" · "&INDEX(Backlog!$D$2:$D$300,MATCH("Done|8",Backlog!$AL$2:$AL$300,0)),"")
B14: =IFERROR(INDEX(Backlog!$A$2:$A$300,MATCH("To Do|9",Backlog!$AL$2:$AL$300,0))&" · "&INDEX(Backlog!$D$2:$D$300,MATCH("To Do|9",Backlog!$AL$2:$AL$300,0)),"") | C14: =IFERROR(INDEX(Backlog!$A$2:$A$300,MATCH("In Progress|9",Backlog!$AL$2:$AL$300,0))&" · "&INDEX(Backlog!$D$2:$D$300,MATCH("In Progress|9",Backlog!$AL$2:$AL$300,0)),"") | D14: =IFERROR(INDEX(Backlog!$A$2:$A$300,MATCH("In Review|9",Backlog!$AL$2:$AL$300,0))&" · "&INDEX(Backlog!$D$2:$D$300,MATCH("In Review|9",Backlog!$AL$2:$AL$300,0)),"") | E14: =IFERROR(INDEX(Backlog!$A$2:$A$300,MATCH("Blocked|9",Backlog!$AL$2:$AL$300,0))&" · "&INDEX(Backlog!$D$2:$D$300,MATCH("Blocked|9",Backlog!$AL$2:$AL$300,0)),"") | F14: =IFERROR(INDEX(Backlog!$A$2:$A$300,MATCH("Done|9",Backlog!$AL$2:$AL$300,0))&" · "&INDEX(Backlog!$D$2:$D$300,MATCH("Done|9",Backlog!$AL$2:$AL$300,0)),"")
B15: =IFERROR(INDEX(Backlog!$A$2:$A$300,MATCH("To Do|10",Backlog!$AL$2:$AL$300,0))&" · "&INDEX(Backlog!$D$2:$D$300,MATCH("To Do|10",Backlog!$AL$2:$AL$300,0)),"") | C15: =IFERROR(INDEX(Backlog!$A$2:$A$300,MATCH("In Progress|10",Backlog!$AL$2:$AL$300,0))&" · "&INDEX(Backlog!$D$2:$D$300,MATCH("In Progress|10",Backlog!$AL$2:$AL$300,0)),"") | D15: =IFERROR(INDEX(Backlog!$A$2:$A$300,MATCH("In Review|10",Backlog!$AL$2:$AL$300,0))&" · "&INDEX(Backlog!$D$2:$D$300,MATCH("In Review|10",Backlog!$AL$2:$AL$300,0)),"") | E15: =IFERROR(INDEX(Backlog!$A$2:$A$300,MATCH("Blocked|10",Backlog!$AL$2:$AL$300,0))&" · "&INDEX(Backlog!$D$2:$D$300,MATCH("Blocked|10",Backlog!$AL$2:$AL$300,0)),"") | F15: =IFERROR(INDEX(Backlog!$A$2:$A$300,MATCH("Done|10",Backlog!$AL$2:$AL$300,0))&" · "&INDEX(Backlog!$D$2:$D$300,MATCH("Done|10",Backlog!$AL$2:$AL$300,0)),"")
B16: =IFERROR(INDEX(Backlog!$A$2:$A$300,MATCH("To Do|11",Backlog!$AL$2:$AL$300,0))&" · "&INDEX(Backlog!$D$2:$D$300,MATCH("To Do|11",Backlog!$AL$2:$AL$300,0)),"") | C16: =IFERROR(INDEX(Backlog!$A$2:$A$300,MATCH("In Progress|11",Backlog!$AL$2:$AL$300,0))&" · "&INDEX(Backlog!$D$2:$D$300,MATCH("In Progress|11",Backlog!$AL$2:$AL$300,0)),"") | D16: =IFERROR(INDEX(Backlog!$A$2:$A$300,MATCH("In Review|11",Backlog!$AL$2:$AL$300,0))&" · "&INDEX(Backlog!$D$2:$D$300,MATCH("In Review|11",Backlog!$AL$2:$AL$300,0)),"") | E16: =IFERROR(INDEX(Backlog!$A$2:$A$300,MATCH("Blocked|11",Backlog!$AL$2:$AL$300,0))&" · "&INDEX(Backlog!$D$2:$D$300,MATCH("Blocked|11",Backlog!$AL$2:$AL$300,0)),"") | F16: =IFERROR(INDEX(Backlog!$A$2:$A$300,MATCH("Done|11",Backlog!$AL$2:$AL$300,0))&" · "&INDEX(Backlog!$D$2:$D$300,MATCH("Done|11",Backlog!$AL$2:$AL$300,0)),"")
B17: =IFERROR(INDEX(Backlog!$A$2:$A$300,MATCH("To Do|12",Backlog!$AL$2:$AL$300,0))&" · "&INDEX(Backlog!$D$2:$D$300,MATCH("To Do|12",Backlog!$AL$2:$AL$300,0)),"") | C17: =IFERROR(INDEX(Backlog!$A$2:$A$300,MATCH("In Progress|12",Backlog!$AL$2:$AL$300,0))&" · "&INDEX(Backlog!$D$2:$D$300,MATCH("In Progress|12",Backlog!$AL$2:$AL$300,0)),"") | D17: =IFERROR(INDEX(Backlog!$A$2:$A$300,MATCH("In Review|12",Backlog!$AL$2:$AL$300,0))&" · "&INDEX(Backlog!$D$2:$D$300,MATCH("In Review|12",Backlog!$AL$2:$AL$300,0)),"") | E17: =IFERROR(INDEX(Backlog!$A$2:$A$300,MATCH("Blocked|12",Backlog!$AL$2:$AL$300,0))&" · "&INDEX(Backlog!$D$2:$D$300,MATCH("Blocked|12",Backlog!$AL$2:$AL$300,0)),"") | F17: =IFERROR(INDEX(Backlog!$A$2:$A$300,MATCH("Done|12",Backlog!$AL$2:$AL$300,0))&" · "&INDEX(Backlog!$D$2:$D$300,MATCH("Done|12",Backlog!$AL$2:$AL$300,0)),"")
B18: =IFERROR(INDEX(Backlog!$A$2:$A$300,MATCH("To Do|13",Backlog!$AL$2:$AL$300,0))&" · "&INDEX(Backlog!$D$2:$D$300,MATCH("To Do|13",Backlog!$AL$2:$AL$300,0)),"") | C18: =IFERROR(INDEX(Backlog!$A$2:$A$300,MATCH("In Progress|13",Backlog!$AL$2:$AL$300,0))&" · "&INDEX(Backlog!$D$2:$D$300,MATCH("In Progress|13",Backlog!$AL$2:$AL$300,0)),"") | D18: =IFERROR(INDEX(Backlog!$A$2:$A$300,MATCH("In Review|13",Backlog!$AL$2:$AL$300,0))&" · "&INDEX(Backlog!$D$2:$D$300,MATCH("In Review|13",Backlog!$AL$2:$AL$300,0)),"") | E18: =IFERROR(INDEX(Backlog!$A$2:$A$300,MATCH("Blocked|13",Backlog!$AL$2:$AL$300,0))&" · "&INDEX(Backlog!$D$2:$D$300,MATCH("Blocked|13",Backlog!$AL$2:$AL$300,0)),"") | F18: =IFERROR(INDEX(Backlog!$A$2:$A$300,MATCH("Done|13",Backlog!$AL$2:$AL$300,0))&" · "&INDEX(Backlog!$D$2:$D$300,MATCH("Done|13",Backlog!$AL$2:$AL$300,0)),"")
B19: =IFERROR(INDEX(Backlog!$A$2:$A$300,MATCH("To Do|14",Backlog!$AL$2:$AL$300,0))&" · "&INDEX(Backlog!$D$2:$D$300,MATCH("To Do|14",Backlog!$AL$2:$AL$300,0)),"") | C19: =IFERROR(INDEX(Backlog!$A$2:$A$300,MATCH("In Progress|14",Backlog!$AL$2:$AL$300,0))&" · "&INDEX(Backlog!$D$2:$D$300,MATCH("In Progress|14",Backlog!$AL$2:$AL$300,0)),"") | D19: =IFERROR(INDEX(Backlog!$A$2:$A$300,MATCH("In Review|14",Backlog!$AL$2:$AL$300,0))&" · "&INDEX(Backlog!$D$2:$D$300,MATCH("In Review|14",Backlog!$AL$2:$AL$300,0)),"") | E19: =IFERROR(INDEX(Backlog!$A$2:$A$300,MATCH("Blocked|14",Backlog!$AL$2:$AL$300,0))&" · "&INDEX(Backlog!$D$2:$D$300,MATCH("Blocked|14",Backlog!$AL$2:$AL$300,0)),"") | F19: =IFERROR(INDEX(Backlog!$A$2:$A$300,MATCH("Done|14",Backlog!$AL$2:$AL$300,0))&" · "&INDEX(Backlog!$D$2:$D$300,MATCH("Done|14",Backlog!$AL$2:$AL$300,0)),"")
B20: =IFERROR(INDEX(Backlog!$A$2:$A$300,MATCH("To Do|15",Backlog!$AL$2:$AL$300,0))&" · "&INDEX(Backlog!$D$2:$D$300,MATCH("To Do|15",Backlog!$AL$2:$AL$300,0)),"") | C20: =IFERROR(INDEX(Backlog!$A$2:$A$300,MATCH("In Progress|15",Backlog!$AL$2:$AL$300,0))&" · "&INDEX(Backlog!$D$2:$D$300,MATCH("In Progress|15",Backlog!$AL$2:$AL$300,0)),"") | D20: =IFERROR(INDEX(Backlog!$A$2:$A$300,MATCH("In Review|15",Backlog!$AL$2:$AL$300,0))&" · "&INDEX(Backlog!$D$2:$D$300,MATCH("In Review|15",Backlog!$AL$2:$AL$300,0)),"") | E20: =IFERROR(INDEX(Backlog!$A$2:$A$300,MATCH("Blocked|15",Backlog!$AL$2:$AL$300,0))&" · "&INDEX(Backlog!$D$2:$D$300,MATCH("Blocked|15",Backlog!$AL$2:$AL$300,0)),"") | F20: =IFERROR(INDEX(Backlog!$A$2:$A$300,MATCH("Done|15",Backlog!$AL$2:$AL$300,0))&" · "&INDEX(Backlog!$D$2:$D$300,MATCH("Done|15",Backlog!$AL$2:$AL$300,0)),"")
B21: =IFERROR(INDEX(Backlog!$A$2:$A$300,MATCH("To Do|16",Backlog!$AL$2:$AL$300,0))&" · "&INDEX(Backlog!$D$2:$D$300,MATCH("To Do|16",Backlog!$AL$2:$AL$300,0)),"") | C21: =IFERROR(INDEX(Backlog!$A$2:$A$300,MATCH("In Progress|16",Backlog!$AL$2:$AL$300,0))&" · "&INDEX(Backlog!$D$2:$D$300,MATCH("In Progress|16",Backlog!$AL$2:$AL$300,0)),"") | D21: =IFERROR(INDEX(Backlog!$A$2:$A$300,MATCH("In Review|16",Backlog!$AL$2:$AL$300,0))&" · "&INDEX(Backlog!$D$2:$D$300,MATCH("In Review|16",Backlog!$AL$2:$AL$300,0)),"") | E21: =IFERROR(INDEX(Backlog!$A$2:$A$300,MATCH("Blocked|16",Backlog!$AL$2:$AL$300,0))&" · "&INDEX(Backlog!$D$2:$D$300,MATCH("Blocked|16",Backlog!$AL$2:$AL$300,0)),"") | F21: =IFERROR(INDEX(Backlog!$A$2:$A$300,MATCH("Done|16",Backlog!$AL$2:$AL$300,0))&" · "&INDEX(Backlog!$D$2:$D$300,MATCH("Done|16",Backlog!$AL$2:$AL$300,0)),"")
B22: =IFERROR(INDEX(Backlog!$A$2:$A$300,MATCH("To Do|17",Backlog!$AL$2:$AL$300,0))&" · "&INDEX(Backlog!$D$2:$D$300,MATCH("To Do|17",Backlog!$AL$2:$AL$300,0)),"") | C22: =IFERROR(INDEX(Backlog!$A$2:$A$300,MATCH("In Progress|17",Backlog!$AL$2:$AL$300,0))&" · "&INDEX(Backlog!$D$2:$D$300,MATCH("In Progress|17",Backlog!$AL$2:$AL$300,0)),"") | D22: =IFERROR(INDEX(Backlog!$A$2:$A$300,MATCH("In Review|17",Backlog!$AL$2:$AL$300,0))&" · "&INDEX(Backlog!$D$2:$D$300,MATCH("In Review|17",Backlog!$AL$2:$AL$300,0)),"") | E22: =IFERROR(INDEX(Backlog!$A$2:$A$300,MATCH("Blocked|17",Backlog!$AL$2:$AL$300,0))&" · "&INDEX(Backlog!$D$2:$D$300,MATCH("Blocked|17",Backlog!$AL$2:$AL$300,0)),"") | F22: =IFERROR(INDEX(Backlog!$A$2:$A$300,MATCH("Done|17",Backlog!$AL$2:$AL$300,0))&" · "&INDEX(Backlog!$D$2:$D$300,MATCH("Done|17",Backlog!$AL$2:$AL$300,0)),"")
B23: =IFERROR(INDEX(Backlog!$A$2:$A$300,MATCH("To Do|18",Backlog!$AL$2:$AL$300,0))&" · "&INDEX(Backlog!$D$2:$D$300,MATCH("To Do|18",Backlog!$AL$2:$AL$300,0)),"") | C23: =IFERROR(INDEX(Backlog!$A$2:$A$300,MATCH("In Progress|18",Backlog!$AL$2:$AL$300,0))&" · "&INDEX(Backlog!$D$2:$D$300,MATCH("In Progress|18",Backlog!$AL$2:$AL$300,0)),"") | D23: =IFERROR(INDEX(Backlog!$A$2:$A$300,MATCH("In Review|18",Backlog!$AL$2:$AL$300,0))&" · "&INDEX(Backlog!$D$2:$D$300,MATCH("In Review|18",Backlog!$AL$2:$AL$300,0)),"") | E23: =IFERROR(INDEX(Backlog!$A$2:$A$300,MATCH("Blocked|18",Backlog!$AL$2:$AL$300,0))&" · "&INDEX(Backlog!$D$2:$D$300,MATCH("Blocked|18",Backlog!$AL$2:$AL$300,0)),"") | F23: =IFERROR(INDEX(Backlog!$A$2:$A$300,MATCH("Done|18",Backlog!$AL$2:$AL$300,0))&" · "&INDEX(Backlog!$D$2:$D$300,MATCH("Done|18",Backlog!$AL$2:$AL$300,0)),"")
B24: =IFERROR(INDEX(Backlog!$A$2:$A$300,MATCH("To Do|19",Backlog!$AL$2:$AL$300,0))&" · "&INDEX(Backlog!$D$2:$D$300,MATCH("To Do|19",Backlog!$AL$2:$AL$300,0)),"") | C24: =IFERROR(INDEX(Backlog!$A$2:$A$300,MATCH("In Progress|19",Backlog!$AL$2:$AL$300,0))&" · "&INDEX(Backlog!$D$2:$D$300,MATCH("In Progress|19",Backlog!$AL$2:$AL$300,0)),"") | D24: =IFERROR(INDEX(Backlog!$A$2:$A$300,MATCH("In Review|19",Backlog!$AL$2:$AL$300,0))&" · "&INDEX(Backlog!$D$2:$D$300,MATCH("In Review|19",Backlog!$AL$2:$AL$300,0)),"") | E24: =IFERROR(INDEX(Backlog!$A$2:$A$300,MATCH("Blocked|19",Backlog!$AL$2:$AL$300,0))&" · "&INDEX(Backlog!$D$2:$D$300,MATCH("Blocked|19",Backlog!$AL$2:$AL$300,0)),"") | F24: =IFERROR(INDEX(Backlog!$A$2:$A$300,MATCH("Done|19",Backlog!$AL$2:$AL$300,0))&" · "&INDEX(Backlog!$D$2:$D$300,MATCH("Done|19",Backlog!$AL$2:$AL$300,0)),"")
B25: =IFERROR(INDEX(Backlog!$A$2:$A$300,MATCH("To Do|20",Backlog!$AL$2:$AL$300,0))&" · "&INDEX(Backlog!$D$2:$D$300,MATCH("To Do|20",Backlog!$AL$2:$AL$300,0)),"") | C25: =IFERROR(INDEX(Backlog!$A$2:$A$300,MATCH("In Progress|20",Backlog!$AL$2:$AL$300,0))&" · "&INDEX(Backlog!$D$2:$D$300,MATCH("In Progress|20",Backlog!$AL$2:$AL$300,0)),"") | D25: =IFERROR(INDEX(Backlog!$A$2:$A$300,MATCH("In Review|20",Backlog!$AL$2:$AL$300,0))&" · "&INDEX(Backlog!$D$2:$D$300,MATCH("In Review|20",Backlog!$AL$2:$AL$300,0)),"") | E25: =IFERROR(INDEX(Backlog!$A$2:$A$300,MATCH("Blocked|20",Backlog!$AL$2:$AL$300,0))&" · "&INDEX(Backlog!$D$2:$D$300,MATCH("Blocked|20",Backlog!$AL$2:$AL$300,0)),"") | F25: =IFERROR(INDEX(Backlog!$A$2:$A$300,MATCH("Done|20",Backlog!$AL$2:$AL$300,0))&" · "&INDEX(Backlog!$D$2:$D$300,MATCH("Done|20",Backlog!$AL$2:$AL$300,0)),"")
B26: =IFERROR(INDEX(Backlog!$A$2:$A$300,MATCH("To Do|21",Backlog!$AL$2:$AL$300,0))&" · "&INDEX(Backlog!$D$2:$D$300,MATCH("To Do|21",Backlog!$AL$2:$AL$300,0)),"") | C26: =IFERROR(INDEX(Backlog!$A$2:$A$300,MATCH("In Progress|21",Backlog!$AL$2:$AL$300,0))&" · "&INDEX(Backlog!$D$2:$D$300,MATCH("In Progress|21",Backlog!$AL$2:$AL$300,0)),"") | D26: =IFERROR(INDEX(Backlog!$A$2:$A$300,MATCH("In Review|21",Backlog!$AL$2:$AL$300,0))&" · "&INDEX(Backlog!$D$2:$D$300,MATCH("In Review|21",Backlog!$AL$2:$AL$300,0)),"") | E26: =IFERROR(INDEX(Backlog!$A$2:$A$300,MATCH("Blocked|21",Backlog!$AL$2:$AL$300,0))&" · "&INDEX(Backlog!$D$2:$D$300,MATCH("Blocked|21",Backlog!$AL$2:$AL$300,0)),"") | F26: =IFERROR(INDEX(Backlog!$A$2:$A$300,MATCH("Done|21",Backlog!$AL$2:$AL$300,0))&" · "&INDEX(Backlog!$D$2:$D$300,MATCH("Done|21",Backlog!$AL$2:$AL$300,0)),"")
B27: =IFERROR(INDEX(Backlog!$A$2:$A$300,MATCH("To Do|22",Backlog!$AL$2:$AL$300,0))&" · "&INDEX(Backlog!$D$2:$D$300,MATCH("To Do|22",Backlog!$AL$2:$AL$300,0)),"") | C27: =IFERROR(INDEX(Backlog!$A$2:$A$300,MATCH("In Progress|22",Backlog!$AL$2:$AL$300,0))&" · "&INDEX(Backlog!$D$2:$D$300,MATCH("In Progress|22",Backlog!$AL$2:$AL$300,0)),"") | D27: =IFERROR(INDEX(Backlog!$A$2:$A$300,MATCH("In Review|22",Backlog!$AL$2:$AL$300,0))&" · "&INDEX(Backlog!$D$2:$D$300,MATCH("In Review|22",Backlog!$AL$2:$AL$300,0)),"") | E27: =IFERROR(INDEX(Backlog!$A$2:$A$300,MATCH("Blocked|22",Backlog!$AL$2:$AL$300,0))&" · "&INDEX(Backlog!$D$2:$D$300,MATCH("Blocked|22",Backlog!$AL$2:$AL$300,0)),"") | F27: =IFERROR(INDEX(Backlog!$A$2:$A$300,MATCH("Done|22",Backlog!$AL$2:$AL$300,0))&" · "&INDEX(Backlog!$D$2:$D$300,MATCH("Done|22",Backlog!$AL$2:$AL$300,0)),"")
B28: =IFERROR(INDEX(Backlog!$A$2:$A$300,MATCH("To Do|23",Backlog!$AL$2:$AL$300,0))&" · "&INDEX(Backlog!$D$2:$D$300,MATCH("To Do|23",Backlog!$AL$2:$AL$300,0)),"") | C28: =IFERROR(INDEX(Backlog!$A$2:$A$300,MATCH("In Progress|23",Backlog!$AL$2:$AL$300,0))&" · "&INDEX(Backlog!$D$2:$D$300,MATCH("In Progress|23",Backlog!$AL$2:$AL$300,0)),"") | D28: =IFERROR(INDEX(Backlog!$A$2:$A$300,MATCH("In Review|23",Backlog!$AL$2:$AL$300,0))&" · "&INDEX(Backlog!$D$2:$D$300,MATCH("In Review|23",Backlog!$AL$2:$AL$300,0)),"") | E28: =IFERROR(INDEX(Backlog!$A$2:$A$300,MATCH("Blocked|23",Backlog!$AL$2:$AL$300,0))&" · "&INDEX(Backlog!$D$2:$D$300,MATCH("Blocked|23",Backlog!$AL$2:$AL$300,0)),"") | F28: =IFERROR(INDEX(Backlog!$A$2:$A$300,MATCH("Done|23",Backlog!$AL$2:$AL$300,0))&" · "&INDEX(Backlog!$D$2:$D$300,MATCH("Done|23",Backlog!$AL$2:$AL$300,0)),"")
B29: =IFERROR(INDEX(Backlog!$A$2:$A$300,MATCH("To Do|24",Backlog!$AL$2:$AL$300,0))&" · "&INDEX(Backlog!$D$2:$D$300,MATCH("To Do|24",Backlog!$AL$2:$AL$300,0)),"") | C29: =IFERROR(INDEX(Backlog!$A$2:$A$300,MATCH("In Progress|24",Backlog!$AL$2:$AL$300,0))&" · "&INDEX(Backlog!$D$2:$D$300,MATCH("In Progress|24",Backlog!$AL$2:$AL$300,0)),"") | D29: =IFERROR(INDEX(Backlog!$A$2:$A$300,MATCH("In Review|24",Backlog!$AL$2:$AL$300,0))&" · "&INDEX(Backlog!$D$2:$D$300,MATCH("In Review|24",Backlog!$AL$2:$AL$300,0)),"") | E29: =IFERROR(INDEX(Backlog!$A$2:$A$300,MATCH("Blocked|24",Backlog!$AL$2:$AL$300,0))&" · "&INDEX(Backlog!$D$2:$D$300,MATCH("Blocked|24",Backlog!$AL$2:$AL$300,0)),"") | F29: =IFERROR(INDEX(Backlog!$A$2:$A$300,MATCH("Done|24",Backlog!$AL$2:$AL$300,0))&" · "&INDEX(Backlog!$D$2:$D$300,MATCH("Done|24",Backlog!$AL$2:$AL$300,0)),"")
B30: =IFERROR(INDEX(Backlog!$A$2:$A$300,MATCH("To Do|25",Backlog!$AL$2:$AL$300,0))&" · "&INDEX(Backlog!$D$2:$D$300,MATCH("To Do|25",Backlog!$AL$2:$AL$300,0)),"") | C30: =IFERROR(INDEX(Backlog!$A$2:$A$300,MATCH("In Progress|25",Backlog!$AL$2:$AL$300,0))&" · "&INDEX(Backlog!$D$2:$D$300,MATCH("In Progress|25",Backlog!$AL$2:$AL$300,0)),"") | D30: =IFERROR(INDEX(Backlog!$A$2:$A$300,MATCH("In Review|25",Backlog!$AL$2:$AL$300,0))&" · "&INDEX(Backlog!$D$2:$D$300,MATCH("In Review|25",Backlog!$AL$2:$AL$300,0)),"") | E30: =IFERROR(INDEX(Backlog!$A$2:$A$300,MATCH("Blocked|25",Backlog!$AL$2:$AL$300,0))&" · "&INDEX(Backlog!$D$2:$D$300,MATCH("Blocked|25",Backlog!$AL$2:$AL$300,0)),"") | F30: =IFERROR(INDEX(Backlog!$A$2:$A$300,MATCH("Done|25",Backlog!$AL$2:$AL$300,0))&" · "&INDEX(Backlog!$D$2:$D$300,MATCH("Done|25",Backlog!$AL$2:$AL$300,0)),"")
B31: =IFERROR(INDEX(Backlog!$A$2:$A$300,MATCH("To Do|26",Backlog!$AL$2:$AL$300,0))&" · "&INDEX(Backlog!$D$2:$D$300,MATCH("To Do|26",Backlog!$AL$2:$AL$300,0)),"") | C31: =IFERROR(INDEX(Backlog!$A$2:$A$300,MATCH("In Progress|26",Backlog!$AL$2:$AL$300,0))&" · "&INDEX(Backlog!$D$2:$D$300,MATCH("In Progress|26",Backlog!$AL$2:$AL$300,0)),"") | D31: =IFERROR(INDEX(Backlog!$A$2:$A$300,MATCH("In Review|26",Backlog!$AL$2:$AL$300,0))&" · "&INDEX(Backlog!$D$2:$D$300,MATCH("In Review|26",Backlog!$AL$2:$AL$300,0)),"") | E31: =IFERROR(INDEX(Backlog!$A$2:$A$300,MATCH("Blocked|26",Backlog!$AL$2:$AL$300,0))&" · "&INDEX(Backlog!$D$2:$D$300,MATCH("Blocked|26",Backlog!$AL$2:$AL$300,0)),"") | F31: =IFERROR(INDEX(Backlog!$A$2:$A$300,MATCH("Done|26",Backlog!$AL$2:$AL$300,0))&" · "&INDEX(Backlog!$D$2:$D$300,MATCH("Done|26",Backlog!$AL$2:$AL$300,0)),"")
B32: =IFERROR(INDEX(Backlog!$A$2:$A$300,MATCH("To Do|27",Backlog!$AL$2:$AL$300,0))&" · "&INDEX(Backlog!$D$2:$D$300,MATCH("To Do|27",Backlog!$AL$2:$AL$300,0)),"") | C32: =IFERROR(INDEX(Backlog!$A$2:$A$300,MATCH("In Progress|27",Backlog!$AL$2:$AL$300,0))&" · "&INDEX(Backlog!$D$2:$D$300,MATCH("In Progress|27",Backlog!$AL$2:$AL$300,0)),"") | D32: =IFERROR(INDEX(Backlog!$A$2:$A$300,MATCH("In Review|27",Backlog!$AL$2:$AL$300,0))&" · "&INDEX(Backlog!$D$2:$D$300,MATCH("In Review|27",Backlog!$AL$2:$AL$300,0)),"") | E32: =IFERROR(INDEX(Backlog!$A$2:$A$300,MATCH("Blocked|27",Backlog!$AL$2:$AL$300,0))&" · "&INDEX(Backlog!$D$2:$D$300,MATCH("Blocked|27",Backlog!$AL$2:$AL$300,0)),"") | F32: =IFERROR(INDEX(Backlog!$A$2:$A$300,MATCH("Done|27",Backlog!$AL$2:$AL$300,0))&" · "&INDEX(Backlog!$D$2:$D$300,MATCH("Done|27",Backlog!$AL$2:$AL$300,0)),"")
B33: =IFERROR(INDEX(Backlog!$A$2:$A$300,MATCH("To Do|28",Backlog!$AL$2:$AL$300,0))&" · "&INDEX(Backlog!$D$2:$D$300,MATCH("To Do|28",Backlog!$AL$2:$AL$300,0)),"") | C33: =IFERROR(INDEX(Backlog!$A$2:$A$300,MATCH("In Progress|28",Backlog!$AL$2:$AL$300,0))&" · "&INDEX(Backlog!$D$2:$D$300,MATCH("In Progress|28",Backlog!$AL$2:$AL$300,0)),"") | D33: =IFERROR(INDEX(Backlog!$A$2:$A$300,MATCH("In Review|28",Backlog!$AL$2:$AL$300,0))&" · "&INDEX(Backlog!$D$2:$D$300,MATCH("In Review|28",Backlog!$AL$2:$AL$300,0)),"") | E33: =IFERROR(INDEX(Backlog!$A$2:$A$300,MATCH("Blocked|28",Backlog!$AL$2:$AL$300,0))&" · "&INDEX(Backlog!$D$2:$D$300,MATCH("Blocked|28",Backlog!$AL$2:$AL$300,0)),"") | F33: =IFERROR(INDEX(Backlog!$A$2:$A$300,MATCH("Done|28",Backlog!$AL$2:$AL$300,0))&" · "&INDEX(Backlog!$D$2:$D$300,MATCH("Done|28",Backlog!$AL$2:$AL$300,0)),"")
B34: =IFERROR(INDEX(Backlog!$A$2:$A$300,MATCH("To Do|29",Backlog!$AL$2:$AL$300,0))&" · "&INDEX(Backlog!$D$2:$D$300,MATCH("To Do|29",Backlog!$AL$2:$AL$300,0)),"") | C34: =IFERROR(INDEX(Backlog!$A$2:$A$300,MATCH("In Progress|29",Backlog!$AL$2:$AL$300,0))&" · "&INDEX(Backlog!$D$2:$D$300,MATCH("In Progress|29",Backlog!$AL$2:$AL$300,0)),"") | D34: =IFERROR(INDEX(Backlog!$A$2:$A$300,MATCH("In Review|29",Backlog!$AL$2:$AL$300,0))&" · "&INDEX(Backlog!$D$2:$D$300,MATCH("In Review|29",Backlog!$AL$2:$AL$300,0)),"") | E34: =IFERROR(INDEX(Backlog!$A$2:$A$300,MATCH("Blocked|29",Backlog!$AL$2:$AL$300,0))&" · "&INDEX(Backlog!$D$2:$D$300,MATCH("Blocked|29",Backlog!$AL$2:$AL$300,0)),"") | F34: =IFERROR(INDEX(Backlog!$A$2:$A$300,MATCH("Done|29",Backlog!$AL$2:$AL$300,0))&" · "&INDEX(Backlog!$D$2:$D$300,MATCH("Done|29",Backlog!$AL$2:$AL$300,0)),"")
B35: =IFERROR(INDEX(Backlog!$A$2:$A$300,MATCH("To Do|30",Backlog!$AL$2:$AL$300,0))&" · "&INDEX(Backlog!$D$2:$D$300,MATCH("To Do|30",Backlog!$AL$2:$AL$300,0)),"") | C35: =IFERROR(INDEX(Backlog!$A$2:$A$300,MATCH("In Progress|30",Backlog!$AL$2:$AL$300,0))&" · "&INDEX(Backlog!$D$2:$D$300,MATCH("In Progress|30",Backlog!$AL$2:$AL$300,0)),"") | D35: =IFERROR(INDEX(Backlog!$A$2:$A$300,MATCH("In Review|30",Backlog!$AL$2:$AL$300,0))&" · "&INDEX(Backlog!$D$2:$D$300,MATCH("In Review|30",Backlog!$AL$2:$AL$300,0)),"") | E35: =IFERROR(INDEX(Backlog!$A$2:$A$300,MATCH("Blocked|30",Backlog!$AL$2:$AL$300,0))&" · "&INDEX(Backlog!$D$2:$D$300,MATCH("Blocked|30",Backlog!$AL$2:$AL$300,0)),"") | F35: =IFERROR(INDEX(Backlog!$A$2:$A$300,MATCH("Done|30",Backlog!$AL$2:$AL$300,0))&" · "&INDEX(Backlog!$D$2:$D$300,MATCH("Done|30",Backlog!$AL$2:$AL$300,0)),"")
B36: =IFERROR(INDEX(Backlog!$A$2:$A$300,MATCH("To Do|31",Backlog!$AL$2:$AL$300,0))&" · "&INDEX(Backlog!$D$2:$D$300,MATCH("To Do|31",Backlog!$AL$2:$AL$300,0)),"") | C36: =IFERROR(INDEX(Backlog!$A$2:$A$300,MATCH("In Progress|31",Backlog!$AL$2:$AL$300,0))&" · "&INDEX(Backlog!$D$2:$D$300,MATCH("In Progress|31",Backlog!$AL$2:$AL$300,0)),"") | D36: =IFERROR(INDEX(Backlog!$A$2:$A$300,MATCH("In Review|31",Backlog!$AL$2:$AL$300,0))&" · "&INDEX(Backlog!$D$2:$D$300,MATCH("In Review|31",Backlog!$AL$2:$AL$300,0)),"") | E36: =IFERROR(INDEX(Backlog!$A$2:$A$300,MATCH("Blocked|31",Backlog!$AL$2:$AL$300,0))&" · "&INDEX(Backlog!$D$2:$D$300,MATCH("Blocked|31",Backlog!$AL$2:$AL$300,0)),"") | F36: =IFERROR(INDEX(Backlog!$A$2:$A$300,MATCH("Done|31",Backlog!$AL$2:$AL$300,0))&" · "&INDEX(Backlog!$D$2:$D$300,MATCH("Done|31",Backlog!$AL$2:$AL$300,0)),"")
B37: =IFERROR(INDEX(Backlog!$A$2:$A$300,MATCH("To Do|32",Backlog!$AL$2:$AL$300,0))&" · "&INDEX(Backlog!$D$2:$D$300,MATCH("To Do|32",Backlog!$AL$2:$AL$300,0)),"") | C37: =IFERROR(INDEX(Backlog!$A$2:$A$300,MATCH("In Progress|32",Backlog!$AL$2:$AL$300,0))&" · "&INDEX(Backlog!$D$2:$D$300,MATCH("In Progress|32",Backlog!$AL$2:$AL$300,0)),"") | D37: =IFERROR(INDEX(Backlog!$A$2:$A$300,MATCH("In Review|32",Backlog!$AL$2:$AL$300,0))&" · "&INDEX(Backlog!$D$2:$D$300,MATCH("In Review|32",Backlog!$AL$2:$AL$300,0)),"") | E37: =IFERROR(INDEX(Backlog!$A$2:$A$300,MATCH("Blocked|32",Backlog!$AL$2:$AL$300,0))&" · "&INDEX(Backlog!$D$2:$D$300,MATCH("Blocked|32",Backlog!$AL$2:$AL$300,0)),"") | F37: =IFERROR(INDEX(Backlog!$A$2:$A$300,MATCH("Done|32",Backlog!$AL$2:$AL$300,0))&" · "&INDEX(Backlog!$D$2:$D$300,MATCH("Done|32",Backlog!$AL$2:$AL$300,0)),"")
B38: =IFERROR(INDEX(Backlog!$A$2:$A$300,MATCH("To Do|33",Backlog!$AL$2:$AL$300,0))&" · "&INDEX(Backlog!$D$2:$D$300,MATCH("To Do|33",Backlog!$AL$2:$AL$300,0)),"") | C38: =IFERROR(INDEX(Backlog!$A$2:$A$300,MATCH("In Progress|33",Backlog!$AL$2:$AL$300,0))&" · "&INDEX(Backlog!$D$2:$D$300,MATCH("In Progress|33",Backlog!$AL$2:$AL$300,0)),"") | D38: =IFERROR(INDEX(Backlog!$A$2:$A$300,MATCH("In Review|33",Backlog!$AL$2:$AL$300,0))&" · "&INDEX(Backlog!$D$2:$D$300,MATCH("In Review|33",Backlog!$AL$2:$AL$300,0)),"") | E38: =IFERROR(INDEX(Backlog!$A$2:$A$300,MATCH("Blocked|33",Backlog!$AL$2:$AL$300,0))&" · "&INDEX(Backlog!$D$2:$D$300,MATCH("Blocked|33",Backlog!$AL$2:$AL$300,0)),"") | F38: =IFERROR(INDEX(Backlog!$A$2:$A$300,MATCH("Done|33",Backlog!$AL$2:$AL$300,0))&" · "&INDEX(Backlog!$D$2:$D$300,MATCH("Done|33",Backlog!$AL$2:$AL$300,0)),"")
B39: =IFERROR(INDEX(Backlog!$A$2:$A$300,MATCH("To Do|34",Backlog!$AL$2:$AL$300,0))&" · "&INDEX(Backlog!$D$2:$D$300,MATCH("To Do|34",Backlog!$AL$2:$AL$300,0)),"") | C39: =IFERROR(INDEX(Backlog!$A$2:$A$300,MATCH("In Progress|34",Backlog!$AL$2:$AL$300,0))&" · "&INDEX(Backlog!$D$2:$D$300,MATCH("In Progress|34",Backlog!$AL$2:$AL$300,0)),"") | D39: =IFERROR(INDEX(Backlog!$A$2:$A$300,MATCH("In Review|34",Backlog!$AL$2:$AL$300,0))&" · "&INDEX(Backlog!$D$2:$D$300,MATCH("In Review|34",Backlog!$AL$2:$AL$300,0)),"") | E39: =IFERROR(INDEX(Backlog!$A$2:$A$300,MATCH("Blocked|34",Backlog!$AL$2:$AL$300,0))&" · "&INDEX(Backlog!$D$2:$D$300,MATCH("Blocked|34",Backlog!$AL$2:$AL$300,0)),"") | F39: =IFERROR(INDEX(Backlog!$A$2:$A$300,MATCH("Done|34",Backlog!$AL$2:$AL$300,0))&" · "&INDEX(Backlog!$D$2:$D$300,MATCH("Done|34",Backlog!$AL$2:$AL$300,0)),"")
B40: =IFERROR(INDEX(Backlog!$A$2:$A$300,MATCH("To Do|35",Backlog!$AL$2:$AL$300,0))&" · "&INDEX(Backlog!$D$2:$D$300,MATCH("To Do|35",Backlog!$AL$2:$AL$300,0)),"") | C40: =IFERROR(INDEX(Backlog!$A$2:$A$300,MATCH("In Progress|35",Backlog!$AL$2:$AL$300,0))&" · "&INDEX(Backlog!$D$2:$D$300,MATCH("In Progress|35",Backlog!$AL$2:$AL$300,0)),"") | D40: =IFERROR(INDEX(Backlog!$A$2:$A$300,MATCH("In Review|35",Backlog!$AL$2:$AL$300,0))&" · "&INDEX(Backlog!$D$2:$D$300,MATCH("In Review|35",Backlog!$AL$2:$AL$300,0)),"") | E40: =IFERROR(INDEX(Backlog!$A$2:$A$300,MATCH("Blocked|35",Backlog!$AL$2:$AL$300,0))&" · "&INDEX(Backlog!$D$2:$D$300,MATCH("Blocked|35",Backlog!$AL$2:$AL$300,0)),"") | F40: =IFERROR(INDEX(Backlog!$A$2:$A$300,MATCH("Done|35",Backlog!$AL$2:$AL$300,0))&" · "&INDEX(Backlog!$D$2:$D$300,MATCH("Done|35",Backlog!$AL$2:$AL$300,0)),"")
B41: =IFERROR(INDEX(Backlog!$A$2:$A$300,MATCH("To Do|36",Backlog!$AL$2:$AL$300,0))&" · "&INDEX(Backlog!$D$2:$D$300,MATCH("To Do|36",Backlog!$AL$2:$AL$300,0)),"") | C41: =IFERROR(INDEX(Backlog!$A$2:$A$300,MATCH("In Progress|36",Backlog!$AL$2:$AL$300,0))&" · "&INDEX(Backlog!$D$2:$D$300,MATCH("In Progress|36",Backlog!$AL$2:$AL$300,0)),"") | D41: =IFERROR(INDEX(Backlog!$A$2:$A$300,MATCH("In Review|36",Backlog!$AL$2:$AL$300,0))&" · "&INDEX(Backlog!$D$2:$D$300,MATCH("In Review|36",Backlog!$AL$2:$AL$300,0)),"") | E41: =IFERROR(INDEX(Backlog!$A$2:$A$300,MATCH("Blocked|36",Backlog!$AL$2:$AL$300,0))&" · "&INDEX(Backlog!$D$2:$D$300,MATCH("Blocked|36",Backlog!$AL$2:$AL$300,0)),"") | F41: =IFERROR(INDEX(Backlog!$A$2:$A$300,MATCH("Done|36",Backlog!$AL$2:$AL$300,0))&" · "&INDEX(Backlog!$D$2:$D$300,MATCH("Done|36",Backlog!$AL$2:$AL$300,0)),"")
B42: =IFERROR(INDEX(Backlog!$A$2:$A$300,MATCH("To Do|37",Backlog!$AL$2:$AL$300,0))&" · "&INDEX(Backlog!$D$2:$D$300,MATCH("To Do|37",Backlog!$AL$2:$AL$300,0)),"") | C42: =IFERROR(INDEX(Backlog!$A$2:$A$300,MATCH("In Progress|37",Backlog!$AL$2:$AL$300,0))&" · "&INDEX(Backlog!$D$2:$D$300,MATCH("In Progress|37",Backlog!$AL$2:$AL$300,0)),"") | D42: =IFERROR(INDEX(Backlog!$A$2:$A$300,MATCH("In Review|37",Backlog!$AL$2:$AL$300,0))&" · "&INDEX(Backlog!$D$2:$D$300,MATCH("In Review|37",Backlog!$AL$2:$AL$300,0)),"") | E42: =IFERROR(INDEX(Backlog!$A$2:$A$300,MATCH("Blocked|37",Backlog!$AL$2:$AL$300,0))&" · "&INDEX(Backlog!$D$2:$D$300,MATCH("Blocked|37",Backlog!$AL$2:$AL$300,0)),"") | F42: =IFERROR(INDEX(Backlog!$A$2:$A$300,MATCH("Done|37",Backlog!$AL$2:$AL$300,0))&" · "&INDEX(Backlog!$D$2:$D$300,MATCH("Done|37",Backlog!$AL$2:$AL$300,0)),"")
B43: =IFERROR(INDEX(Backlog!$A$2:$A$300,MATCH("To Do|38",Backlog!$AL$2:$AL$300,0))&" · "&INDEX(Backlog!$D$2:$D$300,MATCH("To Do|38",Backlog!$AL$2:$AL$300,0)),"") | C43: =IFERROR(INDEX(Backlog!$A$2:$A$300,MATCH("In Progress|38",Backlog!$AL$2:$AL$300,0))&" · "&INDEX(Backlog!$D$2:$D$300,MATCH("In Progress|38",Backlog!$AL$2:$AL$300,0)),"") | D43: =IFERROR(INDEX(Backlog!$A$2:$A$300,MATCH("In Review|38",Backlog!$AL$2:$AL$300,0))&" · "&INDEX(Backlog!$D$2:$D$300,MATCH("In Review|38",Backlog!$AL$2:$AL$300,0)),"") | E43: =IFERROR(INDEX(Backlog!$A$2:$A$300,MATCH("Blocked|38",Backlog!$AL$2:$AL$300,0))&" · "&INDEX(Backlog!$D$2:$D$300,MATCH("Blocked|38",Backlog!$AL$2:$AL$300,0)),"") | F43: =IFERROR(INDEX(Backlog!$A$2:$A$300,MATCH("Done|38",Backlog!$AL$2:$AL$300,0))&" · "&INDEX(Backlog!$D$2:$D$300,MATCH("Done|38",Backlog!$AL$2:$AL$300,0)),"")
B44: =IFERROR(INDEX(Backlog!$A$2:$A$300,MATCH("To Do|39",Backlog!$AL$2:$AL$300,0))&" · "&INDEX(Backlog!$D$2:$D$300,MATCH("To Do|39",Backlog!$AL$2:$AL$300,0)),"") | C44: =IFERROR(INDEX(Backlog!$A$2:$A$300,MATCH("In Progress|39",Backlog!$AL$2:$AL$300,0))&" · "&INDEX(Backlog!$D$2:$D$300,MATCH("In Progress|39",Backlog!$AL$2:$AL$300,0)),"") | D44: =IFERROR(INDEX(Backlog!$A$2:$A$300,MATCH("In Review|39",Backlog!$AL$2:$AL$300,0))&" · "&INDEX(Backlog!$D$2:$D$300,MATCH("In Review|39",Backlog!$AL$2:$AL$300,0)),"") | E44: =IFERROR(INDEX(Backlog!$A$2:$A$300,MATCH("Blocked|39",Backlog!$AL$2:$AL$300,0))&" · "&INDEX(Backlog!$D$2:$D$300,MATCH("Blocked|39",Backlog!$AL$2:$AL$300,0)),"") | F44: =IFERROR(INDEX(Backlog!$A$2:$A$300,MATCH("Done|39",Backlog!$AL$2:$AL$300,0))&" · "&INDEX(Backlog!$D$2:$D$300,MATCH("Done|39",Backlog!$AL$2:$AL$300,0)),"")
B45: =IFERROR(INDEX(Backlog!$A$2:$A$300,MATCH("To Do|40",Backlog!$AL$2:$AL$300,0))&" · "&INDEX(Backlog!$D$2:$D$300,MATCH("To Do|40",Backlog!$AL$2:$AL$300,0)),"") | C45: =IFERROR(INDEX(Backlog!$A$2:$A$300,MATCH("In Progress|40",Backlog!$AL$2:$AL$300,0))&" · "&INDEX(Backlog!$D$2:$D$300,MATCH("In Progress|40",Backlog!$AL$2:$AL$300,0)),"") | D45: =IFERROR(INDEX(Backlog!$A$2:$A$300,MATCH("In Review|40",Backlog!$AL$2:$AL$300,0))&" · "&INDEX(Backlog!$D$2:$D$300,MATCH("In Review|40",Backlog!$AL$2:$AL$300,0)),"") | E45: =IFERROR(INDEX(Backlog!$A$2:$A$300,MATCH("Blocked|40",Backlog!$AL$2:$AL$300,0))&" · "&INDEX(Backlog!$D$2:$D$300,MATCH("Blocked|40",Backlog!$AL$2:$AL$300,0)),"") | F45: =IFERROR(INDEX(Backlog!$A$2:$A$300,MATCH("Done|40",Backlog!$AL$2:$AL$300,0))&" · "&INDEX(Backlog!$D$2:$D$300,MATCH("Done|40",Backlog!$AL$2:$AL$300,0)),"")
B46: =IFERROR(INDEX(Backlog!$A$2:$A$300,MATCH("To Do|41",Backlog!$AL$2:$AL$300,0))&" · "&INDEX(Backlog!$D$2:$D$300,MATCH("To Do|41",Backlog!$AL$2:$AL$300,0)),"") | C46: =IFERROR(INDEX(Backlog!$A$2:$A$300,MATCH("In Progress|41",Backlog!$AL$2:$AL$300,0))&" · "&INDEX(Backlog!$D$2:$D$300,MATCH("In Progress|41",Backlog!$AL$2:$AL$300,0)),"") | D46: =IFERROR(INDEX(Backlog!$A$2:$A$300,MATCH("In Review|41",Backlog!$AL$2:$AL$300,0))&" · "&INDEX(Backlog!$D$2:$D$300,MATCH("In Review|41",Backlog!$AL$2:$AL$300,0)),"") | E46: =IFERROR(INDEX(Backlog!$A$2:$A$300,MATCH("Blocked|41",Backlog!$AL$2:$AL$300,0))&" · "&INDEX(Backlog!$D$2:$D$300,MATCH("Blocked|41",Backlog!$AL$2:$AL$300,0)),"") | F46: =IFERROR(INDEX(Backlog!$A$2:$A$300,MATCH("Done|41",Backlog!$AL$2:$AL$300,0))&" · "&INDEX(Backlog!$D$2:$D$300,MATCH("Done|41",Backlog!$AL$2:$AL$300,0)),"")
B47: =IFERROR(INDEX(Backlog!$A$2:$A$300,MATCH("To Do|42",Backlog!$AL$2:$AL$300,0))&" · "&INDEX(Backlog!$D$2:$D$300,MATCH("To Do|42",Backlog!$AL$2:$AL$300,0)),"") | C47: =IFERROR(INDEX(Backlog!$A$2:$A$300,MATCH("In Progress|42",Backlog!$AL$2:$AL$300,0))&" · "&INDEX(Backlog!$D$2:$D$300,MATCH("In Progress|42",Backlog!$AL$2:$AL$300,0)),"") | D47: =IFERROR(INDEX(Backlog!$A$2:$A$300,MATCH("In Review|42",Backlog!$AL$2:$AL$300,0))&" · "&INDEX(Backlog!$D$2:$D$300,MATCH("In Review|42",Backlog!$AL$2:$AL$300,0)),"") | E47: =IFERROR(INDEX(Backlog!$A$2:$A$300,MATCH("Blocked|42",Backlog!$AL$2:$AL$300,0))&" · "&INDEX(Backlog!$D$2:$D$300,MATCH("Blocked|42",Backlog!$AL$2:$AL$300,0)),"") | F47: =IFERROR(INDEX(Backlog!$A$2:$A$300,MATCH("Done|42",Backlog!$AL$2:$AL$300,0))&" · "&INDEX(Backlog!$D$2:$D$300,MATCH("Done|42",Backlog!$AL$2:$AL$300,0)),"")
B48: =IFERROR(INDEX(Backlog!$A$2:$A$300,MATCH("To Do|43",Backlog!$AL$2:$AL$300,0))&" · "&INDEX(Backlog!$D$2:$D$300,MATCH("To Do|43",Backlog!$AL$2:$AL$300,0)),"") | C48: =IFERROR(INDEX(Backlog!$A$2:$A$300,MATCH("In Progress|43",Backlog!$AL$2:$AL$300,0))&" · "&INDEX(Backlog!$D$2:$D$300,MATCH("In Progress|43",Backlog!$AL$2:$AL$300,0)),"") | D48: =IFERROR(INDEX(Backlog!$A$2:$A$300,MATCH("In Review|43",Backlog!$AL$2:$AL$300,0))&" · "&INDEX(Backlog!$D$2:$D$300,MATCH("In Review|43",Backlog!$AL$2:$AL$300,0)),"") | E48: =IFERROR(INDEX(Backlog!$A$2:$A$300,MATCH("Blocked|43",Backlog!$AL$2:$AL$300,0))&" · "&INDEX(Backlog!$D$2:$D$300,MATCH("Blocked|43",Backlog!$AL$2:$AL$300,0)),"") | F48: =IFERROR(INDEX(Backlog!$A$2:$A$300,MATCH("Done|43",Backlog!$AL$2:$AL$300,0))&" · "&INDEX(Backlog!$D$2:$D$300,MATCH("Done|43",Backlog!$AL$2:$AL$300,0)),"")
B49: =IFERROR(INDEX(Backlog!$A$2:$A$300,MATCH("To Do|44",Backlog!$AL$2:$AL$300,0))&" · "&INDEX(Backlog!$D$2:$D$300,MATCH("To Do|44",Backlog!$AL$2:$AL$300,0)),"") | C49: =IFERROR(INDEX(Backlog!$A$2:$A$300,MATCH("In Progress|44",Backlog!$AL$2:$AL$300,0))&" · "&INDEX(Backlog!$D$2:$D$300,MATCH("In Progress|44",Backlog!$AL$2:$AL$300,0)),"") | D49: =IFERROR(INDEX(Backlog!$A$2:$A$300,MATCH("In Review|44",Backlog!$AL$2:$AL$300,0))&" · "&INDEX(Backlog!$D$2:$D$300,MATCH("In Review|44",Backlog!$AL$2:$AL$300,0)),"") | E49: =IFERROR(INDEX(Backlog!$A$2:$A$300,MATCH("Blocked|44",Backlog!$AL$2:$AL$300,0))&" · "&INDEX(Backlog!$D$2:$D$300,MATCH("Blocked|44",Backlog!$AL$2:$AL$300,0)),"") | F49: =IFERROR(INDEX(Backlog!$A$2:$A$300,MATCH("Done|44",Backlog!$AL$2:$AL$300,0))&" · "&INDEX(Backlog!$D$2:$D$300,MATCH("Done|44",Backlog!$AL$2:$AL$300,0)),"")
B50: =IFERROR(INDEX(Backlog!$A$2:$A$300,MATCH("To Do|45",Backlog!$AL$2:$AL$300,0))&" · "&INDEX(Backlog!$D$2:$D$300,MATCH("To Do|45",Backlog!$AL$2:$AL$300,0)),"") | C50: =IFERROR(INDEX(Backlog!$A$2:$A$300,MATCH("In Progress|45",Backlog!$AL$2:$AL$300,0))&" · "&INDEX(Backlog!$D$2:$D$300,MATCH("In Progress|45",Backlog!$AL$2:$AL$300,0)),"") | D50: =IFERROR(INDEX(Backlog!$A$2:$A$300,MATCH("In Review|45",Backlog!$AL$2:$AL$300,0))&" · "&INDEX(Backlog!$D$2:$D$300,MATCH("In Review|45",Backlog!$AL$2:$AL$300,0)),"") | E50: =IFERROR(INDEX(Backlog!$A$2:$A$300,MATCH("Blocked|45",Backlog!$AL$2:$AL$300,0))&" · "&INDEX(Backlog!$D$2:$D$300,MATCH("Blocked|45",Backlog!$AL$2:$AL$300,0)),"") | F50: =IFERROR(INDEX(Backlog!$A$2:$A$300,MATCH("Done|45",Backlog!$AL$2:$AL$300,0))&" · "&INDEX(Backlog!$D$2:$D$300,MATCH("Done|45",Backlog!$AL$2:$AL$300,0)),"")
B51: =IFERROR(INDEX(Backlog!$A$2:$A$300,MATCH("To Do|46",Backlog!$AL$2:$AL$300,0))&" · "&INDEX(Backlog!$D$2:$D$300,MATCH("To Do|46",Backlog!$AL$2:$AL$300,0)),"") | C51: =IFERROR(INDEX(Backlog!$A$2:$A$300,MATCH("In Progress|46",Backlog!$AL$2:$AL$300,0))&" · "&INDEX(Backlog!$D$2:$D$300,MATCH("In Progress|46",Backlog!$AL$2:$AL$300,0)),"") | D51: =IFERROR(INDEX(Backlog!$A$2:$A$300,MATCH("In Review|46",Backlog!$AL$2:$AL$300,0))&" · "&INDEX(Backlog!$D$2:$D$300,MATCH("In Review|46",Backlog!$AL$2:$AL$300,0)),"") | E51: =IFERROR(INDEX(Backlog!$A$2:$A$300,MATCH("Blocked|46",Backlog!$AL$2:$AL$300,0))&" · "&INDEX(Backlog!$D$2:$D$300,MATCH("Blocked|46",Backlog!$AL$2:$AL$300,0)),"") | F51: =IFERROR(INDEX(Backlog!$A$2:$A$300,MATCH("Done|46",Backlog!$AL$2:$AL$300,0))&" · "&INDEX(Backlog!$D$2:$D$300,MATCH("Done|46",Backlog!$AL$2:$AL$300,0)),"")
B52: =IFERROR(INDEX(Backlog!$A$2:$A$300,MATCH("To Do|47",Backlog!$AL$2:$AL$300,0))&" · "&INDEX(Backlog!$D$2:$D$300,MATCH("To Do|47",Backlog!$AL$2:$AL$300,0)),"") | C52: =IFERROR(INDEX(Backlog!$A$2:$A$300,MATCH("In Progress|47",Backlog!$AL$2:$AL$300,0))&" · "&INDEX(Backlog!$D$2:$D$300,MATCH("In Progress|47",Backlog!$AL$2:$AL$300,0)),"") | D52: =IFERROR(INDEX(Backlog!$A$2:$A$300,MATCH("In Review|47",Backlog!$AL$2:$AL$300,0))&" · "&INDEX(Backlog!$D$2:$D$300,MATCH("In Review|47",Backlog!$AL$2:$AL$300,0)),"") | E52: =IFERROR(INDEX(Backlog!$A$2:$A$300,MATCH("Blocked|47",Backlog!$AL$2:$AL$300,0))&" · "&INDEX(Backlog!$D$2:$D$300,MATCH("Blocked|47",Backlog!$AL$2:$AL$300,0)),"") | F52: =IFERROR(INDEX(Backlog!$A$2:$A$300,MATCH("Done|47",Backlog!$AL$2:$AL$300,0))&" · "&INDEX(Backlog!$D$2:$D$300,MATCH("Done|47",Backlog!$AL$2:$AL$300,0)),"")
B53: =IFERROR(INDEX(Backlog!$A$2:$A$300,MATCH("To Do|48",Backlog!$AL$2:$AL$300,0))&" · "&INDEX(Backlog!$D$2:$D$300,MATCH("To Do|48",Backlog!$AL$2:$AL$300,0)),"") | C53: =IFERROR(INDEX(Backlog!$A$2:$A$300,MATCH("In Progress|48",Backlog!$AL$2:$AL$300,0))&" · "&INDEX(Backlog!$D$2:$D$300,MATCH("In Progress|48",Backlog!$AL$2:$AL$300,0)),"") | D53: =IFERROR(INDEX(Backlog!$A$2:$A$300,MATCH("In Review|48",Backlog!$AL$2:$AL$300,0))&" · "&INDEX(Backlog!$D$2:$D$300,MATCH("In Review|48",Backlog!$AL$2:$AL$300,0)),"") | E53: =IFERROR(INDEX(Backlog!$A$2:$A$300,MATCH("Blocked|48",Backlog!$AL$2:$AL$300,0))&" · "&INDEX(Backlog!$D$2:$D$300,MATCH("Blocked|48",Backlog!$AL$2:$AL$300,0)),"") | F53: =IFERROR(INDEX(Backlog!$A$2:$A$300,MATCH("Done|48",Backlog!$AL$2:$AL$300,0))&" · "&INDEX(Backlog!$D$2:$D$300,MATCH("Done|48",Backlog!$AL$2:$AL$300,0)),"")
B54: =IFERROR(INDEX(Backlog!$A$2:$A$300,MATCH("To Do|49",Backlog!$AL$2:$AL$300,0))&" · "&INDEX(Backlog!$D$2:$D$300,MATCH("To Do|49",Backlog!$AL$2:$AL$300,0)),"") | C54: =IFERROR(INDEX(Backlog!$A$2:$A$300,MATCH("In Progress|49",Backlog!$AL$2:$AL$300,0))&" · "&INDEX(Backlog!$D$2:$D$300,MATCH("In Progress|49",Backlog!$AL$2:$AL$300,0)),"") | D54: =IFERROR(INDEX(Backlog!$A$2:$A$300,MATCH("In Review|49",Backlog!$AL$2:$AL$300,0))&" · "&INDEX(Backlog!$D$2:$D$300,MATCH("In Review|49",Backlog!$AL$2:$AL$300,0)),"") | E54: =IFERROR(INDEX(Backlog!$A$2:$A$300,MATCH("Blocked|49",Backlog!$AL$2:$AL$300,0))&" · "&INDEX(Backlog!$D$2:$D$300,MATCH("Blocked|49",Backlog!$AL$2:$AL$300,0)),"") | F54: =IFERROR(INDEX(Backlog!$A$2:$A$300,MATCH("Done|49",Backlog!$AL$2:$AL$300,0))&" · "&INDEX(Backlog!$D$2:$D$300,MATCH("Done|49",Backlog!$AL$2:$AL$300,0)),"")
B55: =IFERROR(INDEX(Backlog!$A$2:$A$300,MATCH("To Do|50",Backlog!$AL$2:$AL$300,0))&" · "&INDEX(Backlog!$D$2:$D$300,MATCH("To Do|50",Backlog!$AL$2:$AL$300,0)),"") | C55: =IFERROR(INDEX(Backlog!$A$2:$A$300,MATCH("In Progress|50",Backlog!$AL$2:$AL$300,0))&" · "&INDEX(Backlog!$D$2:$D$300,MATCH("In Progress|50",Backlog!$AL$2:$AL$300,0)),"") | D55: =IFERROR(INDEX(Backlog!$A$2:$A$300,MATCH("In Review|50",Backlog!$AL$2:$AL$300,0))&" · "&INDEX(Backlog!$D$2:$D$300,MATCH("In Review|50",Backlog!$AL$2:$AL$300,0)),"") | E55: =IFERROR(INDEX(Backlog!$A$2:$A$300,MATCH("Blocked|50",Backlog!$AL$2:$AL$300,0))&" · "&INDEX(Backlog!$D$2:$D$300,MATCH("Blocked|50",Backlog!$AL$2:$AL$300,0)),"") | F55: =IFERROR(INDEX(Backlog!$A$2:$A$300,MATCH("Done|50",Backlog!$AL$2:$AL$300,0))&" · "&INDEX(Backlog!$D$2:$D$300,MATCH("Done|50",Backlog!$AL$2:$AL$300,0)),"")
B56: =IFERROR(INDEX(Backlog!$A$2:$A$300,MATCH("To Do|51",Backlog!$AL$2:$AL$300,0))&" · "&INDEX(Backlog!$D$2:$D$300,MATCH("To Do|51",Backlog!$AL$2:$AL$300,0)),"") | C56: =IFERROR(INDEX(Backlog!$A$2:$A$300,MATCH("In Progress|51",Backlog!$AL$2:$AL$300,0))&" · "&INDEX(Backlog!$D$2:$D$300,MATCH("In Progress|51",Backlog!$AL$2:$AL$300,0)),"") | D56: =IFERROR(INDEX(Backlog!$A$2:$A$300,MATCH("In Review|51",Backlog!$AL$2:$AL$300,0))&" · "&INDEX(Backlog!$D$2:$D$300,MATCH("In Review|51",Backlog!$AL$2:$AL$300,0)),"") | E56: =IFERROR(INDEX(Backlog!$A$2:$A$300,MATCH("Blocked|51",Backlog!$AL$2:$AL$300,0))&" · "&INDEX(Backlog!$D$2:$D$300,MATCH("Blocked|51",Backlog!$AL$2:$AL$300,0)),"") | F56: =IFERROR(INDEX(Backlog!$A$2:$A$300,MATCH("Done|51",Backlog!$AL$2:$AL$300,0))&" · "&INDEX(Backlog!$D$2:$D$300,MATCH("Done|51",Backlog!$AL$2:$AL$300,0)),"")
B57: =IFERROR(INDEX(Backlog!$A$2:$A$300,MATCH("To Do|52",Backlog!$AL$2:$AL$300,0))&" · "&INDEX(Backlog!$D$2:$D$300,MATCH("To Do|52",Backlog!$AL$2:$AL$300,0)),"") | C57: =IFERROR(INDEX(Backlog!$A$2:$A$300,MATCH("In Progress|52",Backlog!$AL$2:$AL$300,0))&" · "&INDEX(Backlog!$D$2:$D$300,MATCH("In Progress|52",Backlog!$AL$2:$AL$300,0)),"") | D57: =IFERROR(INDEX(Backlog!$A$2:$A$300,MATCH("In Review|52",Backlog!$AL$2:$AL$300,0))&" · "&INDEX(Backlog!$D$2:$D$300,MATCH("In Review|52",Backlog!$AL$2:$AL$300,0)),"") | E57: =IFERROR(INDEX(Backlog!$A$2:$A$300,MATCH("Blocked|52",Backlog!$AL$2:$AL$300,0))&" · "&INDEX(Backlog!$D$2:$D$300,MATCH("Blocked|52",Backlog!$AL$2:$AL$300,0)),"") | F57: =IFERROR(INDEX(Backlog!$A$2:$A$300,MATCH("Done|52",Backlog!$AL$2:$AL$300,0))&" · "&INDEX(Backlog!$D$2:$D$300,MATCH("Done|52",Backlog!$AL$2:$AL$300,0)),"")
B58: =IFERROR(INDEX(Backlog!$A$2:$A$300,MATCH("To Do|53",Backlog!$AL$2:$AL$300,0))&" · "&INDEX(Backlog!$D$2:$D$300,MATCH("To Do|53",Backlog!$AL$2:$AL$300,0)),"") | C58: =IFERROR(INDEX(Backlog!$A$2:$A$300,MATCH("In Progress|53",Backlog!$AL$2:$AL$300,0))&" · "&INDEX(Backlog!$D$2:$D$300,MATCH("In Progress|53",Backlog!$AL$2:$AL$300,0)),"") | D58: =IFERROR(INDEX(Backlog!$A$2:$A$300,MATCH("In Review|53",Backlog!$AL$2:$AL$300,0))&" · "&INDEX(Backlog!$D$2:$D$300,MATCH("In Review|53",Backlog!$AL$2:$AL$300,0)),"") | E58: =IFERROR(INDEX(Backlog!$A$2:$A$300,MATCH("Blocked|53",Backlog!$AL$2:$AL$300,0))&" · "&INDEX(Backlog!$D$2:$D$300,MATCH("Blocked|53",Backlog!$AL$2:$AL$300,0)),"") | F58: =IFERROR(INDEX(Backlog!$A$2:$A$300,MATCH("Done|53",Backlog!$AL$2:$AL$300,0))&" · "&INDEX(Backlog!$D$2:$D$300,MATCH("Done|53",Backlog!$AL$2:$AL$300,0)),"")
B59: =IFERROR(INDEX(Backlog!$A$2:$A$300,MATCH("To Do|54",Backlog!$AL$2:$AL$300,0))&" · "&INDEX(Backlog!$D$2:$D$300,MATCH("To Do|54",Backlog!$AL$2:$AL$300,0)),"") | C59: =IFERROR(INDEX(Backlog!$A$2:$A$300,MATCH("In Progress|54",Backlog!$AL$2:$AL$300,0))&" · "&INDEX(Backlog!$D$2:$D$300,MATCH("In Progress|54",Backlog!$AL$2:$AL$300,0)),"") | D59: =IFERROR(INDEX(Backlog!$A$2:$A$300,MATCH("In Review|54",Backlog!$AL$2:$AL$300,0))&" · "&INDEX(Backlog!$D$2:$D$300,MATCH("In Review|54",Backlog!$AL$2:$AL$300,0)),"") | E59: =IFERROR(INDEX(Backlog!$A$2:$A$300,MATCH("Blocked|54",Backlog!$AL$2:$AL$300,0))&" · "&INDEX(Backlog!$D$2:$D$300,MATCH("Blocked|54",Backlog!$AL$2:$AL$300,0)),"") | F59: =IFERROR(INDEX(Backlog!$A$2:$A$300,MATCH("Done|54",Backlog!$AL$2:$AL$300,0))&" · "&INDEX(Backlog!$D$2:$D$300,MATCH("Done|54",Backlog!$AL$2:$AL$300,0)),"")
B60: =IFERROR(INDEX(Backlog!$A$2:$A$300,MATCH("To Do|55",Backlog!$AL$2:$AL$300,0))&" · "&INDEX(Backlog!$D$2:$D$300,MATCH("To Do|55",Backlog!$AL$2:$AL$300,0)),"") | C60: =IFERROR(INDEX(Backlog!$A$2:$A$300,MATCH("In Progress|55",Backlog!$AL$2:$AL$300,0))&" · "&INDEX(Backlog!$D$2:$D$300,MATCH("In Progress|55",Backlog!$AL$2:$AL$300,0)),"") | D60: =IFERROR(INDEX(Backlog!$A$2:$A$300,MATCH("In Review|55",Backlog!$AL$2:$AL$300,0))&" · "&INDEX(Backlog!$D$2:$D$300,MATCH("In Review|55",Backlog!$AL$2:$AL$300,0)),"") | E60: =IFERROR(INDEX(Backlog!$A$2:$A$300,MATCH("Blocked|55",Backlog!$AL$2:$AL$300,0))&" · "&INDEX(Backlog!$D$2:$D$300,MATCH("Blocked|55",Backlog!$AL$2:$AL$300,0)),"") | F60: =IFERROR(INDEX(Backlog!$A$2:$A$300,MATCH("Done|55",Backlog!$AL$2:$AL$300,0))&" · "&INDEX(Backlog!$D$2:$D$300,MATCH("Done|55",Backlog!$AL$2:$AL$300,0)),"")
B61: =IFERROR(INDEX(Backlog!$A$2:$A$300,MATCH("To Do|56",Backlog!$AL$2:$AL$300,0))&" · "&INDEX(Backlog!$D$2:$D$300,MATCH("To Do|56",Backlog!$AL$2:$AL$300,0)),"") | C61: =IFERROR(INDEX(Backlog!$A$2:$A$300,MATCH("In Progress|56",Backlog!$AL$2:$AL$300,0))&" · "&INDEX(Backlog!$D$2:$D$300,MATCH("In Progress|56",Backlog!$AL$2:$AL$300,0)),"") | D61: =IFERROR(INDEX(Backlog!$A$2:$A$300,MATCH("In Review|56",Backlog!$AL$2:$AL$300,0))&" · "&INDEX(Backlog!$D$2:$D$300,MATCH("In Review|56",Backlog!$AL$2:$AL$300,0)),"") | E61: =IFERROR(INDEX(Backlog!$A$2:$A$300,MATCH("Blocked|56",Backlog!$AL$2:$AL$300,0))&" · "&INDEX(Backlog!$D$2:$D$300,MATCH("Blocked|56",Backlog!$AL$2:$AL$300,0)),"") | F61: =IFERROR(INDEX(Backlog!$A$2:$A$300,MATCH("Done|56",Backlog!$AL$2:$AL$300,0))&" · "&INDEX(Backlog!$D$2:$D$300,MATCH("Done|56",Backlog!$AL$2:$AL$300,0)),"")
B62: =IFERROR(INDEX(Backlog!$A$2:$A$300,MATCH("To Do|57",Backlog!$AL$2:$AL$300,0))&" · "&INDEX(Backlog!$D$2:$D$300,MATCH("To Do|57",Backlog!$AL$2:$AL$300,0)),"") | C62: =IFERROR(INDEX(Backlog!$A$2:$A$300,MATCH("In Progress|57",Backlog!$AL$2:$AL$300,0))&" · "&INDEX(Backlog!$D$2:$D$300,MATCH("In Progress|57",Backlog!$AL$2:$AL$300,0)),"") | D62: =IFERROR(INDEX(Backlog!$A$2:$A$300,MATCH("In Review|57",Backlog!$AL$2:$AL$300,0))&" · "&INDEX(Backlog!$D$2:$D$300,MATCH("In Review|57",Backlog!$AL$2:$AL$300,0)),"") | E62: =IFERROR(INDEX(Backlog!$A$2:$A$300,MATCH("Blocked|57",Backlog!$AL$2:$AL$300,0))&" · "&INDEX(Backlog!$D$2:$D$300,MATCH("Blocked|57",Backlog!$AL$2:$AL$300,0)),"") | F62: =IFERROR(INDEX(Backlog!$A$2:$A$300,MATCH("Done|57",Backlog!$AL$2:$AL$300,0))&" · "&INDEX(Backlog!$D$2:$D$300,MATCH("Done|57",Backlog!$AL$2:$AL$300,0)),"")
B63: =IFERROR(INDEX(Backlog!$A$2:$A$300,MATCH("To Do|58",Backlog!$AL$2:$AL$300,0))&" · "&INDEX(Backlog!$D$2:$D$300,MATCH("To Do|58",Backlog!$AL$2:$AL$300,0)),"") | C63: =IFERROR(INDEX(Backlog!$A$2:$A$300,MATCH("In Progress|58",Backlog!$AL$2:$AL$300,0))&" · "&INDEX(Backlog!$D$2:$D$300,MATCH("In Progress|58",Backlog!$AL$2:$AL$300,0)),"") | D63: =IFERROR(INDEX(Backlog!$A$2:$A$300,MATCH("In Review|58",Backlog!$AL$2:$AL$300,0))&" · "&INDEX(Backlog!$D$2:$D$300,MATCH("In Review|58",Backlog!$AL$2:$AL$300,0)),"") | E63: =IFERROR(INDEX(Backlog!$A$2:$A$300,MATCH("Blocked|58",Backlog!$AL$2:$AL$300,0))&" · "&INDEX(Backlog!$D$2:$D$300,MATCH("Blocked|58",Backlog!$AL$2:$AL$300,0)),"") | F63: =IFERROR(INDEX(Backlog!$A$2:$A$300,MATCH("Done|58",Backlog!$AL$2:$AL$300,0))&" · "&INDEX(Backlog!$D$2:$D$300,MATCH("Done|58",Backlog!$AL$2:$AL$300,0)),"")
B64: =IFERROR(INDEX(Backlog!$A$2:$A$300,MATCH("To Do|59",Backlog!$AL$2:$AL$300,0))&" · "&INDEX(Backlog!$D$2:$D$300,MATCH("To Do|59",Backlog!$AL$2:$AL$300,0)),"") | C64: =IFERROR(INDEX(Backlog!$A$2:$A$300,MATCH("In Progress|59",Backlog!$AL$2:$AL$300,0))&" · "&INDEX(Backlog!$D$2:$D$300,MATCH("In Progress|59",Backlog!$AL$2:$AL$300,0)),"") | D64: =IFERROR(INDEX(Backlog!$A$2:$A$300,MATCH("In Review|59",Backlog!$AL$2:$AL$300,0))&" · "&INDEX(Backlog!$D$2:$D$300,MATCH("In Review|59",Backlog!$AL$2:$AL$300,0)),"") | E64: =IFERROR(INDEX(Backlog!$A$2:$A$300,MATCH("Blocked|59",Backlog!$AL$2:$AL$300,0))&" · "&INDEX(Backlog!$D$2:$D$300,MATCH("Blocked|59",Backlog!$AL$2:$AL$300,0)),"") | F64: =IFERROR(INDEX(Backlog!$A$2:$A$300,MATCH("Done|59",Backlog!$AL$2:$AL$300,0))&" · "&INDEX(Backlog!$D$2:$D$300,MATCH("Done|59",Backlog!$AL$2:$AL$300,0)),"")
B65: =IFERROR(INDEX(Backlog!$A$2:$A$300,MATCH("To Do|60",Backlog!$AL$2:$AL$300,0))&" · "&INDEX(Backlog!$D$2:$D$300,MATCH("To Do|60",Backlog!$AL$2:$AL$300,0)),"") | C65: =IFERROR(INDEX(Backlog!$A$2:$A$300,MATCH("In Progress|60",Backlog!$AL$2:$AL$300,0))&" · "&INDEX(Backlog!$D$2:$D$300,MATCH("In Progress|60",Backlog!$AL$2:$AL$300,0)),"") | D65: =IFERROR(INDEX(Backlog!$A$2:$A$300,MATCH("In Review|60",Backlog!$AL$2:$AL$300,0))&" · "&INDEX(Backlog!$D$2:$D$300,MATCH("In Review|60",Backlog!$AL$2:$AL$300,0)),"") | E65: =IFERROR(INDEX(Backlog!$A$2:$A$300,MATCH("Blocked|60",Backlog!$AL$2:$AL$300,0))&" · "&INDEX(Backlog!$D$2:$D$300,MATCH("Blocked|60",Backlog!$AL$2:$AL$300,0)),"") | F65: =IFERROR(INDEX(Backlog!$A$2:$A$300,MATCH("Done|60",Backlog!$AL$2:$AL$300,0))&" · "&INDEX(Backlog!$D$2:$D$300,MATCH("Done|60",Backlog!$AL$2:$AL$300,0)),"")
B66: =IFERROR(INDEX(Backlog!$A$2:$A$300,MATCH("To Do|61",Backlog!$AL$2:$AL$300,0))&" · "&INDEX(Backlog!$D$2:$D$300,MATCH("To Do|61",Backlog!$AL$2:$AL$300,0)),"") | C66: =IFERROR(INDEX(Backlog!$A$2:$A$300,MATCH("In Progress|61",Backlog!$AL$2:$AL$300,0))&" · "&INDEX(Backlog!$D$2:$D$300,MATCH("In Progress|61",Backlog!$AL$2:$AL$300,0)),"") | D66: =IFERROR(INDEX(Backlog!$A$2:$A$300,MATCH("In Review|61",Backlog!$AL$2:$AL$300,0))&" · "&INDEX(Backlog!$D$2:$D$300,MATCH("In Review|61",Backlog!$AL$2:$AL$300,0)),"") | E66: =IFERROR(INDEX(Backlog!$A$2:$A$300,MATCH("Blocked|61",Backlog!$AL$2:$AL$300,0))&" · "&INDEX(Backlog!$D$2:$D$300,MATCH("Blocked|61",Backlog!$AL$2:$AL$300,0)),"") | F66: =IFERROR(INDEX(Backlog!$A$2:$A$300,MATCH("Done|61",Backlog!$AL$2:$AL$300,0))&" · "&INDEX(Backlog!$D$2:$D$300,MATCH("Done|61",Backlog!$AL$2:$AL$300,0)),"")
B67: =IFERROR(INDEX(Backlog!$A$2:$A$300,MATCH("To Do|62",Backlog!$AL$2:$AL$300,0))&" · "&INDEX(Backlog!$D$2:$D$300,MATCH("To Do|62",Backlog!$AL$2:$AL$300,0)),"") | C67: =IFERROR(INDEX(Backlog!$A$2:$A$300,MATCH("In Progress|62",Backlog!$AL$2:$AL$300,0))&" · "&INDEX(Backlog!$D$2:$D$300,MATCH("In Progress|62",Backlog!$AL$2:$AL$300,0)),"") | D67: =IFERROR(INDEX(Backlog!$A$2:$A$300,MATCH("In Review|62",Backlog!$AL$2:$AL$300,0))&" · "&INDEX(Backlog!$D$2:$D$300,MATCH("In Review|62",Backlog!$AL$2:$AL$300,0)),"") | E67: =IFERROR(INDEX(Backlog!$A$2:$A$300,MATCH("Blocked|62",Backlog!$AL$2:$AL$300,0))&" · "&INDEX(Backlog!$D$2:$D$300,MATCH("Blocked|62",Backlog!$AL$2:$AL$300,0)),"") | F67: =IFERROR(INDEX(Backlog!$A$2:$A$300,MATCH("Done|62",Backlog!$AL$2:$AL$300,0))&" · "&INDEX(Backlog!$D$2:$D$300,MATCH("Done|62",Backlog!$AL$2:$AL$300,0)),"")
B68: =IFERROR(INDEX(Backlog!$A$2:$A$300,MATCH("To Do|63",Backlog!$AL$2:$AL$300,0))&" · "&INDEX(Backlog!$D$2:$D$300,MATCH("To Do|63",Backlog!$AL$2:$AL$300,0)),"") | C68: =IFERROR(INDEX(Backlog!$A$2:$A$300,MATCH("In Progress|63",Backlog!$AL$2:$AL$300,0))&" · "&INDEX(Backlog!$D$2:$D$300,MATCH("In Progress|63",Backlog!$AL$2:$AL$300,0)),"") | D68: =IFERROR(INDEX(Backlog!$A$2:$A$300,MATCH("In Review|63",Backlog!$AL$2:$AL$300,0))&" · "&INDEX(Backlog!$D$2:$D$300,MATCH("In Review|63",Backlog!$AL$2:$AL$300,0)),"") | E68: =IFERROR(INDEX(Backlog!$A$2:$A$300,MATCH("Blocked|63",Backlog!$AL$2:$AL$300,0))&" · "&INDEX(Backlog!$D$2:$D$300,MATCH("Blocked|63",Backlog!$AL$2:$AL$300,0)),"") | F68: =IFERROR(INDEX(Backlog!$A$2:$A$300,MATCH("Done|63",Backlog!$AL$2:$AL$300,0))&" · "&INDEX(Backlog!$D$2:$D$300,MATCH("Done|63",Backlog!$AL$2:$AL$300,0)),"")
B69: =IFERROR(INDEX(Backlog!$A$2:$A$300,MATCH("To Do|64",Backlog!$AL$2:$AL$300,0))&" · "&INDEX(Backlog!$D$2:$D$300,MATCH("To Do|64",Backlog!$AL$2:$AL$300,0)),"") | C69: =IFERROR(INDEX(Backlog!$A$2:$A$300,MATCH("In Progress|64",Backlog!$AL$2:$AL$300,0))&" · "&INDEX(Backlog!$D$2:$D$300,MATCH("In Progress|64",Backlog!$AL$2:$AL$300,0)),"") | D69: =IFERROR(INDEX(Backlog!$A$2:$A$300,MATCH("In Review|64",Backlog!$AL$2:$AL$300,0))&" · "&INDEX(Backlog!$D$2:$D$300,MATCH("In Review|64",Backlog!$AL$2:$AL$300,0)),"") | E69: =IFERROR(INDEX(Backlog!$A$2:$A$300,MATCH("Blocked|64",Backlog!$AL$2:$AL$300,0))&" · "&INDEX(Backlog!$D$2:$D$300,MATCH("Blocked|64",Backlog!$AL$2:$AL$300,0)),"") | F69: =IFERROR(INDEX(Backlog!$A$2:$A$300,MATCH("Done|64",Backlog!$AL$2:$AL$300,0))&" · "&INDEX(Backlog!$D$2:$D$300,MATCH("Done|64",Backlog!$AL$2:$AL$300,0)),"")
B70: =IFERROR(INDEX(Backlog!$A$2:$A$300,MATCH("To Do|65",Backlog!$AL$2:$AL$300,0))&" · "&INDEX(Backlog!$D$2:$D$300,MATCH("To Do|65",Backlog!$AL$2:$AL$300,0)),"") | C70: =IFERROR(INDEX(Backlog!$A$2:$A$300,MATCH("In Progress|65",Backlog!$AL$2:$AL$300,0))&" · "&INDEX(Backlog!$D$2:$D$300,MATCH("In Progress|65",Backlog!$AL$2:$AL$300,0)),"") | D70: =IFERROR(INDEX(Backlog!$A$2:$A$300,MATCH("In Review|65",Backlog!$AL$2:$AL$300,0))&" · "&INDEX(Backlog!$D$2:$D$300,MATCH("In Review|65",Backlog!$AL$2:$AL$300,0)),"") | E70: =IFERROR(INDEX(Backlog!$A$2:$A$300,MATCH("Blocked|65",Backlog!$AL$2:$AL$300,0))&" · "&INDEX(Backlog!$D$2:$D$300,MATCH("Blocked|65",Backlog!$AL$2:$AL$300,0)),"") | F70: =IFERROR(INDEX(Backlog!$A$2:$A$300,MATCH("Done|65",Backlog!$AL$2:$AL$300,0))&" · "&INDEX(Backlog!$D$2:$D$300,MATCH("Done|65",Backlog!$AL$2:$AL$300,0)),"")
B71: =IFERROR(INDEX(Backlog!$A$2:$A$300,MATCH("To Do|66",Backlog!$AL$2:$AL$300,0))&" · "&INDEX(Backlog!$D$2:$D$300,MATCH("To Do|66",Backlog!$AL$2:$AL$300,0)),"") | C71: =IFERROR(INDEX(Backlog!$A$2:$A$300,MATCH("In Progress|66",Backlog!$AL$2:$AL$300,0))&" · "&INDEX(Backlog!$D$2:$D$300,MATCH("In Progress|66",Backlog!$AL$2:$AL$300,0)),"") | D71: =IFERROR(INDEX(Backlog!$A$2:$A$300,MATCH("In Review|66",Backlog!$AL$2:$AL$300,0))&" · "&INDEX(Backlog!$D$2:$D$300,MATCH("In Review|66",Backlog!$AL$2:$AL$300,0)),"") | E71: =IFERROR(INDEX(Backlog!$A$2:$A$300,MATCH("Blocked|66",Backlog!$AL$2:$AL$300,0))&" · "&INDEX(Backlog!$D$2:$D$300,MATCH("Blocked|66",Backlog!$AL$2:$AL$300,0)),"") | F71: =IFERROR(INDEX(Backlog!$A$2:$A$300,MATCH("Done|66",Backlog!$AL$2:$AL$300,0))&" · "&INDEX(Backlog!$D$2:$D$300,MATCH("Done|66",Backlog!$AL$2:$AL$300,0)),"")
B72: =IFERROR(INDEX(Backlog!$A$2:$A$300,MATCH("To Do|67",Backlog!$AL$2:$AL$300,0))&" · "&INDEX(Backlog!$D$2:$D$300,MATCH("To Do|67",Backlog!$AL$2:$AL$300,0)),"") | C72: =IFERROR(INDEX(Backlog!$A$2:$A$300,MATCH("In Progress|67",Backlog!$AL$2:$AL$300,0))&" · "&INDEX(Backlog!$D$2:$D$300,MATCH("In Progress|67",Backlog!$AL$2:$AL$300,0)),"") | D72: =IFERROR(INDEX(Backlog!$A$2:$A$300,MATCH("In Review|67",Backlog!$AL$2:$AL$300,0))&" · "&INDEX(Backlog!$D$2:$D$300,MATCH("In Review|67",Backlog!$AL$2:$AL$300,0)),"") | E72: =IFERROR(INDEX(Backlog!$A$2:$A$300,MATCH("Blocked|67",Backlog!$AL$2:$AL$300,0))&" · "&INDEX(Backlog!$D$2:$D$300,MATCH("Blocked|67",Backlog!$AL$2:$AL$300,0)),"") | F72: =IFERROR(INDEX(Backlog!$A$2:$A$300,MATCH("Done|67",Backlog!$AL$2:$AL$300,0))&" · "&INDEX(Backlog!$D$2:$D$300,MATCH("Done|67",Backlog!$AL$2:$AL$300,0)),"")
B73: =IFERROR(INDEX(Backlog!$A$2:$A$300,MATCH("To Do|68",Backlog!$AL$2:$AL$300,0))&" · "&INDEX(Backlog!$D$2:$D$300,MATCH("To Do|68",Backlog!$AL$2:$AL$300,0)),"") | C73: =IFERROR(INDEX(Backlog!$A$2:$A$300,MATCH("In Progress|68",Backlog!$AL$2:$AL$300,0))&" · "&INDEX(Backlog!$D$2:$D$300,MATCH("In Progress|68",Backlog!$AL$2:$AL$300,0)),"") | D73: =IFERROR(INDEX(Backlog!$A$2:$A$300,MATCH("In Review|68",Backlog!$AL$2:$AL$300,0))&" · "&INDEX(Backlog!$D$2:$D$300,MATCH("In Review|68",Backlog!$AL$2:$AL$300,0)),"") | E73: =IFERROR(INDEX(Backlog!$A$2:$A$300,MATCH("Blocked|68",Backlog!$AL$2:$AL$300,0))&" · "&INDEX(Backlog!$D$2:$D$300,MATCH("Blocked|68",Backlog!$AL$2:$AL$300,0)),"") | F73: =IFERROR(INDEX(Backlog!$A$2:$A$300,MATCH("Done|68",Backlog!$AL$2:$AL$300,0))&" · "&INDEX(Backlog!$D$2:$D$300,MATCH("Done|68",Backlog!$AL$2:$AL$300,0)),"")
B74: =IFERROR(INDEX(Backlog!$A$2:$A$300,MATCH("To Do|69",Backlog!$AL$2:$AL$300,0))&" · "&INDEX(Backlog!$D$2:$D$300,MATCH("To Do|69",Backlog!$AL$2:$AL$300,0)),"") | C74: =IFERROR(INDEX(Backlog!$A$2:$A$300,MATCH("In Progress|69",Backlog!$AL$2:$AL$300,0))&" · "&INDEX(Backlog!$D$2:$D$300,MATCH("In Progress|69",Backlog!$AL$2:$AL$300,0)),"") | D74: =IFERROR(INDEX(Backlog!$A$2:$A$300,MATCH("In Review|69",Backlog!$AL$2:$AL$300,0))&" · "&INDEX(Backlog!$D$2:$D$300,MATCH("In Review|69",Backlog!$AL$2:$AL$300,0)),"") | E74: =IFERROR(INDEX(Backlog!$A$2:$A$300,MATCH("Blocked|69",Backlog!$AL$2:$AL$300,0))&" · "&INDEX(Backlog!$D$2:$D$300,MATCH("Blocked|69",Backlog!$AL$2:$AL$300,0)),"") | F74: =IFERROR(INDEX(Backlog!$A$2:$A$300,MATCH("Done|69",Backlog!$AL$2:$AL$300,0))&" · "&INDEX(Backlog!$D$2:$D$300,MATCH("Done|69",Backlog!$AL$2:$AL$300,0)),"")
B75: =IFERROR(INDEX(Backlog!$A$2:$A$300,MATCH("To Do|70",Backlog!$AL$2:$AL$300,0))&" · "&INDEX(Backlog!$D$2:$D$300,MATCH("To Do|70",Backlog!$AL$2:$AL$300,0)),"") | C75: =IFERROR(INDEX(Backlog!$A$2:$A$300,MATCH("In Progress|70",Backlog!$AL$2:$AL$300,0))&" · "&INDEX(Backlog!$D$2:$D$300,MATCH("In Progress|70",Backlog!$AL$2:$AL$300,0)),"") | D75: =IFERROR(INDEX(Backlog!$A$2:$A$300,MATCH("In Review|70",Backlog!$AL$2:$AL$300,0))&" · "&INDEX(Backlog!$D$2:$D$300,MATCH("In Review|70",Backlog!$AL$2:$AL$300,0)),"") | E75: =IFERROR(INDEX(Backlog!$A$2:$A$300,MATCH("Blocked|70",Backlog!$AL$2:$AL$300,0))&" · "&INDEX(Backlog!$D$2:$D$300,MATCH("Blocked|70",Backlog!$AL$2:$AL$300,0)),"") | F75: =IFERROR(INDEX(Backlog!$A$2:$A$300,MATCH("Done|70",Backlog!$AL$2:$AL$300,0))&" · "&INDEX(Backlog!$D$2:$D$300,MATCH("Done|70",Backlog!$AL$2:$AL$300,0)),"")
B76: =IFERROR(INDEX(Backlog!$A$2:$A$300,MATCH("To Do|71",Backlog!$AL$2:$AL$300,0))&" · "&INDEX(Backlog!$D$2:$D$300,MATCH("To Do|71",Backlog!$AL$2:$AL$300,0)),"") | C76: =IFERROR(INDEX(Backlog!$A$2:$A$300,MATCH("In Progress|71",Backlog!$AL$2:$AL$300,0))&" · "&INDEX(Backlog!$D$2:$D$300,MATCH("In Progress|71",Backlog!$AL$2:$AL$300,0)),"") | D76: =IFERROR(INDEX(Backlog!$A$2:$A$300,MATCH("In Review|71",Backlog!$AL$2:$AL$300,0))&" · "&INDEX(Backlog!$D$2:$D$300,MATCH("In Review|71",Backlog!$AL$2:$AL$300,0)),"") | E76: =IFERROR(INDEX(Backlog!$A$2:$A$300,MATCH("Blocked|71",Backlog!$AL$2:$AL$300,0))&" · "&INDEX(Backlog!$D$2:$D$300,MATCH("Blocked|71",Backlog!$AL$2:$AL$300,0)),"") | F76: =IFERROR(INDEX(Backlog!$A$2:$A$300,MATCH("Done|71",Backlog!$AL$2:$AL$300,0))&" · "&INDEX(Backlog!$D$2:$D$300,MATCH("Done|71",Backlog!$AL$2:$AL$300,0)),"")
B77: =IFERROR(INDEX(Backlog!$A$2:$A$300,MATCH("To Do|72",Backlog!$AL$2:$AL$300,0))&" · "&INDEX(Backlog!$D$2:$D$300,MATCH("To Do|72",Backlog!$AL$2:$AL$300,0)),"") | C77: =IFERROR(INDEX(Backlog!$A$2:$A$300,MATCH("In Progress|72",Backlog!$AL$2:$AL$300,0))&" · "&INDEX(Backlog!$D$2:$D$300,MATCH("In Progress|72",Backlog!$AL$2:$AL$300,0)),"") | D77: =IFERROR(INDEX(Backlog!$A$2:$A$300,MATCH("In Review|72",Backlog!$AL$2:$AL$300,0))&" · "&INDEX(Backlog!$D$2:$D$300,MATCH("In Review|72",Backlog!$AL$2:$AL$300,0)),"") | E77: =IFERROR(INDEX(Backlog!$A$2:$A$300,MATCH("Blocked|72",Backlog!$AL$2:$AL$300,0))&" · "&INDEX(Backlog!$D$2:$D$300,MATCH("Blocked|72",Backlog!$AL$2:$AL$300,0)),"") | F77: =IFERROR(INDEX(Backlog!$A$2:$A$300,MATCH("Done|72",Backlog!$AL$2:$AL$300,0))&" · "&INDEX(Backlog!$D$2:$D$300,MATCH("Done|72",Backlog!$AL$2:$AL$300,0)),"")
B78: =IFERROR(INDEX(Backlog!$A$2:$A$300,MATCH("To Do|73",Backlog!$AL$2:$AL$300,0))&" · "&INDEX(Backlog!$D$2:$D$300,MATCH("To Do|73",Backlog!$AL$2:$AL$300,0)),"") | C78: =IFERROR(INDEX(Backlog!$A$2:$A$300,MATCH("In Progress|73",Backlog!$AL$2:$AL$300,0))&" · "&INDEX(Backlog!$D$2:$D$300,MATCH("In Progress|73",Backlog!$AL$2:$AL$300,0)),"") | D78: =IFERROR(INDEX(Backlog!$A$2:$A$300,MATCH("In Review|73",Backlog!$AL$2:$AL$300,0))&" · "&INDEX(Backlog!$D$2:$D$300,MATCH("In Review|73",Backlog!$AL$2:$AL$300,0)),"") | E78: =IFERROR(INDEX(Backlog!$A$2:$A$300,MATCH("Blocked|73",Backlog!$AL$2:$AL$300,0))&" · "&INDEX(Backlog!$D$2:$D$300,MATCH("Blocked|73",Backlog!$AL$2:$AL$300,0)),"") | F78: =IFERROR(INDEX(Backlog!$A$2:$A$300,MATCH("Done|73",Backlog!$AL$2:$AL$300,0))&" · "&INDEX(Backlog!$D$2:$D$300,MATCH("Done|73",Backlog!$AL$2:$AL$300,0)),"")
B79: =IFERROR(INDEX(Backlog!$A$2:$A$300,MATCH("To Do|74",Backlog!$AL$2:$AL$300,0))&" · "&INDEX(Backlog!$D$2:$D$300,MATCH("To Do|74",Backlog!$AL$2:$AL$300,0)),"") | C79: =IFERROR(INDEX(Backlog!$A$2:$A$300,MATCH("In Progress|74",Backlog!$AL$2:$AL$300,0))&" · "&INDEX(Backlog!$D$2:$D$300,MATCH("In Progress|74",Backlog!$AL$2:$AL$300,0)),"") | D79: =IFERROR(INDEX(Backlog!$A$2:$A$300,MATCH("In Review|74",Backlog!$AL$2:$AL$300,0))&" · "&INDEX(Backlog!$D$2:$D$300,MATCH("In Review|74",Backlog!$AL$2:$AL$300,0)),"") | E79: =IFERROR(INDEX(Backlog!$A$2:$A$300,MATCH("Blocked|74",Backlog!$AL$2:$AL$300,0))&" · "&INDEX(Backlog!$D$2:$D$300,MATCH("Blocked|74",Backlog!$AL$2:$AL$300,0)),"") | F79: =IFERROR(INDEX(Backlog!$A$2:$A$300,MATCH("Done|74",Backlog!$AL$2:$AL$300,0))&" · "&INDEX(Backlog!$D$2:$D$300,MATCH("Done|74",Backlog!$AL$2:$AL$300,0)),"")
B80: =IFERROR(INDEX(Backlog!$A$2:$A$300,MATCH("To Do|75",Backlog!$AL$2:$AL$300,0))&" · "&INDEX(Backlog!$D$2:$D$300,MATCH("To Do|75",Backlog!$AL$2:$AL$300,0)),"") | C80: =IFERROR(INDEX(Backlog!$A$2:$A$300,MATCH("In Progress|75",Backlog!$AL$2:$AL$300,0))&" · "&INDEX(Backlog!$D$2:$D$300,MATCH("In Progress|75",Backlog!$AL$2:$AL$300,0)),"") | D80: =IFERROR(INDEX(Backlog!$A$2:$A$300,MATCH("In Review|75",Backlog!$AL$2:$AL$300,0))&" · "&INDEX(Backlog!$D$2:$D$300,MATCH("In Review|75",Backlog!$AL$2:$AL$300,0)),"") | E80: =IFERROR(INDEX(Backlog!$A$2:$A$300,MATCH("Blocked|75",Backlog!$AL$2:$AL$300,0))&" · "&INDEX(Backlog!$D$2:$D$300,MATCH("Blocked|75",Backlog!$AL$2:$AL$300,0)),"") | F80: =IFERROR(INDEX(Backlog!$A$2:$A$300,MATCH("Done|75",Backlog!$AL$2:$AL$300,0))&" · "&INDEX(Backlog!$D$2:$D$300,MATCH("Done|75",Backlog!$AL$2:$AL$300,0)),"")
B81: =IFERROR(INDEX(Backlog!$A$2:$A$300,MATCH("To Do|76",Backlog!$AL$2:$AL$300,0))&" · "&INDEX(Backlog!$D$2:$D$300,MATCH("To Do|76",Backlog!$AL$2:$AL$300,0)),"") | C81: =IFERROR(INDEX(Backlog!$A$2:$A$300,MATCH("In Progress|76",Backlog!$AL$2:$AL$300,0))&" · "&INDEX(Backlog!$D$2:$D$300,MATCH("In Progress|76",Backlog!$AL$2:$AL$300,0)),"") | D81: =IFERROR(INDEX(Backlog!$A$2:$A$300,MATCH("In Review|76",Backlog!$AL$2:$AL$300,0))&" · "&INDEX(Backlog!$D$2:$D$300,MATCH("In Review|76",Backlog!$AL$2:$AL$300,0)),"") | E81: =IFERROR(INDEX(Backlog!$A$2:$A$300,MATCH("Blocked|76",Backlog!$AL$2:$AL$300,0))&" · "&INDEX(Backlog!$D$2:$D$300,MATCH("Blocked|76",Backlog!$AL$2:$AL$300,0)),"") | F81: =IFERROR(INDEX(Backlog!$A$2:$A$300,MATCH("Done|76",Backlog!$AL$2:$AL$300,0))&" · "&INDEX(Backlog!$D$2:$D$300,MATCH("Done|76",Backlog!$AL$2:$AL$300,0)),"")
B82: =IFERROR(INDEX(Backlog!$A$2:$A$300,MATCH("To Do|77",Backlog!$AL$2:$AL$300,0))&" · "&INDEX(Backlog!$D$2:$D$300,MATCH("To Do|77",Backlog!$AL$2:$AL$300,0)),"") | C82: =IFERROR(INDEX(Backlog!$A$2:$A$300,MATCH("In Progress|77",Backlog!$AL$2:$AL$300,0))&" · "&INDEX(Backlog!$D$2:$D$300,MATCH("In Progress|77",Backlog!$AL$2:$AL$300,0)),"") | D82: =IFERROR(INDEX(Backlog!$A$2:$A$300,MATCH("In Review|77",Backlog!$AL$2:$AL$300,0))&" · "&INDEX(Backlog!$D$2:$D$300,MATCH("In Review|77",Backlog!$AL$2:$AL$300,0)),"") | E82: =IFERROR(INDEX(Backlog!$A$2:$A$300,MATCH("Blocked|77",Backlog!$AL$2:$AL$300,0))&" · "&INDEX(Backlog!$D$2:$D$300,MATCH("Blocked|77",Backlog!$AL$2:$AL$300,0)),"") | F82: =IFERROR(INDEX(Backlog!$A$2:$A$300,MATCH("Done|77",Backlog!$AL$2:$AL$300,0))&" · "&INDEX(Backlog!$D$2:$D$300,MATCH("Done|77",Backlog!$AL$2:$AL$300,0)),"")
B83: =IFERROR(INDEX(Backlog!$A$2:$A$300,MATCH("To Do|78",Backlog!$AL$2:$AL$300,0))&" · "&INDEX(Backlog!$D$2:$D$300,MATCH("To Do|78",Backlog!$AL$2:$AL$300,0)),"") | C83: =IFERROR(INDEX(Backlog!$A$2:$A$300,MATCH("In Progress|78",Backlog!$AL$2:$AL$300,0))&" · "&INDEX(Backlog!$D$2:$D$300,MATCH("In Progress|78",Backlog!$AL$2:$AL$300,0)),"") | D83: =IFERROR(INDEX(Backlog!$A$2:$A$300,MATCH("In Review|78",Backlog!$AL$2:$AL$300,0))&" · "&INDEX(Backlog!$D$2:$D$300,MATCH("In Review|78",Backlog!$AL$2:$AL$300,0)),"") | E83: =IFERROR(INDEX(Backlog!$A$2:$A$300,MATCH("Blocked|78",Backlog!$AL$2:$AL$300,0))&" · "&INDEX(Backlog!$D$2:$D$300,MATCH("Blocked|78",Backlog!$AL$2:$AL$300,0)),"") | F83: =IFERROR(INDEX(Backlog!$A$2:$A$300,MATCH("Done|78",Backlog!$AL$2:$AL$300,0))&" · "&INDEX(Backlog!$D$2:$D$300,MATCH("Done|78",Backlog!$AL$2:$AL$300,0)),"")
B84: =IFERROR(INDEX(Backlog!$A$2:$A$300,MATCH("To Do|79",Backlog!$AL$2:$AL$300,0))&" · "&INDEX(Backlog!$D$2:$D$300,MATCH("To Do|79",Backlog!$AL$2:$AL$300,0)),"") | C84: =IFERROR(INDEX(Backlog!$A$2:$A$300,MATCH("In Progress|79",Backlog!$AL$2:$AL$300,0))&" · "&INDEX(Backlog!$D$2:$D$300,MATCH("In Progress|79",Backlog!$AL$2:$AL$300,0)),"") | D84: =IFERROR(INDEX(Backlog!$A$2:$A$300,MATCH("In Review|79",Backlog!$AL$2:$AL$300,0))&" · "&INDEX(Backlog!$D$2:$D$300,MATCH("In Review|79",Backlog!$AL$2:$AL$300,0)),"") | E84: =IFERROR(INDEX(Backlog!$A$2:$A$300,MATCH("Blocked|79",Backlog!$AL$2:$AL$300,0))&" · "&INDEX(Backlog!$D$2:$D$300,MATCH("Blocked|79",Backlog!$AL$2:$AL$300,0)),"") | F84: =IFERROR(INDEX(Backlog!$A$2:$A$300,MATCH("Done|79",Backlog!$AL$2:$AL$300,0))&" · "&INDEX(Backlog!$D$2:$D$300,MATCH("Done|79",Backlog!$AL$2:$AL$300,0)),"")
B85: =IFERROR(INDEX(Backlog!$A$2:$A$300,MATCH("To Do|80",Backlog!$AL$2:$AL$300,0))&" · "&INDEX(Backlog!$D$2:$D$300,MATCH("To Do|80",Backlog!$AL$2:$AL$300,0)),"") | C85: =IFERROR(INDEX(Backlog!$A$2:$A$300,MATCH("In Progress|80",Backlog!$AL$2:$AL$300,0))&" · "&INDEX(Backlog!$D$2:$D$300,MATCH("In Progress|80",Backlog!$AL$2:$AL$300,0)),"") | D85: =IFERROR(INDEX(Backlog!$A$2:$A$300,MATCH("In Review|80",Backlog!$AL$2:$AL$300,0))&" · "&INDEX(Backlog!$D$2:$D$300,MATCH("In Review|80",Backlog!$AL$2:$AL$300,0)),"") | E85: =IFERROR(INDEX(Backlog!$A$2:$A$300,MATCH("Blocked|80",Backlog!$AL$2:$AL$300,0))&" · "&INDEX(Backlog!$D$2:$D$300,MATCH("Blocked|80",Backlog!$AL$2:$AL$300,0)),"") | F85: =IFERROR(INDEX(Backlog!$A$2:$A$300,MATCH("Done|80",Backlog!$AL$2:$AL$300,0))&" · "&INDEX(Backlog!$D$2:$D$300,MATCH("Done|80",Backlog!$AL$2:$AL$300,0)),"")
B86: =IFERROR(INDEX(Backlog!$A$2:$A$300,MATCH("To Do|81",Backlog!$AL$2:$AL$300,0))&" · "&INDEX(Backlog!$D$2:$D$300,MATCH("To Do|81",Backlog!$AL$2:$AL$300,0)),"") | C86: =IFERROR(INDEX(Backlog!$A$2:$A$300,MATCH("In Progress|81",Backlog!$AL$2:$AL$300,0))&" · "&INDEX(Backlog!$D$2:$D$300,MATCH("In Progress|81",Backlog!$AL$2:$AL$300,0)),"") | D86: =IFERROR(INDEX(Backlog!$A$2:$A$300,MATCH("In Review|81",Backlog!$AL$2:$AL$300,0))&" · "&INDEX(Backlog!$D$2:$D$300,MATCH("In Review|81",Backlog!$AL$2:$AL$300,0)),"") | E86: =IFERROR(INDEX(Backlog!$A$2:$A$300,MATCH("Blocked|81",Backlog!$AL$2:$AL$300,0))&" · "&INDEX(Backlog!$D$2:$D$300,MATCH("Blocked|81",Backlog!$AL$2:$AL$300,0)),"") | F86: =IFERROR(INDEX(Backlog!$A$2:$A$300,MATCH("Done|81",Backlog!$AL$2:$AL$300,0))&" · "&INDEX(Backlog!$D$2:$D$300,MATCH("Done|81",Backlog!$AL$2:$AL$300,0)),"")
B87: =IFERROR(INDEX(Backlog!$A$2:$A$300,MATCH("To Do|82",Backlog!$AL$2:$AL$300,0))&" · "&INDEX(Backlog!$D$2:$D$300,MATCH("To Do|82",Backlog!$AL$2:$AL$300,0)),"") | C87: =IFERROR(INDEX(Backlog!$A$2:$A$300,MATCH("In Progress|82",Backlog!$AL$2:$AL$300,0))&" · "&INDEX(Backlog!$D$2:$D$300,MATCH("In Progress|82",Backlog!$AL$2:$AL$300,0)),"") | D87: =IFERROR(INDEX(Backlog!$A$2:$A$300,MATCH("In Review|82",Backlog!$AL$2:$AL$300,0))&" · "&INDEX(Backlog!$D$2:$D$300,MATCH("In Review|82",Backlog!$AL$2:$AL$300,0)),"") | E87: =IFERROR(INDEX(Backlog!$A$2:$A$300,MATCH("Blocked|82",Backlog!$AL$2:$AL$300,0))&" · "&INDEX(Backlog!$D$2:$D$300,MATCH("Blocked|82",Backlog!$AL$2:$AL$300,0)),"") | F87: =IFERROR(INDEX(Backlog!$A$2:$A$300,MATCH("Done|82",Backlog!$AL$2:$AL$300,0))&" · "&INDEX(Backlog!$D$2:$D$300,MATCH("Done|82",Backlog!$AL$2:$AL$300,0)),"")

Sheet Dashboard
A1: Dashboard
A2: All figures are formulas over Backlog, Screens, Test Cases and Translations.
A4: Key figures
A5: Total tickets | B5: =COUNTA(Backlog!$A$2:$A$300)
A6: Total story points | B6: =SUM(Backlog!$U$2:$U$300)
A7: Blocked tickets | B7: =COUNTIF(Backlog!$AD$2:$AD$300,"Blocked")
A8: Awaiting human review (In Review) | B8: =COUNTIF(Backlog!$AD$2:$AD$300,"In Review")
A9: Awaiting merge (Git-PR-CI) | B9: =COUNTIF('Git-PR-CI'!$M$2:$M$300,"Pending")
A10: Failed checks (Git-PR-CI) | B10: =COUNTIF('Git-PR-CI'!$E$2:$L$300,"Fail")
A11: Open dependencies (not Done, has deps) | B11: =COUNTIFS(Backlog!$A$2:$A$300,"<>",Backlog!$AD$2:$AD$300,"<>Done",Backlog!$N$2:$N$300,"<>None")
A12: Screens with design missing | B12: =COUNTIF(Screens!$P$2:$P$100,"Design Missing")
A13: Screens not yet verified | B13: =COUNTA(Screens!$B$2:$B$100)-COUNTIF(Screens!$Q$2:$Q$100,"Verified")
A14: Test cases not passing | B14: =COUNTA('Test Cases'!$A$2:$A$300)-COUNTIF('Test Cases'!$N$2:$N$300,"Pass")
A15: Kannada strings missing | B15: =COUNTIF(Translations!$G$2:$G$500,"Missing")
A16: Kannada strings awaiting native review | B16: =COUNTIF(Translations!$G$2:$G$500,"Needs native review")+COUNTIF(Translations!$G$2:$G$500,"Draft")
A18: By status | B18: Tickets | C18: Points | E18: By priority | F18: Tickets | G18: Points | I18: By MoSCoW | J18: Tickets | K18: Points
A19: To Do | B19: =COUNTIF(Backlog!$AD$2:$AD$300,"To Do") | C19: =SUMIF(Backlog!$AD$2:$AD$300,"To Do",Backlog!$U$2:$U$300) | E19: Highest | F19: =COUNTIF(Backlog!$H$2:$H$300,"Highest") | G19: =SUMIF(Backlog!$H$2:$H$300,"Highest",Backlog!$U$2:$U$300) | I19: Must | J19: =COUNTIF(Backlog!$I$2:$I$300,"Must") | K19: =SUMIF(Backlog!$I$2:$I$300,"Must",Backlog!$U$2:$U$300)
A20: In Progress | B20: =COUNTIF(Backlog!$AD$2:$AD$300,"In Progress") | C20: =SUMIF(Backlog!$AD$2:$AD$300,"In Progress",Backlog!$U$2:$U$300) | E20: High | F20: =COUNTIF(Backlog!$H$2:$H$300,"High") | G20: =SUMIF(Backlog!$H$2:$H$300,"High",Backlog!$U$2:$U$300) | I20: Should | J20: =COUNTIF(Backlog!$I$2:$I$300,"Should") | K20: =SUMIF(Backlog!$I$2:$I$300,"Should",Backlog!$U$2:$U$300)
A21: In Review | B21: =COUNTIF(Backlog!$AD$2:$AD$300,"In Review") | C21: =SUMIF(Backlog!$AD$2:$AD$300,"In Review",Backlog!$U$2:$U$300) | E21: Medium | F21: =COUNTIF(Backlog!$H$2:$H$300,"Medium") | G21: =SUMIF(Backlog!$H$2:$H$300,"Medium",Backlog!$U$2:$U$300) | I21: Could | J21: =COUNTIF(Backlog!$I$2:$I$300,"Could") | K21: =SUMIF(Backlog!$I$2:$I$300,"Could",Backlog!$U$2:$U$300)
A22: Blocked | B22: =COUNTIF(Backlog!$AD$2:$AD$300,"Blocked") | C22: =SUMIF(Backlog!$AD$2:$AD$300,"Blocked",Backlog!$U$2:$U$300) | E22: Low | F22: =COUNTIF(Backlog!$H$2:$H$300,"Low") | G22: =SUMIF(Backlog!$H$2:$H$300,"Low",Backlog!$U$2:$U$300) | I22: Won't | J22: =COUNTIF(Backlog!$I$2:$I$300,"Won't") | K22: =SUMIF(Backlog!$I$2:$I$300,"Won't",Backlog!$U$2:$U$300)
A23: Done | B23: =COUNTIF(Backlog!$AD$2:$AD$300,"Done") | C23: =SUMIF(Backlog!$AD$2:$AD$300,"Done",Backlog!$U$2:$U$300)
A24: Needs Clarification | B24: =COUNTIF(Backlog!$AD$2:$AD$300,"Needs Clarification") | C24: =SUMIF(Backlog!$AD$2:$AD$300,"Needs Clarification",Backlog!$U$2:$U$300)
A26: By phase | B26: Tickets | C26: Points | E26: By type | F26: Tickets | G26: Points | I26: By Kannada status | J26: Tickets | K26: Points
A27: P0 | B27: =COUNTIF(Backlog!$J$2:$J$300,"P0") | C27: =SUMIF(Backlog!$J$2:$J$300,"P0",Backlog!$U$2:$U$300) | E27: Story | F27: =COUNTIF(Backlog!$B$2:$B$300,"Story") | G27: =SUMIF(Backlog!$B$2:$B$300,"Story",Backlog!$U$2:$U$300) | I27: N/A | J27: =COUNTIF(Backlog!$AI$2:$AI$300,"N/A") | K27: =SUMIF(Backlog!$AI$2:$AI$300,"N/A",Backlog!$U$2:$U$300)
A28: P1 | B28: =COUNTIF(Backlog!$J$2:$J$300,"P1") | C28: =SUMIF(Backlog!$J$2:$J$300,"P1",Backlog!$U$2:$U$300) | E28: Task | F28: =COUNTIF(Backlog!$B$2:$B$300,"Task") | G28: =SUMIF(Backlog!$B$2:$B$300,"Task",Backlog!$U$2:$U$300) | I28: Missing | J28: =COUNTIF(Backlog!$AI$2:$AI$300,"Missing") | K28: =SUMIF(Backlog!$AI$2:$AI$300,"Missing",Backlog!$U$2:$U$300)
A29: P2 | B29: =COUNTIF(Backlog!$J$2:$J$300,"P2") | C29: =SUMIF(Backlog!$J$2:$J$300,"P2",Backlog!$U$2:$U$300) | E29: Bug | F29: =COUNTIF(Backlog!$B$2:$B$300,"Bug") | G29: =SUMIF(Backlog!$B$2:$B$300,"Bug",Backlog!$U$2:$U$300) | I29: Draft | J29: =COUNTIF(Backlog!$AI$2:$AI$300,"Draft") | K29: =SUMIF(Backlog!$AI$2:$AI$300,"Draft",Backlog!$U$2:$U$300)
A30: P3 | B30: =COUNTIF(Backlog!$J$2:$J$300,"P3") | C30: =SUMIF(Backlog!$J$2:$J$300,"P3",Backlog!$U$2:$U$300) | I30: Needs native review | J30: =COUNTIF(Backlog!$AI$2:$AI$300,"Needs native review") | K30: =SUMIF(Backlog!$AI$2:$AI$300,"Needs native review",Backlog!$U$2:$U$300)
A31: P4 | B31: =COUNTIF(Backlog!$J$2:$J$300,"P4") | C31: =SUMIF(Backlog!$J$2:$J$300,"P4",Backlog!$U$2:$U$300) | I31: Approved | J31: =COUNTIF(Backlog!$AI$2:$AI$300,"Approved") | K31: =SUMIF(Backlog!$AI$2:$AI$300,"Approved",Backlog!$U$2:$U$300)
A32: P5 | B32: =COUNTIF(Backlog!$J$2:$J$300,"P5") | C32: =SUMIF(Backlog!$J$2:$J$300,"P5",Backlog!$U$2:$U$300)
A33: P6 | B33: =COUNTIF(Backlog!$J$2:$J$300,"P6") | C33: =SUMIF(Backlog!$J$2:$J$300,"P6",Backlog!$U$2:$U$300)
A34: P7 | B34: =COUNTIF(Backlog!$J$2:$J$300,"P7") | C34: =SUMIF(Backlog!$J$2:$J$300,"P7",Backlog!$U$2:$U$300)
A35: P8 | B35: =COUNTIF(Backlog!$J$2:$J$300,"P8") | C35: =SUMIF(Backlog!$J$2:$J$300,"P8",Backlog!$U$2:$U$300)
A37: By epic | B37: Tickets | C37: Points
A38: LS-EPIC-01 | B38: =COUNTIF(Backlog!$C$2:$C$300,"LS-EPIC-01") | C38: =SUMIF(Backlog!$C$2:$C$300,"LS-EPIC-01",Backlog!$U$2:$U$300)
A39: LS-EPIC-02 | B39: =COUNTIF(Backlog!$C$2:$C$300,"LS-EPIC-02") | C39: =SUMIF(Backlog!$C$2:$C$300,"LS-EPIC-02",Backlog!$U$2:$U$300)
A40: LS-EPIC-03 | B40: =COUNTIF(Backlog!$C$2:$C$300,"LS-EPIC-03") | C40: =SUMIF(Backlog!$C$2:$C$300,"LS-EPIC-03",Backlog!$U$2:$U$300)
A41: LS-EPIC-04 | B41: =COUNTIF(Backlog!$C$2:$C$300,"LS-EPIC-04") | C41: =SUMIF(Backlog!$C$2:$C$300,"LS-EPIC-04",Backlog!$U$2:$U$300)
A42: LS-EPIC-05 | B42: =COUNTIF(Backlog!$C$2:$C$300,"LS-EPIC-05") | C42: =SUMIF(Backlog!$C$2:$C$300,"LS-EPIC-05",Backlog!$U$2:$U$300)
A43: LS-EPIC-06 | B43: =COUNTIF(Backlog!$C$2:$C$300,"LS-EPIC-06") | C43: =SUMIF(Backlog!$C$2:$C$300,"LS-EPIC-06",Backlog!$U$2:$U$300)
A44: LS-EPIC-07 | B44: =COUNTIF(Backlog!$C$2:$C$300,"LS-EPIC-07") | C44: =SUMIF(Backlog!$C$2:$C$300,"LS-EPIC-07",Backlog!$U$2:$U$300)
A45: LS-EPIC-08 | B45: =COUNTIF(Backlog!$C$2:$C$300,"LS-EPIC-08") | C45: =SUMIF(Backlog!$C$2:$C$300,"LS-EPIC-08",Backlog!$U$2:$U$300)
A46: LS-EPIC-09 | B46: =COUNTIF(Backlog!$C$2:$C$300,"LS-EPIC-09") | C46: =SUMIF(Backlog!$C$2:$C$300,"LS-EPIC-09",Backlog!$U$2:$U$300)
A47: LS-EPIC-10 | B47: =COUNTIF(Backlog!$C$2:$C$300,"LS-EPIC-10") | C47: =SUMIF(Backlog!$C$2:$C$300,"LS-EPIC-10",Backlog!$U$2:$U$300)
A48: LS-EPIC-11 | B48: =COUNTIF(Backlog!$C$2:$C$300,"LS-EPIC-11") | C48: =SUMIF(Backlog!$C$2:$C$300,"LS-EPIC-11",Backlog!$U$2:$U$300)
A49: LS-EPIC-12 | B49: =COUNTIF(Backlog!$C$2:$C$300,"LS-EPIC-12") | C49: =SUMIF(Backlog!$C$2:$C$300,"LS-EPIC-12",Backlog!$U$2:$U$300)
A50: LS-EPIC-13 | B50: =COUNTIF(Backlog!$C$2:$C$300,"LS-EPIC-13") | C50: =SUMIF(Backlog!$C$2:$C$300,"LS-EPIC-13",Backlog!$U$2:$U$300)
A51: LS-EPIC-14 | B51: =COUNTIF(Backlog!$C$2:$C$300,"LS-EPIC-14") | C51: =SUMIF(Backlog!$C$2:$C$300,"LS-EPIC-14",Backlog!$U$2:$U$300)
A52: LS-EPIC-15 | B52: =COUNTIF(Backlog!$C$2:$C$300,"LS-EPIC-15") | C52: =SUMIF(Backlog!$C$2:$C$300,"LS-EPIC-15",Backlog!$U$2:$U$300)

Sheet Backlog
A1: Issue Key | B1: Issue Type | C1: Epic Link | D1: Summary | E1: Description | F1: User Story | G1: Business Value | H1: Priority | I1: MoSCoW | J1: Phase | K1: Component/Module | L1: Screen ID | M1: Figma Frame Reference | N1: Dependencies | O1: Blocks / Blocked By | P1: Acceptance Criteria | Q1: Definition of Done | R1: Implementation Notes | S1: Required Tests | T1: Test Evidence | U1: Estimate (Story Points) | V1: Estimated Complexity | W1: Risk | X1: Agent Role | Y1: Parallelizable | Z1: Shared File Conflict Risk | AA1: Branch Name | AB1: Pull Request Link | AC1: Assignee | AD1: Status | AE1: Reviewer | AF1: Approval Status | AG1: Actual Result | AH1: Localization Impact | AI1: Kannada Translation Status | AJ1: Notes | AK1: Requirement IDs | AL1: Board Key (formula)
A2: LS-001 | B2: Task | C2: LS-EPIC-01 | D2: Read-only repository & toolchain discovery | E2: Inspect local repo, git state, branches, Gradle/AGP/Kotlin/JDK/SDK versions, modules, manifests, tests, CI, existing docs, cross-platform readiness (gradlew/gradlew.bat, .gitattributes, encodings). No file changes. | F2: – | G2: Delivery clarity – avoids rework | H2: Highest | I2: Must | J2: P0 | K2: Repo / tooling | L2: – | M2: – | N2: None | O2: Blocks: LS-003, LS-005, LS-007, LS-008, LS-030, LS-131 Blocked by: – | P2: 1. Discovery report covers all 17 items of master prompt §2.2 2. Zero files changed (git status clean before/after) 3. Toolchain versions and compatibility issues listed 4. Report ends with Approval gate question | Q2: Std DoD: AC met · no hardcoded strings/colours/dims/config · EN + KN strings present · unit/UI tests pass · lint + translation check pass · screenshots EN/KN attached (UI) · docs updated · human PR review & merge · post-merge verified | R2: Use tokens, string resources (EN+KN) and AppConfig only. | S2: N/A (read-only) – verify `git status` unchanged | T2: Read-only: git/GitHub inspection, Figma whoami, network probes | U2: 3 | V2: Medium | W2: Low | X2: Orchestrator | Y2: Yes | Z2: Low | AA2: feature/LS-001-read-only-repository-toolchain-discovery | AD2: Done | AE2: Project owner (human) | AF2: Approval A — report delivered | AG2: P0 assessment delivered 29 Oct 2026 (Claude Doc "LittleStory — P0 Discovery Assessment"): repo docs-only, default branch misconfigured, Figma Make not readable by agents, cloud workspace cannot reach dl.google.com. | AH2: None | AI2: N/A | AJ2: Run on owner's machine via Claude Code CLI. | AK2: NFR-09 | AL2: =AD2&"|"&COUNTIF(AD$2:AD2,AD2)
A3: LS-002 | B3: Task | C3: LS-EPIC-01 | D3: Extract Figma Make design: screen inventory, tokens, specs | E3: Inventory all screens/states of Figma Make file 2DYtUW39GtnsDpUd5jSu6x; extract tokens, typography, components, motion, copy and accessibility gaps. | F3: – | G3: Delivery clarity – avoids rework | H3: Highest | I3: Must | J3: P0 | K3: Design | L3: SCR-01…SCR-18 | M3: Design pack – all screens (docs/design/screens/) | N3: None | O3: Blocks: LS-003, LS-004, LS-008 Blocked by: – | P3: 1. All prototype screens listed with screenshot 2. Tokens JSON produced 3. Component catalogue and per-screen specs written 4. Missing designs identified | Q3: Std DoD: AC met · no hardcoded strings/colours/dims/config · EN + KN strings present · unit/UI tests pass · lint + translation check pass · screenshots EN/KN attached (UI) · docs updated · human PR review & merge · post-merge verified | R3: Use tokens, string resources (EN+KN) and AppConfig only. | S3: Manual review | T3: docs/design/: 22 screenshots, design-tokens.json, LittleStory_Figma_Design_Details.md | U3: 3 | V3: Medium | W3: Low | X3: UI Integration & Visual Regression Engineer | Y3: Yes | Z3: Low | AA3: – (no code) | AD3: Done | AE3: Project owner (human) | AF3: Not required – design pack supplied | AG3: 18 screens / 22 states inventoried; tokens, typography, components, motion, a11y gaps extracted; 5 missing screens identified | AH3: None | AI3: N/A | AJ3: Completed from supplied design pack: LittleStory_Figma_Design_Details.md, design-tokens.json, 22 screenshots. | AK3: NFR-10 | AL3: =AD3&"|"&COUNTIF(AD$2:AD3,AD3)
A4: LS-003 | B4: Task | C4: LS-EPIC-01 | D4: Requirements catalogue, user journeys A–G and edge cases | E4: Write docs/product/* (vision, FR/NFR from the Requirements sheet, journeys A–G incl. language change, edge cases, MVP scope) and docs/design/screen-inventory.md + screen-state-matrix.md. | F4: – | G4: Delivery clarity – avoids rework | H4: High | I4: Must | J4: P1 | K4: Docs | L4: All | M4: Design pack – all screens (docs/design/screens/) | N4: LS-001, LS-002 | O4: Blocks: LS-006 Blocked by: LS-001, LS-002 | P4: 1. Every FR/NFR has ID, MoSCoW, source, screens, acceptance summary 2. Journeys map to SCR IDs 3. Edge cases include Kannada text expansion, empty states, cancel/retry 4. Unverified items marked as assumptions | Q4: Std DoD: AC met · no hardcoded strings/colours/dims/config · EN + KN strings present · unit/UI tests pass · lint + translation check pass · screenshots EN/KN attached (UI) · docs updated · human PR review & merge · post-merge verified | R4: Use tokens, string resources (EN+KN) and AppConfig only. | S4: Doc review | U4: 5 | V4: High | W4: Low | X4: Product Manager / BA | Y4: Yes | Z4: Low | AA4: claude/project-thread-veobz7 | AD4: In Review | AE4: Project owner (human) | AF4: Approval B granted — awaiting owner review of docs PR | AG4: Drafted 29 Oct 2026: docs/product/* | AH4: None | AI4: N/A | AK4: All FR/NFR | AL4: =AD4&"|"&COUNTIF(AD$2:AD4,AD4)
A5: LS-004 | B5: Task | C5: LS-EPIC-01 | D5: Resolve design gaps & open product decisions | E5: Decision log for: LittleKatha→LittleStory rename in assets; 7 design languages vs EN/KN MVP; missing screens (SCR-19…23); app vs story language; reminders scheduling; demo subscription flag; gendered placeholder copy; greeting time-of-day; transition animations; swipe in onboarding. | F5: – | G5: Delivery clarity – avoids rework | H5: High | I5: Must | J5: P1 | K5: Docs / Design | L5: SCR-19…SCR-23 | M5: Design pack – all screens (docs/design/screens/) | N5: LS-002 | O5: Blocks: LS-046, LS-051, LS-111, LS-113, LS-114, LS-115 Blocked by: LS-002 | P5: 1. Each open question in 'Risks & Questions' has an owner decision or explicit deferral 2. Decisions recorded in docs/project-management/decision-log.md 3. Affected tickets updated | Q5: Std DoD: AC met · no hardcoded strings/colours/dims/config · EN + KN strings present · unit/UI tests pass · lint + translation check pass · screenshots EN/KN attached (UI) · docs updated · human PR review & merge · post-merge verified | R5: Use tokens, string resources (EN+KN) and AppConfig only. | S5: Doc review | U5: 2 | V5: Low | W5: Medium | X5: Technical Product Owner | Y5: Yes | Z5: Low | AA5: claude/project-thread-veobz7 | AD5: In Review | AE5: Project owner (human) | AF5: Approval B granted — awaiting owner review of docs PR | AG5: Drafted 29 Oct 2026: docs/project-management/decision-log.md (D10, D13), docs/design/figma-audit.md | AH5: None | AI5: N/A | AJ5: Blocks LS-046, LS-051, LS-111, LS-113, LS-114, LS-115. | AK5: FR-20, FR-22, FR-23, FR-25 | AL5: =AD5&"|"&COUNTIF(AD$2:AD5,AD5)
A6: LS-005 | B6: Task | C6: LS-EPIC-01 | D6: CLAUDE.md and .github/copilot-instructions.md | E6: Agent instructions mirrored for Claude Code and GitHub Copilot: architecture, no-hardcoding, EN/KN localization, testing, cross-platform, approval levels. | F6: – | G6: Delivery clarity – avoids rework | H6: High | I6: Must | J6: P1 | K6: Repo root | L6: – | M6: – | N6: LS-001 | O6: Blocks: – Blocked by: LS-001 | P6: 1. Both files exist with consistent rules 2. Rules reference docs paths 3. Approval levels A–F stated | Q6: Std DoD: AC met · no hardcoded strings/colours/dims/config · EN + KN strings present · unit/UI tests pass · lint + translation check pass · screenshots EN/KN attached (UI) · docs updated · human PR review & merge · post-merge verified | R6: Shared files: CLAUDE.md, .github/copilot-instructions.md Use tokens, string resources (EN+KN) and AppConfig only. | S6: Doc review | U6: 2 | V6: Low | W6: Low | X6: Orchestrator | Y6: Yes | Z6: Medium | AA6: claude/project-thread-veobz7 | AD6: In Review | AE6: Project owner (human) | AF6: Approval B granted — awaiting owner review of docs PR | AG6: Drafted 29 Oct 2026: CLAUDE.md, .github/copilot-instructions.md | AH6: None | AI6: N/A | AK6: NFR-01, NFR-02, NFR-09 | AL6: =AD6&"|"&COUNTIF(AD$2:AD6,AD6)
A7: LS-006 | B7: Task | C7: LS-EPIC-01 | D7: Prompt library (prompts/00–21) and per-ticket prompts | E7: Create prompts listed in the Prompt Library sheet and prompts/tickets/LS-###.md for each ticket with scope, forbidden changes, l10n and stop conditions. | F7: – | G7: Delivery clarity – avoids rework | H7: Medium | I7: Must | J7: P1 | K7: prompts/ | L7: – | M7: – | N7: LS-003, LS-008 | O7: Blocks: – Blocked by: LS-003, LS-008 | P7: 1. All prompt files exist and do not contradict the master prompt 2. Each ticket prompt includes forbidden-hardcoding rule and EN/KN requirement | Q7: Std DoD: AC met · no hardcoded strings/colours/dims/config · EN + KN strings present · unit/UI tests pass · lint + translation check pass · screenshots EN/KN attached (UI) · docs updated · human PR review & merge · post-merge verified | R7: Use tokens, string resources (EN+KN) and AppConfig only. | S7: Doc review | U7: 3 | V7: Medium | W7: Low | X7: Documentation & Jira Backlog Manager | Y7: Yes | Z7: Low | AA7: claude/project-thread-veobz7 | AD7: In Review | AE7: Project owner (human) | AF7: Approval B granted — awaiting owner review of docs PR | AG7: Drafted 29 Oct 2026: prompts/00–21, prompts/tickets/ (P2) | AH7: None | AI7: N/A | AL7: =AD7&"|"&COUNTIF(AD$2:AD7,AD7)
A8: LS-007 | B8: Task | C8: LS-EPIC-01 | D8: Commit backlog workbook and design reference pack to docs/ | E8: Place this workbook at docs/project-management/ and the design pack at docs/design/ (screens/, design-tokens.json, LittleStory_Figma_Design_Details.md) so hyperlinks resolve. | F8: – | G8: Delivery clarity – avoids rework | H8: Medium | I8: Must | J8: P1 | K8: Docs | L8: All | M8: Design pack – all screens (docs/design/screens/) | N8: LS-001 | O8: Blocks: – Blocked by: LS-001 | P8: 1. Workbook opens with all sheets and images 2. Screenshot hyperlinks resolve from docs/project-management/ 3. Committed on a docs branch via PR | Q8: Std DoD: AC met · no hardcoded strings/colours/dims/config · EN + KN strings present · unit/UI tests pass · lint + translation check pass · screenshots EN/KN attached (UI) · docs updated · human PR review & merge · post-merge verified | R8: Use tokens, string resources (EN+KN) and AppConfig only. | S8: Open workbook; click 3 screenshot links | U8: 1 | V8: Low | W8: Low | X8: Documentation & Jira Backlog Manager | Y8: Yes | Z8: Low | AA8: claude/project-thread-veobz7 | AD8: In Review | AE8: Project owner (human) | AF8: Approval B granted — awaiting owner review of docs PR | AG8: Drafted 29 Oct 2026: docs/ (design pack in PR #1) | AH8: None | AI8: N/A | AL8: =AD8&"|"&COUNTIF(AD$2:AD8,AD8)
A9: LS-008 | B9: Task | C9: LS-EPIC-01 | D9: Architecture ADRs (ADR-001…015) | E9: Write ADRs listed in the Architecture Decisions sheet with options, rationale, consequences; status Proposed until owner approval. | F9: – | G9: Delivery clarity – avoids rework | H9: High | I9: Must | J9: P1 | K9: Docs / Architecture | L9: – | M9: – | N9: LS-001, LS-002 | O9: Blocks: LS-006, LS-030, LS-031 Blocked by: LS-001, LS-002 | P9: 1. 15 ADRs in docs/architecture/adr/ 2. Each references affected tickets 3. Owner approves or comments | Q9: Std DoD: AC met · no hardcoded strings/colours/dims/config · EN + KN strings present · unit/UI tests pass · lint + translation check pass · screenshots EN/KN attached (UI) · docs updated · human PR review & merge · post-merge verified | R9: Use tokens, string resources (EN+KN) and AppConfig only. | S9: Doc review | U9: 3 | V9: Medium | W9: Low | X9: Android Principal Architect | Y9: Yes | Z9: Low | AA9: claude/project-thread-veobz7 | AD9: In Review | AE9: Project owner (human) | AF9: Approval B granted — awaiting owner review of docs PR | AG9: Drafted 29 Oct 2026: docs/architecture/adr/ADR-001…018 | AH9: None | AI9: N/A | AK9: NFR-05 | AL9: =AD9&"|"&COUNTIF(AD$2:AD9,AD9)
A10: LS-010 | B10: Story | C10: LS-EPIC-02 | D10: Colour tokens → Compose theme | E10: Implement all colours from design-tokens.json as named tokens: Material3 ColorScheme mapping + LittleStoryColors extension (night, night-surface, success-bg, favourite, story-art gradients, illustration colours). Single light theme with night surfaces (ADR-013). | F10: As a developer, I want every colour as a named token so design changes happen in one place. | G10: Visual fidelity and consistency | H10: High | I10: Must | J10: P2 | K10: :core:designsystem | L10: All | M10: Design pack – all screens (docs/design/screens/) | N10: LS-031 | O10: Blocks: LS-014, LS-015, LS-018, LS-150 Blocked by: LS-031 | P10: 1. Every token in design-tokens.json exists exactly once in :core:designsystem 2. No hex literal outside token files (lint/detekt check) 3. Preview sheet shows all swatches | Q10: Std DoD: AC met · no hardcoded strings/colours/dims/config · EN + KN strings present · unit/UI tests pass · lint + translation check pass · screenshots EN/KN attached (UI) · docs updated · human PR review & merge · post-merge verified | R10: Shared files: core/designsystem/theme/Color.kt Use tokens, string resources (EN+KN) and AppConfig only. | S10: Unit: token map completeness test vs JSON · Screenshot: colour swatch preview | U10: 3 | V10: Medium | W10: Low | X10: Jetpack Compose UI Engineer | Y10: After deps | Z10: High | AA10: feature/LS-010-colour-tokens-compose-theme | AD10: To Do | AE10: Project owner (human) | AF10: Awaiting Approval C | AH10: None | AI10: N/A | AK10: NFR-01, NFR-10 | AL10: =AD10&"|"&COUNTIF(AD$2:AD10,AD10)
A11: LS-011 | B11: Story | C11: LS-EPIC-02 | D11: Typography: DM Sans + Manrope + Kannada fallback, type scale | E11: Bundle DM Sans (400–700) and Manrope (500–800) as res/font (OFL – record licence), add Noto Sans Kannada (OFL) fallback, define type scale from design (onboarding 29/1.12, hero 25/1.12, topbar 17/800, reader 16/1.95, chip 12/600, eyebrow 10/800 +1.6, nav 10/600). Kannada line-height adjustments. | F11: As a Kannada-speaking parent, I want text to render clearly in my script. | G11: Visual fidelity and consistency | H11: High | I11: Must | J11: P2 | K11: :core:designsystem | L11: All | M11: Design pack – all screens (docs/design/screens/) | N11: LS-031 | O11: Blocks: LS-014, LS-015 Blocked by: LS-031 | P11: 1. All text styles from design spec available as theme tokens 2. Kannada renders with correct glyphs in every style 3. Licences listed in Help & about / docs 4. No inline TextStyle in feature code | Q11: Std DoD: AC met · no hardcoded strings/colours/dims/config · EN + KN strings present · unit/UI tests pass · lint + translation check pass · screenshots EN/KN attached (UI) · docs updated · human PR review & merge · post-merge verified | R11: Shared files: core/designsystem/theme/Type.kt, res/font Use tokens, string resources (EN+KN) and AppConfig only. | S11: Screenshot: type specimen EN + KN at font scale 1.0 and 1.5 | U11: 5 | V11: High | W11: Medium | X11: Jetpack Compose UI Engineer | Y11: After deps | Z11: High | AA11: feature/LS-011-typography-dm-sans-manrope-kannada | AD11: To Do | AE11: Project owner (human) | AF11: Awaiting Approval C | AH11: Layout risk | AI11: Missing | AK11: NFR-01, NFR-02 | AL11: =AD11&"|"&COUNTIF(AD$2:AD11,AD11)
A12: LS-012 | B12: Story | C12: LS-EPIC-02 | D12: Shape, spacing, elevation and motion tokens | E12: Radii (lg 24, md 18, sm 13, button 16, hero 26, sheet 32 top, chip 20, avatar 15/19), spacing scale, shadows (shadow, soft, primary-button, hero, create-nav), layout constants (topbar 68, bottom nav 76, content padding 20/16 compact), motion durations (twinkle 2.4/1.7/1.1 s, button .18 s, toggle .2 s, progress .2/.3 s). | F12: – | G12: Visual fidelity and consistency | H12: High | I12: Must | J12: P2 | K12: :core:designsystem | L12: All | M12: Design pack – all screens (docs/design/screens/) | N12: LS-031 | O12: Blocks: LS-015, LS-018 Blocked by: LS-031 | P12: 1. Tokens defined once in designsystem 2. Compact (≤360dp) and tall (≥900dp) variants handled via window size, not hardcoded checks 3. Reduced-motion flag disables infinite twinkle | Q12: Std DoD: AC met · no hardcoded strings/colours/dims/config · EN + KN strings present · unit/UI tests pass · lint + translation check pass · screenshots EN/KN attached (UI) · docs updated · human PR review & merge · post-merge verified | R12: Shared files: core/designsystem/theme/Dimens.kt, Shape.kt, Motion.kt Use tokens, string resources (EN+KN) and AppConfig only. | S12: Unit: token values · Screenshot: spacing/shape preview | U12: 3 | V12: Medium | W12: Low | X12: Jetpack Compose UI Engineer | Y12: After deps | Z12: High | AA12: feature/LS-012-shape-spacing-elevation-and-motion | AD12: To Do | AE12: Project owner (human) | AF12: Awaiting Approval C | AH12: None | AI12: N/A | AK12: NFR-01, NFR-04 | AL12: =AD12&"|"&COUNTIF(AD$2:AD12,AD12)
A13: LS-013 | B13: Story | C13: LS-EPIC-02 | D13: Icon set (21 line icons) as vector drawables | E13: Recreate icons home, compass, plus, book, user, bell, search, heart, download, play, pause, back, chevron, clock, check, close, edit, moon, settings, volume (24×24, 1.8 stroke, round caps) + filled variants for active heart/download. Add proper rewind-15/forward-15 icons (replaces overlapping glyphs). | F13: – | G13: Visual fidelity and consistency | H13: Medium | I13: Must | J13: P2 | K13: :core:designsystem | L13: All | M13: Design pack – all screens (docs/design/screens/) | N13: LS-031 | O13: Blocks: LS-019, LS-094 Blocked by: LS-031 | P13: 1. All icons in res/drawable with consistent naming ic_* 2. Auto-mirroring set where directional (back, chevron) for RTL 3. Icon catalogue preview | Q13: Std DoD: AC met · no hardcoded strings/colours/dims/config · EN + KN strings present · unit/UI tests pass · lint + translation check pass · screenshots EN/KN attached (UI) · docs updated · human PR review & merge · post-merge verified | R13: Use tokens, string resources (EN+KN) and AppConfig only. | S13: Screenshot: icon catalogue | U13: 3 | V13: Medium | W13: Low | X13: Jetpack Compose UI Engineer | Y13: Yes | Z13: Low | AA13: feature/LS-013-icon-set-21-line-icons | AD13: To Do | AE13: Project owner (human) | AF13: Awaiting Approval C | AH13: None | AI13: N/A | AK13: NFR-10 | AL13: =AD13&"|"&COUNTIF(AD$2:AD13,AD13)
A14: LS-014 | B14: Story | C14: LS-EPIC-02 | D14: LittleStory brand mark composable (default + light) | E14: Rebuild the CSS logo symbol (skewed book outline, inner L curve, crescent, yellow ✦) + 'LittleStory' wordmark (Manrope 800, 18sp). Replace all 'LittleKatha' references. Wordmark text from string resource. | F14: – | G14: Visual fidelity and consistency | H14: Medium | I14: Must | J14: P2 | K14: :core:designsystem | L14: SCR-01, SCR-03, SCR-04a, SCR-12, SCR-13 | M14: SCR-01 Onboarding (3 slides) → 01-onboarding-1-every-day-has-a-story.jpg, 02-onboarding-2-your-child-the-hero.jpg, 03-onboarding-3-listen-dream-repeat.jpg SCR-03 Home → 05-home.jpg SCR-04a Discover → 06-discover.jpg SCR-12 My Stories → 14-my-stories.jpg SCR-13 Profile (settings hub) → 15-profile-settings.jpg | N14: LS-010, LS-011 | O14: Blocks: LS-060 Blocked by: LS-010, LS-011 | P14: 1. Brand mark matches screenshot geometry with new name 2. Light variant for night backgrounds 3. No 'LittleKatha' anywhere in code/resources | Q14: Std DoD: AC met · no hardcoded strings/colours/dims/config · EN + KN strings present · unit/UI tests pass · lint + translation check pass · screenshots EN/KN attached (UI) · docs updated · human PR review & merge · post-merge verified | R14: Use tokens, string resources (EN+KN) and AppConfig only. | S14: Screenshot: brand mark default/light | U14: 2 | V14: Low | W14: Low | X14: Jetpack Compose UI Engineer | Y14: Yes | Z14: Low | AA14: feature/LS-014-littlestory-brand-mark-composable-default | AD14: To Do | AE14: Project owner (human) | AF14: Awaiting Approval C | AH14: New strings | AI14: Missing | AJ14: Screenshots still show LittleKatha (pre-rename). | AL14: =AD14&"|"&COUNTIF(AD$2:AD14,AD14)
A15: LS-015 | B15: Story | C15: LS-EPIC-02 | D15: Buttons and IconButton components | E15: Button primary/secondary/ghost (52dp, radius 16, optional leading icon, press scale .98, disabled 45%), IconButton 42dp visual with ≥48dp touch target, active favourite style (#9D3158 on #FFEDF2). | F15: – | G15: Visual fidelity and consistency | H15: High | I15: Must | J15: P2 | K15: :core:designsystem | L15: All | M15: Design pack – all screens (docs/design/screens/) | N15: LS-010, LS-011, LS-012 | O15: Blocks: LS-016, LS-017, LS-018, LS-019, LS-020 Blocked by: LS-010, LS-011, LS-012 | P15: 1. All variants + disabled + pressed previews 2. Touch target ≥48dp 3. contentDescription required parameter for IconButton | Q15: Std DoD: AC met · no hardcoded strings/colours/dims/config · EN + KN strings present · unit/UI tests pass · lint + translation check pass · screenshots EN/KN attached (UI) · docs updated · human PR review & merge · post-merge verified | R15: Use tokens, string resources (EN+KN) and AppConfig only. | S15: Compose UI test: click/disabled · Screenshot EN/KN long label | U15: 3 | V15: Medium | W15: Low | X15: Jetpack Compose UI Engineer | Y15: After deps | Z15: Low | AA15: feature/LS-015-buttons-and-iconbutton-components | AD15: To Do | AE15: Project owner (human) | AF15: Awaiting Approval C | AH15: None | AI15: N/A | AK15: NFR-04 | AL15: =AD15&"|"&COUNTIF(AD$2:AD15,AD15)
A16: LS-016 | B16: Story | C16: LS-EPIC-02 | D16: Form components: text field, select, chips, segmented, toggle, search, tabs | E16: Form card inputs (48dp, radius 13, lavender focus ring), dropdown select, chips single/multi (selected = soft-lavender + check), segmented control, toggle switch (43×25 visual, role switch), search field with clear, pill tabs. | F16: – | G16: Visual fidelity and consistency | H16: High | I16: Must | J16: P2 | K16: :core:designsystem | L16: SCR-02, SCR-04a, SCR-07, SCR-12, SCR-13, SCR-16 | M16: SCR-02 Setup – Child profile → 04-setup-profile.jpg SCR-04a Discover → 06-discover.jpg SCR-07 Create a Story → 07-create-story.jpg, 08-create-story-more-options-and-error.jpg SCR-12 My Stories → 14-my-stories.jpg SCR-13 Profile (settings hub) → 15-profile-settings.jpg SCR-16 Bedtime Reminder → 17-bedtime-reminder.jpg | N16: LS-015 | O16: Blocks: LS-020, LS-061, LS-071, LS-080, LS-100, LS-110 Blocked by: LS-015 | P16: 1. Each component exposes selected/checked semantics 2. Focus states visible 3. Long Kannada labels wrap/scroll without clipping | Q16: Std DoD: AC met · no hardcoded strings/colours/dims/config · EN + KN strings present · unit/UI tests pass · lint + translation check pass · screenshots EN/KN attached (UI) · docs updated · human PR review & merge · post-merge verified | R16: Use tokens, string resources (EN+KN) and AppConfig only. | S16: Compose UI tests for state changes · Screenshot EN/KN | U16: 5 | V16: High | W16: Low | X16: Jetpack Compose UI Engineer | Y16: After deps | Z16: Low | AA16: feature/LS-016-form-components-text-field-select | AD16: To Do | AE16: Project owner (human) | AF16: Awaiting Approval C | AH16: Layout risk | AI16: Missing | AK16: NFR-04 | AL16: =AD16&"|"&COUNTIF(AD$2:AD16,AD16)
A17: LS-017 | B17: Story | C17: LS-EPIC-02 | D17: Feedback components: bottom sheet, dialog, toast, empty state, notes banner, progress bars | E17: Bottom sheet (handle, rows, cancel, dim overlay), centred dialog with success icon, toast/snackbar, empty state, green trust/notes banner, progress bars (reading 3dp, generation gradient, playback slider, storage). | F17: – | G17: Visual fidelity and consistency | H17: High | I17: Must | J17: P2 | K17: :core:designsystem | L17: SCR-04b, SCR-08, SCR-11b, SCR-12, SCR-15, SCR-16, SCR-17 | M17: SCR-04b Discover – No results (empty state) → 06-discover.jpg SCR-08 Generating + Paused → 09-generating.jpg SCR-11b Player – Sleep timer sheet → 13-player-sleep-timer-sheet.jpg SCR-12 My Stories → 14-my-stories.jpg SCR-15 Subscription (demo) + dialog → 16-subscription.jpg SCR-16 Bedtime Reminder → 17-bedtime-reminder.jpg SCR-17 Offline Downloads → 18-offline-downloads.jpg | N17: LS-015 | O17: Blocks: LS-020, LS-060, LS-072, LS-083, LS-092, LS-101, LS-113 Blocked by: LS-015 | P17: 1. Sheet/dialog trap focus and dismiss on back 2. Toast duration from config 3. Progress exposes progress semantics | Q17: Std DoD: AC met · no hardcoded strings/colours/dims/config · EN + KN strings present · unit/UI tests pass · lint + translation check pass · screenshots EN/KN attached (UI) · docs updated · human PR review & merge · post-merge verified | R17: Use tokens, string resources (EN+KN) and AppConfig only. | S17: Compose UI tests · Screenshot EN/KN | U17: 5 | V17: High | W17: Low | X17: Jetpack Compose UI Engineer | Y17: After deps | Z17: Low | AA17: feature/LS-017-feedback-components-bottom-sheet-dialog | AD17: To Do | AE17: Project owner (human) | AF17: Awaiting Approval C | AH17: None | AI17: N/A | AK17: NFR-04 | AL17: =AD17&"|"&COUNTIF(AD$2:AD17,AD17)
A18: LS-018 | B18: Story | C18: LS-EPIC-02 | D18: Story components: StoryArt, StoryCard, ListStoryRow, ContinueCard, SectionHeader, Avatar | E18: StoryArt drawn in Compose (gradient 145°, crescent moon, stars, hill, figure + motifs elephant/cricket/moon/forest/space/festival) driven by story data; StoryCard (2 sizes), ListStoryRow, ContinueCard, SectionHeader, CSS-style Avatar with selected outline. | F18: – | G18: Visual fidelity and consistency | H18: High | I18: Must | J18: P2 | K18: :core:ui | L18: SCR-03, SCR-04a, SCR-05, SCR-06, SCR-09, SCR-10, SCR-11a, SCR-12, SCR-17 | M18: SCR-03 Home → 05-home.jpg SCR-04a Discover → 06-discover.jpg SCR-05 Category (Indian Tales) → 21-category-indian-tales.jpg SCR-06 Story Detail → 22-story-detail.jpg SCR-09 Story Ready → 10-story-ready.jpg SCR-10 Reader → 11-reader.jpg SCR-11a Player → 12-player.jpg SCR-12 My Stories → 14-my-stories.jpg SCR-17 Offline Downloads → 18-offline-downloads.jpg | N18: LS-010, LS-012, LS-015 | O18: Blocks: LS-020, LS-070, LS-071, LS-073, LS-074, LS-084, LS-090, LS-092, LS-100, LS-101 Blocked by: LS-010, LS-012, LS-015 | P18: 1. All six motifs render matching screenshots 2. Art colours come from tokens/story data, not literals 3. Cards announce title, category, duration, favourite state | Q18: Std DoD: AC met · no hardcoded strings/colours/dims/config · EN + KN strings present · unit/UI tests pass · lint + translation check pass · screenshots EN/KN attached (UI) · docs updated · human PR review & merge · post-merge verified | R18: Use tokens, string resources (EN+KN) and AppConfig only. | S18: Screenshot: each motif + card variants EN/KN long title | U18: 8 | V18: Very High | W18: Medium | X18: Jetpack Compose UI Engineer | Y18: After deps | Z18: Low | AA18: feature/LS-018-story-components-storyart-storycard-liststoryrow | AD18: To Do | AE18: Project owner (human) | AF18: Awaiting Approval C | AH18: Layout risk | AI18: Missing | AJ18: ADR-010 (Canvas vs vector). | AK18: NFR-10 | AL18: =AD18&"|"&COUNTIF(AD$2:AD18,AD18)
A19: LS-019 | B19: Story | C19: LS-EPIC-02 | D19: Navigation chrome: TopBar, BottomNav, sticky action bars | E19: TopBar (back or brand, centred title, right action, 68dp), BottomNav 5 tabs with active pill and raised Create tile (48×40, 5dp ring), sticky single/dual action bars, window insets. | F19: – | G19: Visual fidelity and consistency | H19: High | I19: Must | J19: P2 | K19: :core:ui | L19: All | M19: Design pack – all screens (docs/design/screens/) | N19: LS-013, LS-015 | O19: Blocks: LS-020, LS-050 Blocked by: LS-013, LS-015 | P19: 1. BottomNav labels fit in Kannada at 10sp (or approved fallback) 2. Insets correct with edge-to-edge 3. Selected tab announced | Q19: Std DoD: AC met · no hardcoded strings/colours/dims/config · EN + KN strings present · unit/UI tests pass · lint + translation check pass · screenshots EN/KN attached (UI) · docs updated · human PR review & merge · post-merge verified | R19: Use tokens, string resources (EN+KN) and AppConfig only. | S19: Screenshot EN/KN · UI test tab selection | U19: 3 | V19: Medium | W19: Low | X19: Jetpack Compose UI Engineer | Y19: After deps | Z19: Medium | AA19: feature/LS-019-navigation-chrome-topbar-bottomnav-sticky | AD19: To Do | AE19: Project owner (human) | AF19: Awaiting Approval C | AH19: Layout risk | AI19: Missing | AK19: NFR-04 | AL19: =AD19&"|"&COUNTIF(AD$2:AD19,AD19)
A20: LS-020 | B20: Task | C20: LS-EPIC-02 | D20: Design-system catalogue & screenshot baselines (EN/KN) | E20: Preview catalogue screen (debug only) + screenshot baselines for all components in EN, KN and pseudo-locale. | F20: – | G20: Visual fidelity and consistency | H20: Medium | I20: Should | J20: P2 | K20: :core:designsystem | L20: – | M20: – | N20: LS-015, LS-016, LS-017, LS-018, LS-019, LS-035 | O20: Blocks: – Blocked by: LS-015, LS-016, LS-017, LS-018, LS-019, LS-035 | P20: 1. Baselines committed and reviewed by owner 2. Catalogue excluded from release build | Q20: Std DoD: AC met · no hardcoded strings/colours/dims/config · EN + KN strings present · unit/UI tests pass · lint + translation check pass · screenshots EN/KN attached (UI) · docs updated · human PR review & merge · post-merge verified | R20: Use tokens, string resources (EN+KN) and AppConfig only. | S20: Screenshot tests | U20: 3 | V20: Medium | W20: Low | X20: UI Integration & Visual Regression Engineer | Y20: After deps | Z20: Low | AA20: feature/LS-020-design-system-catalogue-screenshot-baselines | AD20: To Do | AE20: Project owner (human) | AF20: Awaiting Approval C | AH20: None | AI20: N/A | AK20: NFR-10 | AL20: =AD20&"|"&COUNTIF(AD$2:AD20,AD20)
A21: LS-030 | B21: Task | C21: LS-EPIC-03 | D21: Project baseline: Gradle wrapper, version catalog, JDK toolchain, .gitattributes | E21: Verify/establish gradlew + gradlew.bat (exec bit), libs.versions.toml, JDK toolchain, minSdk/targetSdk decision, .gitattributes (LF; CRLF for .bat), .gitignore (local.properties, IDE), UTF-8. | F21: – | G21: Maintainable, testable base | H21: Highest | I21: Must | J21: P2 | K21: Build | L21: – | M21: – | N21: LS-001, LS-008, LS-009, LS-039 | O21: Blocks: LS-031, LS-130, LS-132 Blocked by: LS-001, LS-008 | P21: 1. ./gradlew and gradlew.bat assembleDebug succeed on macOS and Windows 2. No machine-specific paths committed 3. No whole-file line-ending diffs | Q21: Std DoD: AC met · no hardcoded strings/colours/dims/config · EN + KN strings present · unit/UI tests pass · lint + translation check pass · screenshots EN/KN attached (UI) · docs updated · human PR review & merge · post-merge verified | R21: Shared files: settings.gradle.kts, gradle/libs.versions.toml, .gitattributes Use tokens, string resources (EN+KN) and AppConfig only. | S21: Build on both OSes | U21: 3 | V21: Medium | W21: Low | X21: Build, Gradle & CI/CD Engineer | Y21: No | Z21: High | AA21: feature/LS-030-project-baseline-gradle-wrapper-version | AD21: To Do | AE21: Project owner (human) | AF21: Awaiting Approval C | AH21: None | AI21: N/A | AK21: NFR-09 | AL21: =AD21&"|"&COUNTIF(AD$2:AD21,AD21)
A22: LS-031 | B22: Task | C22: LS-EPIC-03 | D22: Module structure + build-logic convention plugins | E22: Create the 14 modules proposed in ADR-002 (:app, build-logic, :core:designsystem, :core:ui, :core:common, :domain, :data, :feature:onboarding/home/discover/create/reader/library/settings) and convention plugins for shared Android/Compose/test config. | F22: – | G22: Maintainable, testable base | H22: Highest | I22: Must | J22: P2 | K22: Build | L22: – | M22: – | N22: LS-030, LS-008 | O22: Blocks: LS-010, LS-011, LS-012, LS-013, LS-032, LS-033, LS-034, LS-035, LS-037, LS-040, LS-050 Blocked by: LS-030, LS-008 | P22: 1. Modules compile with dependency rules enforced 2. No duplicated Gradle blocks 3. Module graph documented | Q22: Std DoD: AC met · no hardcoded strings/colours/dims/config · EN + KN strings present · unit/UI tests pass · lint + translation check pass · screenshots EN/KN attached (UI) · docs updated · human PR review & merge · post-merge verified | R22: Shared files: settings.gradle.kts, build-logic/ Use tokens, string resources (EN+KN) and AppConfig only. | S22: Build; dependency-rule check | U22: 5 | V22: High | W22: Low | X22: Android Principal Architect | Y22: No | Z22: High | AA22: feature/LS-031-module-structure-build-logic-convention | AD22: To Do | AE22: Project owner (human) | AF22: Awaiting Approval C | AH22: None | AI22: N/A | AK22: NFR-05 | AL22: =AD22&"|"&COUNTIF(AD$2:AD22,AD22)
A23: LS-032 | B23: Task | C23: LS-EPIC-03 | D23: Dependency injection (Hilt) and Application entry | E23: Hilt setup, Application class, MainActivity single-activity host. | F23: – | G23: Maintainable, testable base | H23: High | I23: Must | J23: P2 | K23: :app | L23: – | M23: – | N23: LS-031 | O23: Blocks: – Blocked by: LS-031 | P23: 1. App launches to placeholder 2. Hilt test runner configured | Q23: Std DoD: AC met · no hardcoded strings/colours/dims/config · EN + KN strings present · unit/UI tests pass · lint + translation check pass · screenshots EN/KN attached (UI) · docs updated · human PR review & merge · post-merge verified | R23: Shared files: app/build.gradle.kts, AndroidManifest.xml Use tokens, string resources (EN+KN) and AppConfig only. | S23: Instrumented smoke test | U23: 2 | V23: Low | W23: Low | X23: Senior Kotlin Engineer | Y23: After deps | Z23: High | AA23: feature/LS-032-dependency-injection-hilt-and-application | AD23: To Do | AE23: Project owner (human) | AF23: Awaiting Approval C | AH23: None | AI23: N/A | AL23: =AD23&"|"&COUNTIF(AD$2:AD23,AD23)
A24: LS-033 | B24: Task | C24: LS-EPIC-03 | D24: Central configuration & feature flags (AppConfig) | E24: Named config objects: validation limits (story text 500, age 3–12), simulated timings (generation +4%/120 ms, player tick), sleep-timer options, speed steps, storage quota (1 GB), toast duration, default language; feature flags: demoSubscription, simulatedAudio, simulatedDownloads, reminders; BuildConfig for version/env. | F24: – | G24: Maintainable, testable base | H24: High | I24: Must | J24: P2 | K24: :core:common | L24: – | M24: – | N24: LS-031 | O24: Blocks: LS-080, LS-082, LS-092, LS-113, LS-150 Blocked by: LS-031 | P24: 1. No magic numbers in feature code for these values 2. Flags toggle features without code edits elsewhere 3. docs/architecture/configuration-and-constants.md lists every value | Q24: Std DoD: AC met · no hardcoded strings/colours/dims/config · EN + KN strings present · unit/UI tests pass · lint + translation check pass · screenshots EN/KN attached (UI) · docs updated · human PR review & merge · post-merge verified | R24: Shared files: core/common/config/AppConfig.kt Use tokens, string resources (EN+KN) and AppConfig only. | S24: Unit: config defaults | U24: 3 | V24: Medium | W24: Low | X24: Senior Kotlin Engineer | Y24: After deps | Z24: Medium | AA24: feature/LS-033-central-configuration-feature-flags-appconfig | AD24: To Do | AE24: Project owner (human) | AF24: Awaiting Approval C | AH24: None | AI24: N/A | AK24: NFR-01 | AL24: =AD24&"|"&COUNTIF(AD$2:AD24,AD24)
A25: LS-034 | B25: Task | C25: LS-EPIC-03 | D25: Lint & static analysis rules (hardcoding, translations) | E25: Lint: HardcodedText, MissingTranslation, SetTextI18n as errors; Detekt/ktlint (if approved) with MagicNumber and custom rule forbidding Color(0x…)/raw .dp in feature modules. | F25: – | G25: Maintainable, testable base | H25: High | I25: Must | J25: P2 | K25: Build | L25: – | M25: – | N25: LS-031 | O25: Blocks: LS-125, LS-130 Blocked by: LS-031 | P25: 1. Introducing a hardcoded string or hex colour in a feature fails the build 2. Baseline file empty | Q25: Std DoD: AC met · no hardcoded strings/colours/dims/config · EN + KN strings present · unit/UI tests pass · lint + translation check pass · screenshots EN/KN attached (UI) · docs updated · human PR review & merge · post-merge verified | R25: Shared files: lint.xml, detekt.yml Use tokens, string resources (EN+KN) and AppConfig only. | S25: Negative test: deliberately add hardcoded string → build fails | U25: 3 | V25: Medium | W25: Low | X25: Code Quality & Maintainability Reviewer | Y25: After deps | Z25: Medium | AA25: feature/LS-034-lint-static-analysis-rules-hardcoding | AD25: To Do | AE25: Project owner (human) | AF25: Awaiting Approval C | AH25: None | AI25: N/A | AK25: NFR-01, NFR-02 | AL25: =AD25&"|"&COUNTIF(AD$2:AD25,AD25)
A26: LS-035 | B26: Task | C26: LS-EPIC-03 | D26: Test infrastructure (unit, UI, screenshot) | E26: JUnit, MockK, coroutines-test, Turbine, Compose UI test, screenshot tool per ADR-011; locale-parameterised test helpers (en, kn, en-XA). | F26: – | G26: Maintainable, testable base | H26: High | I26: Must | J26: P2 | K26: Build / test | L26: – | M26: – | N26: LS-031 | O26: Blocks: LS-020, LS-122 Blocked by: LS-031 | P26: 1. Sample test of each kind passes on CI 2. Screenshot tests run per locale | Q26: Std DoD: AC met · no hardcoded strings/colours/dims/config · EN + KN strings present · unit/UI tests pass · lint + translation check pass · screenshots EN/KN attached (UI) · docs updated · human PR review & merge · post-merge verified | R26: Shared files: gradle/libs.versions.toml Use tokens, string resources (EN+KN) and AppConfig only. | S26: CI run | U26: 3 | V26: Medium | W26: Low | X26: Android Testing & Automation Engineer | Y26: After deps | Z26: Medium | AA26: feature/LS-035-test-infrastructure-unit-ui-screenshot | AD26: To Do | AE26: Project owner (human) | AF26: Awaiting Approval C | AH26: None | AI26: N/A | AL26: =AD26&"|"&COUNTIF(AD$2:AD26,AD26)
A27: LS-036 | B27: Task | C27: LS-EPIC-03 | D27: Mock data sources: per-language JSON assets + loader | E27: assets/mock/stories_{en,kn}.json, categories, notifications, plans, profiles; loader with English fallback; stable IDs identical across languages; seed covers long titles, missing KN translation, empty library. | F27: – | G27: Maintainable, testable base | H27: High | I27: Must | J27: P2 | K27: :data | L27: All | M27: Design pack – all screens (docs/design/screens/) | N27: LS-037 | O27: Blocks: LS-044, LS-070, LS-071, LS-073, LS-074, LS-082, LS-090, LS-112 Blocked by: LS-037 | P27: 1. Six design stories + reader pages load in EN 2. Missing KN entry falls back to EN 3. No mock content in composables/ViewModels | Q27: Std DoD: AC met · no hardcoded strings/colours/dims/config · EN + KN strings present · unit/UI tests pass · lint + translation check pass · screenshots EN/KN attached (UI) · docs updated · human PR review & merge · post-merge verified | R27: Use tokens, string resources (EN+KN) and AppConfig only. | S27: Unit: loader + fallback | U27: 5 | V27: High | W27: Low | X27: Data & Persistence Engineer | Y27: After deps | Z27: Low | AA27: feature/LS-036-mock-data-sources-per-language | AD27: To Do | AE27: Project owner (human) | AF27: Awaiting Approval C | AH27: Content | AI27: Missing | AK27: NFR-06, FR-21 | AL27: =AD27&"|"&COUNTIF(AD$2:AD27,AD27)
A28: LS-037 | B28: Task | C28: LS-EPIC-03 | D28: Domain models & repository interfaces | E28: Story, StoryPage, Category, ChildProfile, Avatar, StoryCreationRequest, GenerationState, ReadingProgress, PlaybackState, Download, ReminderSettings, Notification, Plan, SupportedLanguage; repository interfaces (Catalog, Profiles, Favourites, Library, Generation, Progress, Downloads, Preferences, Notifications, Subscription). | F28: – | G28: Maintainable, testable base | H28: Highest | I28: Must | J28: P2 | K28: :domain | L28: – | M28: – | N28: LS-031 | O28: Blocks: LS-036, LS-038, LS-082, LS-140 Blocked by: LS-031 | P28: 1. Domain has no Android/Compose imports 2. Models documented in docs/architecture/data-models.md | Q28: Std DoD: AC met · no hardcoded strings/colours/dims/config · EN + KN strings present · unit/UI tests pass · lint + translation check pass · screenshots EN/KN attached (UI) · docs updated · human PR review & merge · post-merge verified | R28: Shared files: domain/model/*, domain/repository/* Use tokens, string resources (EN+KN) and AppConfig only. | S28: Unit: model validation | U28: 5 | V28: High | W28: Low | X28: Android Principal Architect | Y28: After deps | Z28: High | AA28: feature/LS-037-domain-models-repository-interfaces | AD28: To Do | AE28: Project owner (human) | AF28: Awaiting Approval C | AH28: None | AI28: N/A | AK28: NFR-05 | AL28: =AD28&"|"&COUNTIF(AD$2:AD28,AD28)
A29: LS-038 | B29: Task | C29: LS-EPIC-03 | D29: Local persistence (DataStore + Room per ADR-004) | E29: DataStore: settings, active profile, language default, reader text size; Room: profiles, favourites, created stories, progress, downloads, notifications read state. | F29: – | G29: Maintainable, testable base | H29: High | I29: Must | J29: P2 | K29: :data | L29: – | M29: – | N29: LS-037 | O29: Blocks: LS-051, LS-062, LS-075, LS-091, LS-101, LS-111 Blocked by: LS-037 | P29: 1. Data survives process death 2. In-memory Room tests 3. No child data logged | Q29: Std DoD: AC met · no hardcoded strings/colours/dims/config · EN + KN strings present · unit/UI tests pass · lint + translation check pass · screenshots EN/KN attached (UI) · docs updated · human PR review & merge · post-merge verified | R29: Use tokens, string resources (EN+KN) and AppConfig only. | S29: Room DAO tests · DataStore tests | U29: 5 | V29: High | W29: Low | X29: Data & Persistence Engineer | Y29: After deps | Z29: Medium | AA29: feature/LS-038-local-persistence-datastore-room-per | AD29: To Do | AE29: Project owner (human) | AF29: Awaiting Approval C | AH29: None | AI29: N/A | AK29: NFR-07, NFR-11 | AL29: =AD29&"|"&COUNTIF(AD$2:AD29,AD29)
A30: LS-040 | B30: Story | C30: LS-EPIC-14 | D30: Localization foundation: EN/KN resources, locale switching, language registry, UiText | E30: values/ + values-kn/ per module, res/xml/locales_config.xml, manifest reference, AppCompatDelegate.setApplicationLocales, SupportedLanguage registry (tag, native name 'English'/'ಕನ್ನಡ', enabled), UiText sealed type for ViewModels, supportsRtl. | F30: As a parent, I want to use the app in Kannada so my family understands it. | G30: Reach Kannada-speaking families | H30: Highest | I30: Must | J30: P2 | K30: :core:common / :core:ui | L30: All | M30: Design pack – all screens (docs/design/screens/) | N30: LS-031 | O30: Blocks: LS-041, LS-042, LS-043, LS-045, LS-046, LS-048, LS-081, LS-150 Blocked by: LS-031 | P30: 1. Switching language updates UI without restart and persists 2. Registry is the only list of languages 3. ViewModels hold no translated text | Q30: Std DoD: AC met · no hardcoded strings/colours/dims/config · EN + KN strings present · unit/UI tests pass · lint + translation check pass · screenshots EN/KN attached (UI) · docs updated · human PR review & merge · post-merge verified | R30: Shared files: locales_config.xml, SupportedLanguage.kt Use tokens, string resources (EN+KN) and AppConfig only. | S30: Unit: registry · UI: switch EN→KN→EN | U30: 5 | V30: High | W30: Low | X30: Accessibility, Localization & i18n Engineer | Y30: After deps | Z30: High | AA30: feature/LS-040-localization-foundation-en-kn-resources | AD30: To Do | AE30: Project owner (human) | AF30: Awaiting Approval C | AH30: New strings | AI30: Missing | AK30: FR-20, NFR-02, NFR-03 | AL30: =AD30&"|"&COUNTIF(AD$2:AD30,AD30)
A31: LS-041 | B31: Task | C31: LS-EPIC-14 | D31: Translation completeness check (key & format-arg parity) in Gradle/CI | E31: Task that fails when a key in values/ is missing in values-kn/ (and any future values-xx/) or format args differ; also checks mock JSON has every story ID per language or explicit fallback. | F31: – | G31: Reach Kannada-speaking families | H31: High | I31: Must | J31: P2 | K31: Build | L31: – | M31: – | N31: LS-040 | O31: Blocks: LS-048, LS-130 Blocked by: LS-040 | P31: 1. Missing KN key fails CI with clear message 2. Mismatched %1$s fails CI | Q31: Std DoD: AC met · no hardcoded strings/colours/dims/config · EN + KN strings present · unit/UI tests pass · lint + translation check pass · screenshots EN/KN attached (UI) · docs updated · human PR review & merge · post-merge verified | R31: Use tokens, string resources (EN+KN) and AppConfig only. | S31: Negative tests | U31: 2 | V31: Low | W31: Low | X31: Build, Gradle & CI/CD Engineer | Y31: After deps | Z31: Low | AA31: feature/LS-041-translation-completeness-check-key-format | AD31: To Do | AE31: Project owner (human) | AF31: Awaiting Approval C | AH31: None | AI31: N/A | AK31: NFR-02 | AL31: =AD31&"|"&COUNTIF(AD$2:AD31,AD31)
A32: LS-042 | B32: Task | C32: LS-EPIC-14 | D32: Pseudo-locales & RTL readiness | E32: Enable en-XA/ar-XB in debug; start/end everywhere; autoMirrored icons. | F32: – | G32: Reach Kannada-speaking families | H32: Medium | I32: Should | J32: P2 | K32: :app | L32: – | M32: – | N32: LS-040 | O32: Blocks: – Blocked by: LS-040 | P32: 1. Key screens render under en-XA without clipping 2. ar-XB mirrors layout correctly | Q32: Std DoD: AC met · no hardcoded strings/colours/dims/config · EN + KN strings present · unit/UI tests pass · lint + translation check pass · screenshots EN/KN attached (UI) · docs updated · human PR review & merge · post-merge verified | R32: Use tokens, string resources (EN+KN) and AppConfig only. | S32: Screenshot en-XA, ar-XB | U32: 1 | V32: Low | W32: Low | X32: Accessibility, Localization & i18n Engineer | Y32: Yes | Z32: Low | AA32: feature/LS-042-pseudo-locales-rtl-readiness | AD32: To Do | AE32: Project owner (human) | AF32: Awaiting Approval C | AH32: None | AI32: N/A | AK32: NFR-03 | AL32: =AD32&"|"&COUNTIF(AD$2:AD32,AD32)
A33: LS-043 | B33: Task | C33: LS-EPIC-14 | D33: Kannada UI strings (draft) + glossary | E33: Populate values-kn for all keys in the Translation Tracking sheet; docs/localization/glossary.md for child-friendly terms (story, bedtime, favourite…). Mark every KN value 'Needs native review'. | F33: – | G33: Reach Kannada-speaking families | H33: High | I33: Must | J33: P6 | K33: Resources | L33: All | M33: Design pack – all screens (docs/design/screens/) | N33: LS-040 | O33: Blocks: LS-047 Blocked by: LS-040 | P33: 1. 100% key coverage in KN 2. Glossary covers recurring terms 3. Translation Tracking sheet updated | Q33: Std DoD: AC met · no hardcoded strings/colours/dims/config · EN + KN strings present · unit/UI tests pass · lint + translation check pass · screenshots EN/KN attached (UI) · docs updated · human PR review & merge · post-merge verified | R33: Use tokens, string resources (EN+KN) and AppConfig only. | S33: Translation completeness check | U33: 5 | V33: High | W33: Medium | X33: Accessibility, Localization & i18n Engineer | Y33: Yes | Z33: Low | AA33: feature/LS-043-kannada-ui-strings-draft-glossary | AD33: To Do | AE33: Project owner (human) | AF33: Awaiting Approval C | AH33: New strings | AI33: Missing | AK33: NFR-02 | AL33: =AD33&"|"&COUNTIF(AD$2:AD33,AD33)
A34: LS-044 | B34: Task | C34: LS-EPIC-14 | D34: Kannada mock story content | E34: Kannada titles, synopses, lessons, reader pages for the six design stories and notifications; stable IDs. | F34: – | G34: Reach Kannada-speaking families | H34: High | I34: Must | J34: P4 | K34: :data assets | L34: SCR-06, SCR-09, SCR-10 | M34: SCR-06 Story Detail → 22-story-detail.jpg SCR-09 Story Ready → 10-story-ready.jpg SCR-10 Reader → 11-reader.jpg | N34: LS-036 | O34: Blocks: LS-047 Blocked by: LS-036 | P34: 1. All six stories readable in KN 2. One deliberate gap tests EN fallback (test data only) | Q34: Std DoD: AC met · no hardcoded strings/colours/dims/config · EN + KN strings present · unit/UI tests pass · lint + translation check pass · screenshots EN/KN attached (UI) · docs updated · human PR review & merge · post-merge verified | R34: Use tokens, string resources (EN+KN) and AppConfig only. | S34: Unit: content loader per locale | U34: 3 | V34: Medium | W34: Medium | X34: Accessibility, Localization & i18n Engineer | Y34: Yes | Z34: Low | AA34: feature/LS-044-kannada-mock-story-content | AD34: To Do | AE34: Project owner (human) | AF34: Awaiting Approval C | AH34: Content | AI34: Missing | AK34: FR-21 | AL34: =AD34&"|"&COUNTIF(AD$2:AD34,AD34)
A35: LS-045 | B35: Story | C35: LS-EPIC-14 | D35: Language selection in Setup (registry-driven) | E35: Setup language select lists only enabled registry languages (English, ಕನ್ನಡ) in their own script; selection sets app language and child default story language per LS-004 decision. | F35: – | G35: Reach Kannada-speaking families | H35: High | I35: Must | J35: P3 | K35: :feature:onboarding | L35: SCR-02 | M35: SCR-02 Setup – Child profile → 04-setup-profile.jpg | N35: LS-040, LS-061 | O35: Blocks: – Blocked by: LS-040, LS-061 | P35: 1. Only EN/KN shown 2. Choosing ಕನ್ನಡ switches UI immediately 3. Selection persists | Q35: Std DoD: AC met · no hardcoded strings/colours/dims/config · EN + KN strings present · unit/UI tests pass · lint + translation check pass · screenshots EN/KN attached (UI) · docs updated · human PR review & merge · post-merge verified | R35: Use tokens, string resources (EN+KN) and AppConfig only. UiState + StateFlow; UiText for messages; preview in EN/KN. | S35: UI test | U35: 2 | V35: Low | W35: Low | X35: Jetpack Compose UI Engineer | Y35: After deps | Z35: Low | AA35: feature/LS-045-language-selection-in-setup-registry | AD35: To Do | AE35: Project owner (human) | AF35: Awaiting Approval C | AH35: New strings | AI35: Missing | AK35: FR-20 | AL35: =AD35&"|"&COUNTIF(AD$2:AD35,AD35)
A36: LS-046 | B36: Story | C36: LS-EPIC-14 | D36: Language preferences screen (from Profile) | E36: New simple screen (design missing – SCR-20) listing registry languages with check; optionally separate story-language default per LS-004. | F36: – | G36: Reach Kannada-speaking families | H36: High | I36: Must | J36: P6 | K36: :feature:settings | L36: SCR-20, SCR-13 | M36: SCR-20 Language preferences → no design (missing) SCR-13 Profile (settings hub) → 15-profile-settings.jpg | N36: LS-004, LS-040, LS-110 | O36: Blocks: – Blocked by: LS-004, LS-040, LS-110 | P36: 1. Reachable from Profile → Language preferences 2. Subtitle on Profile reflects current choice 3. Works with future languages without code change | Q36: Std DoD: AC met · no hardcoded strings/colours/dims/config · EN + KN strings present · unit/UI tests pass · lint + translation check pass · screenshots EN/KN attached (UI) · docs updated · human PR review & merge · post-merge verified | R36: Use tokens, string resources (EN+KN) and AppConfig only. UiState + StateFlow; UiText for messages; preview in EN/KN. | S36: UI test · Screenshot EN/KN | U36: 3 | V36: Medium | W36: Medium | X36: Jetpack Compose UI Engineer | Y36: After deps | Z36: Low | AA36: feature/LS-046-language-preferences-screen-from-profile | AD36: To Do | AE36: Project owner (human) | AF36: Awaiting Approval C | AH36: New strings | AI36: Missing | AJ36: Design missing – reuse settings-row pattern; owner to approve. | AK36: FR-20 | AL36: =AD36&"|"&COUNTIF(AD$2:AD36,AD36)
A37: LS-047 | B37: Task | C37: LS-EPIC-14 | D37: Native Kannada review & sign-off | E37: Fluent Kannada reviewer checks all strings and mock content in context (screenshots), updates statuses to Approved. | F37: – | G37: Reach Kannada-speaking families | H37: High | I37: Must | J37: P7 | K37: Resources | L37: All | M37: Design pack – all screens (docs/design/screens/) | N37: LS-043, LS-044, LS-122 | O37: Blocks: LS-133 Blocked by: LS-043, LS-044, LS-122 | P37: 1. All KN rows 'Approved' 2. Issues logged and fixed | Q37: Std DoD: AC met · no hardcoded strings/colours/dims/config · EN + KN strings present · unit/UI tests pass · lint + translation check pass · screenshots EN/KN attached (UI) · docs updated · human PR review & merge · post-merge verified | R37: Use tokens, string resources (EN+KN) and AppConfig only. | S37: Manual review | U37: 3 | V37: Medium | W37: High | X37: Accessibility, Localization & i18n Engineer | Y37: After deps | Z37: Low | AA37: feature/LS-047-native-kannada-review-sign-off | AD37: To Do | AE37: Project owner (human) | AF37: Awaiting Approval C | AH37: None | AI37: N/A | AJ37: Needs a named reviewer (risk R-12). | AK37: NFR-02 | AL37: =AD37&"|"&COUNTIF(AD$2:AD37,AD37)
A38: LS-048 | B38: Task | C38: LS-EPIC-14 | D38: 'How to add a new language' guide + prompt | E38: docs/localization/adding-a-new-language.md and prompts/20_ADD_NEW_LANGUAGE_PROMPT.md; dry-run with a pseudo language to prove no feature-code change. | F38: – | G38: Reach Kannada-speaking families | H38: Medium | I38: Must | J38: P8 | K38: Docs | L38: – | M38: – | N38: LS-040, LS-041 | O38: Blocks: – Blocked by: LS-040, LS-041 | P38: 1. Dry run adds language with resources + registry + locales_config only | Q38: Std DoD: AC met · no hardcoded strings/colours/dims/config · EN + KN strings present · unit/UI tests pass · lint + translation check pass · screenshots EN/KN attached (UI) · docs updated · human PR review & merge · post-merge verified | R38: Use tokens, string resources (EN+KN) and AppConfig only. | S38: Dry-run evidence | U38: 1 | V38: Low | W38: Low | X38: Accessibility, Localization & i18n Engineer | Y38: Yes | Z38: Low | AA38: feature/LS-048-how-to-add-a-new | AD38: To Do | AE38: Project owner (human) | AF38: Awaiting Approval B | AH38: None | AI38: N/A | AK38: NFR-03 | AL38: =AD38&"|"&COUNTIF(AD$2:AD38,AD38)
A39: LS-050 | B39: Story | C39: LS-EPIC-04 | D39: Navigation graph with typed routes for all screens | E39: Typed destinations for SCR-01…SCR-22; bottom-nav tabs with saved state; back behaviour per screen spec; deep-link targets for notifications. | F39: – | G39: Coherent app structure | H39: Highest | I39: Must | J39: P3 | K39: :app / navigation | L39: All | M39: Design pack – all screens (docs/design/screens/) | N39: LS-019, LS-031 | O39: Blocks: LS-051, LS-052, LS-060, LS-061, LS-070, LS-071, LS-073, LS-074, LS-080, LS-090, LS-110, LS-112 Blocked by: LS-019, LS-031 | P39: 1. All prototype navigation paths work 2. Back from each screen matches spec 3. Routes defined in one place | Q39: Std DoD: AC met · no hardcoded strings/colours/dims/config · EN + KN strings present · unit/UI tests pass · lint + translation check pass · screenshots EN/KN attached (UI) · docs updated · human PR review & merge · post-merge verified | R39: Shared files: AppNavHost.kt, Destinations.kt Use tokens, string resources (EN+KN) and AppConfig only. | S39: UI navigation tests | U39: 5 | V39: High | W39: Low | X39: Navigation & Application State Engineer | Y39: No | Z39: High | AA39: feature/LS-050-navigation-graph-with-typed-routes | AD39: To Do | AE39: Project owner (human) | AF39: Awaiting Approval C | AH39: None | AI39: N/A | AK39: NFR-01 | AL39: =AD39&"|"&COUNTIF(AD$2:AD39,AD39)
A40: LS-051 | B40: Story | C40: LS-EPIC-04 | D40: Splash screen & first-run routing | E40: core-splashscreen; first-run flag routes to Onboarding else Home. | F40: – | G40: Coherent app structure | H40: High | I40: Must | J40: P3 | K40: :app | L40: SCR-19 | M40: SCR-19 Splash / launch → no design (missing) | N40: LS-004, LS-050, LS-038 | O40: Blocks: – Blocked by: LS-004, LS-050, LS-038 | P40: 1. First launch → Onboarding; later → Home 2. No blank frame | Q40: Std DoD: AC met · no hardcoded strings/colours/dims/config · EN + KN strings present · unit/UI tests pass · lint + translation check pass · screenshots EN/KN attached (UI) · docs updated · human PR review & merge · post-merge verified | R40: Use tokens, string resources (EN+KN) and AppConfig only. | S40: UI test with cleared data | U40: 2 | V40: Low | W40: Low | X40: Navigation & Application State Engineer | Y40: After deps | Z40: Low | AA40: feature/LS-051-splash-screen-first-run-routing | AD40: To Do | AE40: Project owner (human) | AF40: Awaiting Approval C | AH40: None | AI40: N/A | AJ40: Design missing – needs owner approval of splash spec. | AK40: FR-25 | AL40: =AD40&"|"&COUNTIF(AD$2:AD40,AD40)
A41: LS-052 | B41: Task | C41: LS-EPIC-04 | D41: Edge-to-edge & system bar styling | E41: Dark icons on cream screens, light icons on night screens (Onboarding, Generating, Player, Subscription hero). | F41: – | G41: Coherent app structure | H41: Medium | I41: Must | J41: P3 | K41: :core:ui | L41: All | M41: Design pack – all screens (docs/design/screens/) | N41: LS-050 | O41: Blocks: – Blocked by: LS-050 | P41: 1. Status/nav bar icons legible on every screen | Q41: Std DoD: AC met · no hardcoded strings/colours/dims/config · EN + KN strings present · unit/UI tests pass · lint + translation check pass · screenshots EN/KN attached (UI) · docs updated · human PR review & merge · post-merge verified | R41: Use tokens, string resources (EN+KN) and AppConfig only. | S41: Screenshot per screen | U41: 2 | V41: Low | W41: Low | X41: Jetpack Compose UI Engineer | Y41: After deps | Z41: Low | AA41: feature/LS-052-edge-to-edge-system-bar | AD41: To Do | AE41: Project owner (human) | AF41: Awaiting Approval C | AH41: None | AI41: N/A | AL41: =AD41&"|"&COUNTIF(AD$2:AD41,AD41)
A42: LS-060 | B42: Story | C42: LS-EPIC-05 | D42: Onboarding – 3 slides | E42: Implement SCR-01: night scene illustration, twinkle animation (reduced-motion aware), sheet with eyebrow/title/body, pager, Continue / Get Started, Skip. | F42: As a new parent, I want a short intro so I understand what LittleStory does. | G42: Personalised first-run experience | H42: High | I42: Must | J42: P3 | K42: :feature:onboarding | L42: SCR-01 | M42: SCR-01 Onboarding (3 slides) → 01-onboarding-1-every-day-has-a-story.jpg, 02-onboarding-2-your-child-the-hero.jpg, 03-onboarding-3-listen-dream-repeat.jpg | N42: LS-050, LS-017, LS-014 | O42: Blocks: LS-121, LS-122, LS-123, LS-125, LS-126 Blocked by: LS-050, LS-017, LS-014 | P42: 1. Copy matches design in EN; KN present 2. Continue advances; slide 3 shows Get Started → Setup 3. Skip → Setup 4. Pager announced | Q42: Std DoD: AC met · no hardcoded strings/colours/dims/config · EN + KN strings present · unit/UI tests pass · lint + translation check pass · screenshots EN/KN attached (UI) · docs updated · human PR review & merge · post-merge verified | R42: Use tokens, string resources (EN+KN) and AppConfig only. UiState + StateFlow; UiText for messages; preview in EN/KN. | S42: UI test flow · Screenshot 3 slides EN/KN | U42: 3 | V42: Medium | W42: Low | X42: Jetpack Compose UI Engineer | Y42: Yes | Z42: Low | AA42: feature/LS-060-onboarding-3-slides | AD42: To Do | AE42: Project owner (human) | AF42: Awaiting Approval C | AH42: New strings | AI42: Missing | AK42: FR-01 | AL42: =AD42&"|"&COUNTIF(AD$2:AD42,AD42)
A43: LS-061 | B43: Story | C43: LS-EPIC-05 | D43: Setup – child profile form | E43: Implement SCR-02 with ViewModel: fields, avatar picker, age 3–12, language (LS-045), interests multi-select, duration segmented, sticky CTA, Skip for now. Validation rules per LS-004. | F43: As a parent, I want to set up my child's profile so stories feel personal. | G43: Personalised first-run experience | H43: High | I43: Must | J43: P3 | K43: :feature:onboarding | L43: SCR-02 | M43: SCR-02 Setup – Child profile → 04-setup-profile.jpg | N43: LS-016, LS-062, LS-050 | O43: Blocks: LS-045, LS-063, LS-121, LS-122, LS-123, LS-125, LS-126 Blocked by: LS-016, LS-062, LS-050 | P43: 1. Defaults as designed for demo data only (empty for real first run – decision) 2. CTA text includes child name via format arg 3. Profile saved and Home shows name | Q43: Std DoD: AC met · no hardcoded strings/colours/dims/config · EN + KN strings present · unit/UI tests pass · lint + translation check pass · screenshots EN/KN attached (UI) · docs updated · human PR review & merge · post-merge verified | R43: Use tokens, string resources (EN+KN) and AppConfig only. UiState + StateFlow; UiText for messages; preview in EN/KN. | S43: ViewModel unit tests · UI test · Screenshot EN/KN | U43: 5 | V43: High | W43: Low | X43: Jetpack Compose UI Engineer | Y43: After deps | Z43: Low | AA43: feature/LS-061-setup-child-profile-form | AD43: To Do | AE43: Project owner (human) | AF43: Awaiting Approval C | AH43: New strings | AI43: Missing | AK43: FR-02, NFR-07 | AL43: =AD43&"|"&COUNTIF(AD$2:AD43,AD43)
A44: LS-062 | B44: Story | C44: LS-EPIC-05 | D44: Profile repository & active-child state | E44: ChildProfileRepository (Room/DataStore), active child flow consumed by Home, Create, Player labels. | F44: – | G44: Personalised first-run experience | H44: High | I44: Must | J44: P3 | K44: :data | L44: SCR-02, SCR-14 | M44: SCR-02 Setup – Child profile → 04-setup-profile.jpg SCR-14 Child Profiles → 20-child-profiles.jpg | N44: LS-038 | O44: Blocks: LS-061, LS-063, LS-070, LS-080, LS-110, LS-121, LS-122, LS-123, LS-125, LS-126 Blocked by: LS-038 | P44: 1. Active child persists 2. Switching child updates all screens | Q44: Std DoD: AC met · no hardcoded strings/colours/dims/config · EN + KN strings present · unit/UI tests pass · lint + translation check pass · screenshots EN/KN attached (UI) · docs updated · human PR review & merge · post-merge verified | R44: Use tokens, string resources (EN+KN) and AppConfig only. | S44: Unit + Room tests | U44: 3 | V44: Medium | W44: Low | X44: Data & Persistence Engineer | Y44: After deps | Z44: Low | AA44: feature/LS-062-profile-repository-active-child-state | AD44: To Do | AE44: Project owner (human) | AF44: Awaiting Approval C | AH44: None | AI44: N/A | AK44: FR-02, FR-03 | AL44: =AD44&"|"&COUNTIF(AD$2:AD44,AD44)
A45: LS-063 | B45: Story | C45: LS-EPIC-05 | D45: Child Profiles – list, switch, edit, add | E45: Implement SCR-14: privacy note, profile cards with Active/Switch, edit → Setup prefilled, Add child. | F45: – | G45: Personalised first-run experience | H45: Medium | I45: Should | J45: P6 | K45: :feature:settings | L45: SCR-14 | M45: SCR-14 Child Profiles → 20-child-profiles.jpg | N45: LS-062, LS-061 | O45: Blocks: LS-121, LS-122, LS-123, LS-125, LS-126 Blocked by: LS-062, LS-061 | P45: 1. Switch changes active child 2. Edit saves changes 3. Add creates new profile | Q45: Std DoD: AC met · no hardcoded strings/colours/dims/config · EN + KN strings present · unit/UI tests pass · lint + translation check pass · screenshots EN/KN attached (UI) · docs updated · human PR review & merge · post-merge verified | R45: Use tokens, string resources (EN+KN) and AppConfig only. UiState + StateFlow; UiText for messages; preview in EN/KN. | S45: UI test · Screenshot EN/KN | U45: 3 | V45: Medium | W45: Low | X45: Jetpack Compose UI Engineer | Y45: Yes | Z45: Low | AA45: feature/LS-063-child-profiles-list-switch-edit | AD45: To Do | AE45: Project owner (human) | AF45: Awaiting Approval C | AH45: New strings | AI45: Missing | AK45: FR-03 | AL45: =AD45&"|"&COUNTIF(AD$2:AD45,AD45)
A46: LS-070 | B46: Story | C46: LS-EPIC-06 | D46: Home screen | E46: Implement SCR-03 with HomeViewModel: greeting, 'Stories for {child}', hero + Create CTA, Continue listening card (hidden if none), category tiles, 'Made for {child}' row with hearts, culture banner, bell/avatar actions. | F46: As a parent, I want tonight's options at a glance so bedtime starts quickly. | G46: Core browsing value | H46: Highest | I46: Must | J46: P4 | K46: :feature:home | L46: SCR-03 | M46: SCR-03 Home → 05-home.jpg | N46: LS-018, LS-050, LS-062, LS-036 | O46: Blocks: LS-120, LS-121, LS-122, LS-123, LS-125, LS-126 Blocked by: LS-018, LS-050, LS-062, LS-036 | P46: 1. Matches screenshot EN 2. KN layout without clipping 3. All tap targets navigate per spec 4. Empty continue state handled | Q46: Std DoD: AC met · no hardcoded strings/colours/dims/config · EN + KN strings present · unit/UI tests pass · lint + translation check pass · screenshots EN/KN attached (UI) · docs updated · human PR review & merge · post-merge verified | R46: Use tokens, string resources (EN+KN) and AppConfig only. UiState + StateFlow; UiText for messages; preview in EN/KN. | S46: ViewModel unit · UI test · Screenshot EN/KN | U46: 5 | V46: High | W46: Low | X46: Jetpack Compose UI Engineer | Y46: After deps | Z46: Low | AA46: feature/LS-070-home-screen | AD46: To Do | AE46: Project owner (human) | AF46: Awaiting Approval C | AH46: New strings | AI46: Missing | AK46: FR-04, FR-24 | AL46: =AD46&"|"&COUNTIF(AD$2:AD46,AD46)
A47: LS-071 | B47: Story | C47: LS-EPIC-06 | D47: Discover – search, featured, filters, grid, rows | E47: Implement SCR-04a: live search (locale-aware), featured card hidden while searching, filter chips, Popular grid, Bedtime favourites row. | F47: – | G47: Core browsing value | H47: High | I47: Must | J47: P4 | K47: :feature:discover | L47: SCR-04a | M47: SCR-04a Discover → 06-discover.jpg | N47: LS-018, LS-016, LS-036, LS-050 | O47: Blocks: LS-072, LS-120, LS-121, LS-122, LS-123, LS-125, LS-126 Blocked by: LS-018, LS-016, LS-036, LS-050 | P47: 1. Search filters by title in EN and KN 2. Chip filters by category 3. 'Results for …' title while searching | Q47: Std DoD: AC met · no hardcoded strings/colours/dims/config · EN + KN strings present · unit/UI tests pass · lint + translation check pass · screenshots EN/KN attached (UI) · docs updated · human PR review & merge · post-merge verified | R47: Use tokens, string resources (EN+KN) and AppConfig only. UiState + StateFlow; UiText for messages; preview in EN/KN. | S47: ViewModel unit (filtering) · UI test · Screenshot EN/KN | U47: 5 | V47: High | W47: Low | X47: Jetpack Compose UI Engineer | Y47: Yes | Z47: Low | AA47: feature/LS-071-discover-search-featured-filters-grid | AD47: To Do | AE47: Project owner (human) | AF47: Awaiting Approval C | AH47: New strings | AI47: Missing | AK47: FR-05 | AL47: =AD47&"|"&COUNTIF(AD$2:AD47,AD47)
A48: LS-072 | B48: Story | C48: LS-EPIC-06 | D48: Discover – no-results empty state | E48: Implement SCR-04b empty state; Clear search resets query and chip. | F48: – | G48: Core browsing value | H48: Medium | I48: Must | J48: P4 | K48: :feature:discover | L48: SCR-04b | M48: SCR-04b Discover – No results (empty state) → 06-discover.jpg | N48: LS-071, LS-017 | O48: Blocks: LS-120, LS-121, LS-122, LS-123, LS-125, LS-126 Blocked by: LS-071, LS-017 | P48: 1. Shown when no match 2. Clear search restores default | Q48: Std DoD: AC met · no hardcoded strings/colours/dims/config · EN + KN strings present · unit/UI tests pass · lint + translation check pass · screenshots EN/KN attached (UI) · docs updated · human PR review & merge · post-merge verified | R48: Use tokens, string resources (EN+KN) and AppConfig only. UiState + StateFlow; UiText for messages; preview in EN/KN. | S48: UI test | U48: 1 | V48: Low | W48: Low | X48: Jetpack Compose UI Engineer | Y48: After deps | Z48: Low | AA48: feature/LS-072-discover-no-results-empty-state | AD48: To Do | AE48: Project owner (human) | AF48: Awaiting Approval C | AH48: New strings | AI48: Missing | AK48: FR-05 | AL48: =AD48&"|"&COUNTIF(AD$2:AD48,AD48)
A49: LS-073 | B49: Story | C49: LS-EPIC-06 | D49: Category screen (generic, sortable) | E49: Implement SCR-05 for any category id: hero (count plural, description), sort select, list rows with offline + heart. | F49: – | G49: Core browsing value | H49: Medium | I49: Should | J49: P4 | K49: :feature:discover | L49: SCR-05 | M49: SCR-05 Category (Indian Tales) → 21-category-indian-tales.jpg | N49: LS-018, LS-036, LS-050 | O49: Blocks: LS-120, LS-121, LS-122, LS-123, LS-125, LS-126 Blocked by: LS-018, LS-036, LS-050 | P49: 1. Works for every category in mock data 2. Sort orders correct 3. '{n} stories' uses plurals | Q49: Std DoD: AC met · no hardcoded strings/colours/dims/config · EN + KN strings present · unit/UI tests pass · lint + translation check pass · screenshots EN/KN attached (UI) · docs updated · human PR review & merge · post-merge verified | R49: Use tokens, string resources (EN+KN) and AppConfig only. UiState + StateFlow; UiText for messages; preview in EN/KN. | S49: Unit: sort · UI test · Screenshot EN/KN | U49: 3 | V49: Medium | W49: Low | X49: Jetpack Compose UI Engineer | Y49: Yes | Z49: Low | AA49: feature/LS-073-category-screen-generic-sortable | AD49: To Do | AE49: Project owner (human) | AF49: Awaiting Approval C | AH49: New strings | AI49: Missing | AK49: FR-06 | AL49: =AD49&"|"&COUNTIF(AD$2:AD49,AD49)
A50: LS-074 | B50: Story | C50: LS-EPIC-06 | D50: Story Detail screen | E50: Implement SCR-06: cover, back/favourite/download, pill, metadata, synopsis, lesson panel, narration row, sticky Listen/Read. | F50: – | G50: Core browsing value | H50: High | I50: Must | J50: P4 | K50: :feature:discover | L50: SCR-06 | M50: SCR-06 Story Detail → 22-story-detail.jpg | N50: LS-018, LS-036, LS-050, LS-075 | O50: Blocks: LS-120, LS-121, LS-122, LS-123, LS-125, LS-126 Blocked by: LS-018, LS-036, LS-050, LS-075 | P50: 1. Data-driven for any story id 2. Language tag reflects story language 3. Listen → Player, Read → Reader | Q50: Std DoD: AC met · no hardcoded strings/colours/dims/config · EN + KN strings present · unit/UI tests pass · lint + translation check pass · screenshots EN/KN attached (UI) · docs updated · human PR review & merge · post-merge verified | R50: Use tokens, string resources (EN+KN) and AppConfig only. UiState + StateFlow; UiText for messages; preview in EN/KN. | S50: UI test · Screenshot EN/KN | U50: 3 | V50: Medium | W50: Low | X50: Jetpack Compose UI Engineer | Y50: Yes | Z50: Low | AA50: feature/LS-074-story-detail-screen | AD50: To Do | AE50: Project owner (human) | AF50: Awaiting Approval C | AH50: New strings | AI50: Missing | AK50: FR-07 | AL50: =AD50&"|"&COUNTIF(AD$2:AD50,AD50)
A51: LS-075 | B51: Story | C51: LS-EPIC-06 | D51: Favourites (shared, persisted) | E51: FavouritesRepository + toggle use case used by every story surface; optimistic UI, no duplicate writes. | F51: – | G51: Core browsing value | H51: High | I51: Must | J51: P4 | K51: :data / :domain | L51: Multiple | M51: Design pack – all screens (docs/design/screens/) | N51: LS-038 | O51: Blocks: LS-074, LS-100, LS-120, LS-121, LS-122, LS-123, LS-125, LS-126 Blocked by: LS-038 | P51: 1. Toggle on any screen reflects everywhere 2. Persists after restart 3. Rapid taps produce consistent state | Q51: Std DoD: AC met · no hardcoded strings/colours/dims/config · EN + KN strings present · unit/UI tests pass · lint + translation check pass · screenshots EN/KN attached (UI) · docs updated · human PR review & merge · post-merge verified | R51: Use tokens, string resources (EN+KN) and AppConfig only. | S51: Unit + Room tests · UI test | U51: 2 | V51: Low | W51: Low | X51: Data & Persistence Engineer | Y51: After deps | Z51: Low | AA51: feature/LS-075-favourites-shared-persisted | AD51: To Do | AE51: Project owner (human) | AF51: Awaiting Approval C | AH51: None | AI51: N/A | AK51: FR-13 | AL51: =AD51&"|"&COUNTIF(AD$2:AD51,AD51)
A52: LS-080 | B52: Story | C52: LS-EPIC-07 | D52: Create a Story – form | E52: Implement SCR-07: intro, textarea with n/500 counter (limit from AppConfig), suggestion chips (neutral copy per LS-004), story hero selector, theme chips, safety note, CTA. | F52: As a parent, I want to turn my child's day into a story. | G52: Signature feature | H52: Highest | I52: Must | J52: P4 | K52: :feature:create | L52: SCR-07 | M52: SCR-07 Create a Story → 07-create-story.jpg, 08-create-story-more-options-and-error.jpg | N52: LS-016, LS-062, LS-033, LS-050 | O52: Blocks: LS-081, LS-120, LS-121, LS-122, LS-123, LS-125, LS-126 Blocked by: LS-016, LS-062, LS-033, LS-050 | P52: 1. Counter enforces limit 2. Suggestions fill text 3. Hero selector lists profiles | Q52: Std DoD: AC met · no hardcoded strings/colours/dims/config · EN + KN strings present · unit/UI tests pass · lint + translation check pass · screenshots EN/KN attached (UI) · docs updated · human PR review & merge · post-merge verified | R52: Use tokens, string resources (EN+KN) and AppConfig only. UiState + StateFlow; UiText for messages; preview in EN/KN. | S52: ViewModel unit · UI test · Screenshot EN/KN | U52: 5 | V52: High | W52: Low | X52: Jetpack Compose UI Engineer | Y52: After deps | Z52: Low | AA52: feature/LS-080-create-a-story-form | AD52: To Do | AE52: Project owner (human) | AF52: Awaiting Approval C | AH52: New strings | AI52: Missing | AK52: FR-08 | AL52: =AD52&"|"&COUNTIF(AD$2:AD52,AD52)
A53: LS-081 | B53: Story | C53: LS-EPIC-07 | D53: Create – more options & validation | E53: Collapsible More options (mood, duration, story language EN/KN from registry), chevron rotation; empty-text error banner announced and cleared on typing. | F53: – | G53: Signature feature | H53: High | I53: Must | J53: P4 | K53: :feature:create | L53: SCR-07 | M53: SCR-07 Create a Story → 07-create-story.jpg, 08-create-story-more-options-and-error.jpg | N53: LS-080, LS-040 | O53: Blocks: LS-120, LS-121, LS-122, LS-123, LS-125, LS-126 Blocked by: LS-080, LS-040 | P53: 1. Empty submit shows error, no navigation 2. Typing clears error 3. Story language limited to EN/KN | Q53: Std DoD: AC met · no hardcoded strings/colours/dims/config · EN + KN strings present · unit/UI tests pass · lint + translation check pass · screenshots EN/KN attached (UI) · docs updated · human PR review & merge · post-merge verified | R53: Use tokens, string resources (EN+KN) and AppConfig only. UiState + StateFlow; UiText for messages; preview in EN/KN. | S53: Unit: validation · UI test · Screenshot error EN/KN | U53: 3 | V53: Medium | W53: Low | X53: Jetpack Compose UI Engineer | Y53: After deps | Z53: Low | AA53: feature/LS-081-create-more-options-validation | AD53: To Do | AE53: Project owner (human) | AF53: Awaiting Approval C | AH53: New strings | AI53: Missing | AK53: FR-08, FR-21 | AL53: =AD53&"|"&COUNTIF(AD$2:AD53,AD53)
... A67: LS-113 | B67: Story | C67: LS-EPIC-10 | D67: Demo subscription (feature-flagged) + dialog | E67: Implement SCR-15 behind demoSubscription flag: hero, benefits, plans from mock data with locale currency format, 'Illustrative pricing only' note, confirmation dialog, no billing. | F67: – | G67: Parent trust and control | H67: Low | I67: Could | J67: P6 | K67: :feature:settings | L67: SCR-15 | M67: SCR-15 Subscription (demo) + dialog → 16-subscription.jpg | N67: LS-017, LS-033, LS-004 | O67: Blocks: LS-120, LS-121, LS-122, LS-123, LS-125, LS-126 Blocked by: LS-017, LS-033, LS-004 | P67: 1. No payment code or permission 2. Flag off hides entry row 3. Prices formatted for locale | Q67: Std DoD: AC met · no hardcoded strings/colours/dims/config · EN + KN strings present · unit/UI tests pass · lint + translation check pass · screenshots EN/KN attached (UI) · docs updated · human PR review & merge · post-merge verified | R67: Use tokens, string resources (EN+KN) and AppConfig only. UiState + StateFlow; UiText for messages; preview in EN/KN. | S67: UI test · Screenshot EN/KN | U67: 3 | V67: Medium | W67: Low | X67: Jetpack Compose UI Engineer | Y67: Yes | Z67: Low | AA67: feature/LS-113-demo-subscription-feature-flagged-dialog | AD67: To Do | AE67: Project owner (human) | AF67: Awaiting Approval C | AH67: New strings | AI67: Missing | AK67: FR-19, NFR-12 | AL67: =AD67&"|"&COUNTIF(AD$2:AD67,AD67)
A68: LS-114 | B68: Story | C68: LS-EPIC-10 | D68: Privacy & parent controls screen | E68: SCR-21 (design missing): explain local-only data, delete all local data action with confirmation. | F68: – | G68: Parent trust and control | H68: Medium | I68: Should | J68: P6 | K68: :feature:settings | L68: SCR-21 | M68: SCR-21 Privacy & parent controls → no design (missing) | N68: LS-004, LS-110 | O68: Blocks: LS-126 Blocked by: LS-004, LS-110 | P68: 1. Content approved by owner 2. Delete clears profiles, favourites, progress, downloads | Q68: Std DoD: AC met · no hardcoded strings/colours/dims/config · EN + KN strings present · unit/UI tests pass · lint + translation check pass · screenshots EN/KN attached (UI) · docs updated · human PR review & merge · post-merge verified | R68: Use tokens, string resources (EN+KN) and AppConfig only. UiState + StateFlow; UiText for messages; preview in EN/KN. | S68: UI test · Unit: data wipe | U68: 3 | V68: Medium | W68: Low | X68: Android Security & Privacy Reviewer | Y68: After deps | Z68: Low | AA68: feature/LS-114-privacy-parent-controls-screen | AD68: Blocked | AE68: Project owner (human) | AF68: Awaiting Approval C | AH68: New strings | AI68: Missing | AJ68: Blocked: design and content missing (LS-004). | AK68: FR-22, NFR-07 | AL68: =AD68&"|"&COUNTIF(AD$2:AD68,AD68)
A69: LS-115 | B69: Story | C69: LS-EPIC-10 | D69: Help & about screen | E69: SCR-22 (design missing): version from BuildConfig, font licences, help text. | F69: – | G69: Parent trust and control | H69: Low | I69: Could | J69: P6 | K69: :feature:settings | L69: SCR-22 | M69: SCR-22 Help & about → no design (missing) | N69: LS-004, LS-110 | O69: Blocks: LS-126 Blocked by: LS-004, LS-110 | P69: 1. Version shown from BuildConfig 2. Licences listed | Q69: Std DoD: AC met · no hardcoded strings/colours/dims/config · EN + KN strings present · unit/UI tests pass · lint + translation check pass · screenshots EN/KN attached (UI) · docs updated · human PR review & merge · post-merge verified | R69: Use tokens, string resources (EN+KN) and AppConfig only. UiState + StateFlow; UiText for messages; preview in EN/KN. | S69: UI test | U69: 1 | V69: Low | W69: Low | X69: Jetpack Compose UI Engineer | Y69: After deps | Z69: Low | AA69: feature/LS-115-help-about-screen | AD69: Blocked | AE69: Project owner (human) | AF69: Awaiting Approval C | AH69: New strings | AI69: Missing | AJ69: Blocked: design missing (LS-004). | AK69: FR-23 | AL69: =AD69&"|"&COUNTIF(AD$2:AD69,AD69)
A70: LS-120 | B70: Task | C70: LS-EPIC-11 | D70: Unit-test coverage gate for ViewModels & use cases | E70: Ensure each ViewModel/use case has tests; report coverage; agree threshold. | F70: – | G70: Release confidence | H70: High | I70: Must | J70: P7 | K70: All | L70: – | M70: – | N70: LS-070…LS-113 | O70: Blocks: – Blocked by: LS-070, LS-071, LS-072, LS-073, LS-074, LS-075, LS-080, LS-081, LS-082, LS-083, LS-084, LS-090, LS-091, LS-092, LS-093, LS-094, LS-100, LS-101, LS-110, LS-111, LS-112, LS-113 | P70: 1. Coverage report in CI 2. Agreed threshold met | Q70: Std DoD: AC met · no hardcoded strings/colours/dims/config · EN + KN strings present · unit/UI tests pass · lint + translation check pass · screenshots EN/KN attached (UI) · docs updated · human PR review & merge · post-merge verified | R70: Use tokens, string resources (EN+KN) and AppConfig only. | S70: Unit | U70: 3 | V70: Medium | W70: Low | X70: Android Testing & Automation Engineer | Y70: After deps | Z70: Low | AA70: feature/LS-120-unit-test-coverage-gate-for | AD70: To Do | AE70: Project owner (human) | AF70: Awaiting Approval C | AH70: None | AI70: N/A | AK70: NFR-05 | AL70: =AD70&"|"&COUNTIF(AD$2:AD70,AD70)
A71: LS-121 | B71: Task | C71: LS-EPIC-11 | D71: End-to-end journey tests A–G (EN & KN) | E71: Automate journeys A (first run), B (discover & read), C (create), D (revisit), E (parent controls), F (audio), G (change language). | F71: – | G71: Release confidence | H71: Highest | I71: Must | J71: P7 | K71: All | L71: All | M71: Design pack – all screens (docs/design/screens/) | N71: LS-060…LS-113 | O71: Blocks: LS-133 Blocked by: LS-060, LS-061, LS-062, LS-063, LS-070, LS-071, LS-072, LS-073, LS-074, LS-075, LS-080, LS-081, LS-082, LS-083, LS-084, LS-090, LS-091, LS-092, LS-093, LS-094, LS-100, LS-101, LS-110, LS-111, LS-112, LS-113 | P71: 1. All journeys pass in en and kn | Q71: Std DoD: AC met · no hardcoded strings/colours/dims/config · EN + KN strings present · unit/UI tests pass · lint + translation check pass · screenshots EN/KN attached (UI) · docs updated · human PR review & merge · post-merge verified | R71: Use tokens, string resources (EN+KN) and AppConfig only. | S71: Instrumented UI | U71: 5 | V71: High | W71: Low | X71: Android Testing & Automation Engineer | Y71: After deps | Z71: Low | AA71: feature/LS-121-end-to-end-journey-tests | AD71: To Do | AE71: Project owner (human) | AF71: Awaiting Approval C | AH71: None | AI71: N/A | AK71: All Must FR | AL71: =AD71&"|"&COUNTIF(AD$2:AD71,AD71)
A72: LS-122 | B72: Task | C72: LS-EPIC-11 | D72: Screenshot regression suite – 22 design states × EN/KN | E72: Baselines for every captured design state in EN and KN (plus en-XA spot checks), compared against design pack. | F72: – | G72: Release confidence | H72: High | I72: Must | J72: P7 | K72: All | L72: All | M72: Design pack – all screens (docs/design/screens/) | N72: LS-035, LS-060…LS-113 | O72: Blocks: LS-047, LS-124, LS-133 Blocked by: LS-060, LS-061, LS-062, LS-063, LS-070, LS-071, LS-072, LS-073, LS-074, LS-075, LS-080, LS-081, LS-082, LS-083, LS-084, LS-090, LS-091, LS-092, LS-093, LS-094, LS-100, LS-101, LS-110, LS-111, LS-112, LS-113, LS-035 | P72: 1. Baselines reviewed by owner 2. Diffs fail CI | Q72: Std DoD: AC met · no hardcoded strings/colours/dims/config · EN + KN strings present · unit/UI tests pass · lint + translation check pass · screenshots EN/KN attached (UI) · docs updated · human PR review & merge · post-merge verified | R72: Use tokens, string resources (EN+KN) and AppConfig only. | S72: Screenshot | U72: 5 | V72: High | W72: Low | X72: UI Integration & Visual Regression Engineer | Y72: After deps | Z72: Low | AA72: feature/LS-122-screenshot-regression-suite-22-design | AD72: To Do | AE72: Project owner (human) | AF72: Awaiting Approval C | AH72: None | AI72: N/A | AK72: NFR-10 | AL72: =AD72&"|"&COUNTIF(AD$2:AD72,AD72)
A73: LS-123 | B73: Task | C73: LS-EPIC-11 | D73: Accessibility audit & fixes | E73: Measure contrast (#716B80 at 10–12sp, #817B8D nav labels), 48dp targets (chips, 42dp icon buttons), selected-state semantics for chips/day picker, focus visibility, reduced motion, TalkBack in EN and KN. | F73: – | G73: Release confidence | H73: High | I73: Must | J73: P7 | K73: All | L73: All | M73: Design pack – all screens (docs/design/screens/) | N73: LS-060…LS-113 | O73: Blocks: LS-133 Blocked by: LS-060, LS-061, LS-062, LS-063, LS-070, LS-071, LS-072, LS-073, LS-074, LS-075, LS-080, LS-081, LS-082, LS-083, LS-084, LS-090, LS-091, LS-092, LS-093, LS-094, LS-100, LS-101, LS-110, LS-111, LS-112, LS-113 | P73: 1. All Must a11y issues fixed or accepted by owner 2. Report in docs/design/accessibility-spec.md | Q73: Std DoD: AC met · no hardcoded strings/colours/dims/config · EN + KN strings present · unit/UI tests pass · lint + translation check pass · screenshots EN/KN attached (UI) · docs updated · human PR review & merge · post-merge verified | R73: Use tokens, string resources (EN+KN) and AppConfig only. | S73: Accessibility Scanner · TalkBack manual | U73: 5 | V73: High | W73: Medium | X73: Accessibility, Localization & i18n Engineer | Y73: After deps | Z73: Low | AA73: feature/LS-123-accessibility-audit-fixes | AD73: To Do | AE73: Project owner (human) | AF73: Awaiting Approval C | AH73: None | AI73: N/A | AK73: NFR-04 | AL73: =AD73&"|"&COUNTIF(AD$2:AD73,AD73)
A74: LS-124 | B74: Task | C74: LS-EPIC-11 | D74: Visual fidelity review vs design pack | E74: Screen-by-screen comparison with severity and defect tickets. | F74: – | G74: Release confidence | H74: High | I74: Must | J74: P7 | K74: All | L74: All | M74: Design pack – all screens (docs/design/screens/) | N74: LS-122 | O74: Blocks: – Blocked by: LS-122 | P74: 1. Report per screen 2. Blocker/High fixed | Q74: Std DoD: AC met · no hardcoded strings/colours/dims/config · EN + KN strings present · unit/UI tests pass · lint + translation check pass · screenshots EN/KN attached (UI) · docs updated · human PR review & merge · post-merge verified | R74: Use tokens, string resources (EN+KN) and AppConfig only. | S74: Manual + screenshot | U74: 3 | V74: Medium | W74: Low | X74: UI Integration & Visual Regression Engineer | Y74: After deps | Z74: Low | AA74: feature/LS-124-visual-fidelity-review-vs-design | AD74: To Do | AE74: Project owner (human) | AF74: Awaiting Approval C | AH74: None | AI74: N/A | AK74: NFR-10 | AL74: =AD74&"|"&COUNTIF(AD$2:AD74,AD74)
A75: LS-125 | B75: Task | C75: LS-EPIC-15 | D75: Maintainability review – hardcoded values audit | E75: Audit for hardcoded strings, colours, dims, routes, limits; duplication; config placement. | F75: – | G75: Cheap future changes | H75: High | I75: Must | J75: P7 | K75: All | L75: – | M75: – | N75: LS-034, LS-060…LS-113 | O75: Blocks: – Blocked by: LS-060, LS-061, LS-062, LS-063, LS-070, LS-071, LS-072, LS-073, LS-074, LS-075, LS-080, LS-081, LS-082, LS-083, LS-084, LS-090, LS-091, LS-092, LS-093, LS-094, LS-100, LS-101, LS-110, LS-111, LS-112, LS-113, LS-034 | P75: 1. Zero hardcoded values in feature modules 2. Findings fixed | Q75: Std DoD: AC met · no hardcoded strings/colours/dims/config · EN + KN strings present · unit/UI tests pass · lint + translation check pass · screenshots EN/KN attached (UI) · docs updated · human PR review & merge · post-merge verified | R75: Use tokens, string resources (EN+KN) and AppConfig only. | S75: Static analysis report | U75: 2 | V75: Low | W75: Low | X75: Code Quality & Maintainability Reviewer | Y75: After deps | Z75: Low | AA75: feature/LS-125-maintainability-review-hardcoded-values-audit | AD75: To Do | AE75: Project owner (human) | AF75: Awaiting Approval C | AH75: None | AI75: N/A | AK75: NFR-01 | AL75: =AD75&"|"&COUNTIF(AD$2:AD75,AD75)
A76: LS-126 | B76: Task | C76: LS-EPIC-11 | D76: Security & privacy review + threat model | E76: docs/security/*: no network/analytics, no secrets, no child data in logs, backup rules, permissions minimal. | F76: – | G76: Release confidence | H76: High | I76: Must | J76: P7 | K76: All | L76: – | M76: – | N76: LS-060…LS-115 | O76: Blocks: LS-133 Blocked by: LS-060, LS-061, LS-062, LS-063, LS-070, LS-071, LS-072, LS-073, LS-074, LS-075, LS-080, LS-081, LS-082, LS-083, LS-084, LS-090, LS-091, LS-092, LS-093, LS-094, LS-100, LS-101, LS-110, LS-111, LS-112, LS-113, LS-114, LS-115 | P76: 1. Threat model and checklist complete 2. Findings resolved | Q76: Std DoD: AC met · no hardcoded strings/colours/dims/config · EN + KN strings present · unit/UI tests pass · lint + translation check pass · screenshots EN/KN attached (UI) · docs updated · human PR review & merge · post-merge verified | R76: Use tokens, string resources (EN+KN) and AppConfig only. | S76: Manual review · lint security checks | U76: 3 | V76: Medium | W76: Low | X76: Android Security & Privacy Reviewer | Y76: After deps | Z76: Low | AA76: feature/LS-126-security-privacy-review-threat-model | AD76: To Do | AE76: Project owner (human) | AF76: Awaiting Approval C | AH76: None | AI76: N/A | AK76: NFR-07 | AL76: =AD76&"|"&COUNTIF(AD$2:AD76,AD76)
A77: LS-130 | B77: Task | C77: LS-EPIC-12 | D77: GitHub Actions PR workflow | E77: Build, unit tests, lint, translation completeness, screenshot verify on PRs to development. | F77: – | G77: Repeatable delivery | H77: High | I77: Must | J77: P2 | K77: .github/workflows | L77: – | M77: – | N77: LS-030, LS-034, LS-041 | O77: Blocks: – Blocked by: LS-030, LS-034, LS-041 | P77: 1. Required checks run on every PR 2. No secrets in workflow | Q77: Std DoD: AC met · no hardcoded strings/colours/dims/config · EN + KN strings present · unit/UI tests pass · lint + translation check pass · screenshots EN/KN attached (UI) · docs updated · human PR review & merge · post-merge verified | R77: Shared files: .github/workflows/ci.yml Use tokens, string resources (EN+KN) and AppConfig only. | S77: CI run | U77: 3 | V77: Medium | W77: Low | X77: Build, Gradle & CI/CD Engineer | Y77: After deps | Z77: Medium | AA77: feature/LS-130-github-actions-pr-workflow | AD77: To Do | AE77: Project owner (human) | AF77: Awaiting Approval C | AH77: None | AI77: N/A | AL77: =AD77&"|"&COUNTIF(AD$2:AD77,AD77)
A78: LS-131 | B78: Task | C78: LS-EPIC-12 | D78: Branch strategy, PR template, CODEOWNERS | E78: Create development branch, PR template (ticket, AC, EN/KN screenshots, tests), CODEOWNERS; owner sets protections (Approval D). | F78: – | G78: Repeatable delivery | H78: High | I78: Must | J78: P1 | K78: .github | L78: – | M78: – | N78: LS-001 | O78: Blocks: – Blocked by: LS-001 | P78: 1. development branch exists 2. PR template used | Q78: Std DoD: AC met · no hardcoded strings/colours/dims/config · EN + KN strings present · unit/UI tests pass · lint + translation check pass · screenshots EN/KN attached (UI) · docs updated · human PR review & merge · post-merge verified | R78: Use tokens, string resources (EN+KN) and AppConfig only. | S78: Open test PR | U78: 1 | V78: Low | W78: Low | X78: Release & Deployment Coordinator | Y78: Yes | Z78: Low | AA78: claude/project-thread-veobz7 | AD78: In Review | AE78: Project owner (human) | AF78: Approval B granted — awaiting owner review of docs PR | AG78: Drafted 29 Oct 2026: .github/pull_request_template.md, .github/CODEOWNERS (development branch awaits owner, D2) | AH78: None | AI78: N/A | AL78: =AD78&"|"&COUNTIF(AD$2:AD78,AD78)
A79: LS-132 | B79: Task | C79: LS-EPIC-12 | D79: Build & run docs (Windows + macOS), release checklist, known limitations | E79: docs/release/*. | F79: – | G79: Repeatable delivery | H79: Medium | I79: Must | J79: P8 | K79: Docs | L79: – | M79: – | N79: LS-030 | O79: Blocks: – Blocked by: LS-030 | P79: 1. A new developer builds on Windows and macOS following the doc | Q79: Std DoD: AC met · no hardcoded strings/colours/dims/config · EN + KN strings present · unit/UI tests pass · lint + translation check pass · screenshots EN/KN attached (UI) · docs updated · human PR review & merge · post-merge verified | R79: Use tokens, string resources (EN+KN) and AppConfig only. | S79: Doc walkthrough | U79: 2 | V79: Low | W79: Low | X79: Release & Deployment Coordinator | Y79: Yes | Z79: Low | AA79: feature/LS-132-build-run-docs-windows-macos | AD79: To Do | AE79: Project owner (human) | AF79: Awaiting Approval B | AH79: None | AI79: N/A | AK79: NFR-09 | AL79: =AD79&"|"&COUNTIF(AD$2:AD79,AD79)
A80: LS-133 | B80: Task | C80: LS-EPIC-12 | D80: Release-readiness report | E80: Final report per master prompt §29. | F80: – | G80: Repeatable delivery | H80: Medium | I80: Must | J80: P8 | K80: Docs | L80: – | M80: – | N80: LS-121, LS-122, LS-123, LS-126, LS-047 | O80: Blocks: – Blocked by: LS-121, LS-122, LS-123, LS-126, LS-047 | P80: 1. Verified vs assumed separated 2. Owner decision on release | Q80: Std DoD: AC met · no hardcoded strings/colours/dims/config · EN + KN strings present · unit/UI tests pass · lint + translation check pass · screenshots EN/KN attached (UI) · docs updated · human PR review & merge · post-merge verified | R80: Use tokens, string resources (EN+KN) and AppConfig only. | S80: Review | U80: 2 | V80: Low | W80: Low | X80: Release & Deployment Coordinator | Y80: After deps | Z80: Low | AA80: feature/LS-133-release-readiness-report | AD80: To Do | AE80: Project owner (human) | AF80: Awaiting Approval B | AH80: None | AI80: N/A | AL80: =AD80&"|"&COUNTIF(AD$2:AD80,AD80)
A81: LS-140 | B81: Task | C81: LS-EPIC-13 | D81: Proposed future API contracts (incl. language negotiation) | E81: docs/api/future-api-contracts.md marked PROPOSED – NOT IMPLEMENTED; locale parameter / Accept-Language and fallback. | F81: – | G81: Future-proofing | H81: Low | I81: Should | J81: P8 | K81: Docs | L81: – | M81: – | N81: LS-037 | O81: Blocks: – Blocked by: LS-037 | P81: 1. Endpoints, errors, pagination, auth, versioning documented | Q81: Std DoD: AC met · no hardcoded strings/colours/dims/config · EN + KN strings present · unit/UI tests pass · lint + translation check pass · screenshots EN/KN attached (UI) · docs updated · human PR review & merge · post-merge verified | R81: Use tokens, string resources (EN+KN) and AppConfig only. | S81: Review | U81: 3 | V81: Medium | W81: Low | X81: API & Backend Integration Architect | Y81: Yes | Z81: Low | AA81: feature/LS-140-proposed-future-api-contracts-incl | AD81: To Do | AE81: Project owner (human) | AF81: Awaiting Approval B | AH81: None | AI81: N/A | AL81: =AD81&"|"&COUNTIF(AD$2:AD81,AD81)
A82: LS-141 | B82: Task | C82: LS-EPIC-13 | D82: AI generation flow & multilingual child-safety plan | E82: docs/api/ai-generation-flow.md: job-based flow, moderation in EN and KN, rate limits, retention, consent. | F82: – | G82: Future-proofing | H82: Low | I82: Should | J82: P8 | K82: Docs | L82: – | M82: – | N82: LS-082 | O82: Blocks: – Blocked by: LS-082 | P82: 1. Safety controls defined per language | Q82: Std DoD: AC met · no hardcoded strings/colours/dims/config · EN + KN strings present · unit/UI tests pass · lint + translation check pass · screenshots EN/KN attached (UI) · docs updated · human PR review & merge · post-merge verified | R82: Use tokens, string resources (EN+KN) and AppConfig only. | S82: Review | U82: 3 | V82: Medium | W82: Low | X82: AI Story Generation Integration Architect | Y82: Yes | Z82: Low | AA82: feature/LS-141-ai-generation-flow-multilingual-child | AD82: To Do | AE82: Project owner (human) | AF82: Awaiting Approval B | AH82: None | AI82: N/A | AL82: =AD82&"|"&COUNTIF(AD$2:AD82,AD82)
A83: LS-150 | B83: Task | C83: LS-EPIC-15 | D83: Configuration docs & 'How to change X' guide | E83: docs/architecture/configuration-and-constants.md and how-to-change.md (colour, string, spacing, mock story, feature flag, language, screen). | F83: – | G83: Cheap future changes | H83: Medium | I83: Must | J83: P2 | K83: Docs | L83: – | M83: – | N83: LS-033, LS-010, LS-040 | O83: Blocks: – Blocked by: LS-033, LS-010, LS-040 | P83: 1. Every central config point documented with file path | Q83: Std DoD: AC met · no hardcoded strings/colours/dims/config · EN + KN strings present · unit/UI tests pass · lint + translation check pass · screenshots EN/KN attached (UI) · docs updated · human PR review & merge · post-merge verified | R83: Use tokens, string resources (EN+KN) and AppConfig only. | S83: Doc walkthrough | U83: 2 | V83: Low | W83: Low | X83: Code Quality & Maintainability Reviewer | Y83: Yes | Z83: Low | AA83: claude/project-thread-veobz7 | AD83: In Review | AE83: Project owner (human) | AF83: Approval B granted — awaiting owner review of docs PR | AG83: Drafted 29 Oct 2026: docs/architecture/configuration-and-constants.md, how-to-change.md (drafted early in P1) | AH83: None | AI83: N/A | AK83: NFR-01 | AL83: =AD83&"|"&COUNTIF(AD$2:AD83,AD83)
A84: LS-009 | B84: Task | C84: LS-EPIC-12 | D84: Repository hygiene: default branch main, development branch | E84: Owner merges PR #1, sets the GitHub default branch back to main and creates development from main (decision D2, R-22). | F84: – | G84: Every branch and PR starts from the right base | H84: Highest | I84: Must | J84: P1 | K84: GitHub settings | L84: – | M84: – | N84: LS-001 | O84: Blocks: LS-030, LS-131 Blocked by: LS-001 | P84: 1. Default branch is main 2. development exists from main 3. PR #1 merged by owner | Q84: Owner confirms settings changed | R84: Owner action in GitHub settings; agents must not change repository settings. | S84: Verify via GitHub API | U84: 1 | V84: Low | W84: Medium | X84: Release and Deployment Coordinator | Y84: Yes | Z84: Low | AA84: – | AD84: To Do | AE84: Project owner (human) | AF84: Awaiting owner (D2) | AH84: None | AI84: N/A | AL84: =AD84&"|"&COUNTIF(AD$2:AD84,AD84)
A85: LS-039 | B85: Task | C85: LS-EPIC-12 | D85: Build verification environment (ADR-017) | E85: Make Android builds verifiable for agent PRs: allow dl.google.com in the cloud environment network settings and rely on GitHub Actions (LS-130) as the shared runner (decision D3, R-21). | F85: – | G85: PRs carry real build and test evidence | H85: Highest | I85: Must | J85: P2 | K85: Environment / CI | L85: – | M85: – | N85: LS-009 | O85: Blocks: LS-030, LS-035, LS-130 Blocked by: LS-009 | P85: 1. A Gradle sync that downloads AGP succeeds in the agent workspace or CI 2. Decision recorded in ADR-017 | Q85: ADR-017 approved and verified with a real sync | R85: Owner changes Network access in the project cloud environment; no credentials in the repo. | S85: Gradle sync / assembleDebug run | U85: 1 | V85: Low | W85: High | X85: Build, Gradle & CI/CD Engineer | Y85: Yes | Z85: Low | AA85: – | AD85: To Do | AE85: Project owner (human) | AF85: Awaiting owner (D3) | AH85: None | AI85: N/A | AL85: =AD85&"|"&COUNTIF(AD$2:AD85,AD85)

Sheet Epics
A1: Epic ID | B1: Epic Name | C1: Goal | D1: Phases | E1: Business Value | F1: Tickets | G1: Story Points | H1: Done | I1: % Done (points)
A2: LS-EPIC-01 | B2: Product Discovery and Requirements | C2: Verified repo/design inventory, requirements, decisions, agent instructions | D2: P0–P1 | E2: Delivery clarity – avoids rework | F2: =COUNTIF(Backlog!$C$2:$C$300,A2) | G2: =SUMIF(Backlog!$C$2:$C$300,A2,Backlog!$U$2:$U$300) | H2: =COUNTIFS(Backlog!$C$2:$C$300,A2,Backlog!$AD$2:$AD$300,"Done") | I2: =IF(G2=0,0,SUMIFS(Backlog!$U$2:$U$300,Backlog!$C$2:$C$300,A2,Backlog!$AD$2:$AD$300,"Done")/G2)
A3: LS-EPIC-02 | B3: Design System (from Figma Make) | C3: Tokens, typography, icons, reusable Compose components matching the design pack | D3: P2 | E3: Visual fidelity and consistency | F3: =COUNTIF(Backlog!$C$2:$C$300,A3) | G3: =SUMIF(Backlog!$C$2:$C$300,A3,Backlog!$U$2:$U$300) | H3: =COUNTIFS(Backlog!$C$2:$C$300,A3,Backlog!$AD$2:$AD$300,"Done") | I3: =IF(G3=0,0,SUMIFS(Backlog!$U$2:$U$300,Backlog!$C$2:$C$300,A3,Backlog!$AD$2:$AD$300,"Done")/G3)
A4: LS-EPIC-03 | B4: Android Foundation | C4: Build, modules, DI, config, mock data, domain, persistence, tooling | D4: P2 | E4: Maintainable, testable base | F4: =COUNTIF(Backlog!$C$2:$C$300,A4) | G4: =SUMIF(Backlog!$C$2:$C$300,A4,Backlog!$U$2:$U$300) | H4: =COUNTIFS(Backlog!$C$2:$C$300,A4,Backlog!$AD$2:$AD$300,"Done") | I4: =IF(G4=0,0,SUMIFS(Backlog!$U$2:$U$300,Backlog!$C$2:$C$300,A4,Backlog!$AD$2:$AD$300,"Done")/G4)
A5: LS-EPIC-04 | B5: Navigation and Application Shell | C5: Typed navigation for all screens, splash, system bars | D5: P3 | E5: Coherent app structure | F5: =COUNTIF(Backlog!$C$2:$C$300,A5) | G5: =SUMIF(Backlog!$C$2:$C$300,A5,Backlog!$U$2:$U$300) | H5: =COUNTIFS(Backlog!$C$2:$C$300,A5,Backlog!$AD$2:$AD$300,"Done") | I5: =IF(G5=0,0,SUMIFS(Backlog!$U$2:$U$300,Backlog!$C$2:$C$300,A5,Backlog!$AD$2:$AD$300,"Done")/G5)
A6: LS-EPIC-05 | B6: Onboarding and Profiles | C6: Onboarding, child setup, multiple child profiles | D6: P3–P6 | E6: Personalised first-run experience | F6: =COUNTIF(Backlog!$C$2:$C$300,A6) | G6: =SUMIF(Backlog!$C$2:$C$300,A6,Backlog!$U$2:$U$300) | H6: =COUNTIFS(Backlog!$C$2:$C$300,A6,Backlog!$AD$2:$AD$300,"Done") | I6: =IF(G6=0,0,SUMIFS(Backlog!$U$2:$U$300,Backlog!$C$2:$C$300,A6,Backlog!$AD$2:$AD$300,"Done")/G6)
A7: LS-EPIC-06 | B7: Home and Story Discovery | C7: Home, Discover, Category, Story Detail, favourites | D7: P4 | E7: Core browsing value | F7: =COUNTIF(Backlog!$C$2:$C$300,A7) | G7: =SUMIF(Backlog!$C$2:$C$300,A7,Backlog!$U$2:$U$300) | H7: =COUNTIFS(Backlog!$C$2:$C$300,A7,Backlog!$AD$2:$AD$300,"Done") | I7: =IF(G7=0,0,SUMIFS(Backlog!$U$2:$U$300,Backlog!$C$2:$C$300,A7,Backlog!$AD$2:$AD$300,"Done")/G7)
A8: LS-EPIC-07 | B8: Story Creation | C8: Create form, simulated generation, story ready | D8: P4 | E8: Signature feature | F8: =COUNTIF(Backlog!$C$2:$C$300,A8) | G8: =SUMIF(Backlog!$C$2:$C$300,A8,Backlog!$U$2:$U$300) | H8: =COUNTIFS(Backlog!$C$2:$C$300,A8,Backlog!$AD$2:$AD$300,"Done") | I8: =IF(G8=0,0,SUMIFS(Backlog!$U$2:$U$300,Backlog!$C$2:$C$300,A8,Backlog!$AD$2:$AD$300,"Done")/G8)
A9: LS-EPIC-08 | B9: Reader and Audio | C9: Reader, simulated player, sleep timer, progress | D9: P5 | E9: Bedtime reading/listening | F9: =COUNTIF(Backlog!$C$2:$C$300,A9) | G9: =SUMIF(Backlog!$C$2:$C$300,A9,Backlog!$U$2:$U$300) | H9: =COUNTIFS(Backlog!$C$2:$C$300,A9,Backlog!$AD$2:$AD$300,"Done") | I9: =IF(G9=0,0,SUMIFS(Backlog!$U$2:$U$300,Backlog!$C$2:$C$300,A9,Backlog!$AD$2:$AD$300,"Done")/G9)
A10: LS-EPIC-09 | B10: Saved Library and Downloads | C10: My Stories, recently played, simulated downloads | D10: P5–P6 | E10: Re-engagement | F10: =COUNTIF(Backlog!$C$2:$C$300,A10) | G10: =SUMIF(Backlog!$C$2:$C$300,A10,Backlog!$U$2:$U$300) | H10: =COUNTIFS(Backlog!$C$2:$C$300,A10,Backlog!$AD$2:$AD$300,"Done") | I10: =IF(G10=0,0,SUMIFS(Backlog!$U$2:$U$300,Backlog!$C$2:$C$300,A10,Backlog!$AD$2:$AD$300,"Done")/G10)
A11: LS-EPIC-10 | B11: Parent Controls, Settings and Privacy | C11: Settings hub, reminders, notifications, demo subscription, privacy, help | D11: P6 | E11: Parent trust and control | F11: =COUNTIF(Backlog!$C$2:$C$300,A11) | G11: =SUMIF(Backlog!$C$2:$C$300,A11,Backlog!$U$2:$U$300) | H11: =COUNTIFS(Backlog!$C$2:$C$300,A11,Backlog!$AD$2:$AD$300,"Done") | I11: =IF(G11=0,0,SUMIFS(Backlog!$U$2:$U$300,Backlog!$C$2:$C$300,A11,Backlog!$AD$2:$AD$300,"Done")/G11)
A12: LS-EPIC-11 | B12: Testing and Visual Quality | C12: Unit/UI/E2E/screenshot/a11y/security reviews | D12: P7 | E12: Release confidence | F12: =COUNTIF(Backlog!$C$2:$C$300,A12) | G12: =SUMIF(Backlog!$C$2:$C$300,A12,Backlog!$U$2:$U$300) | H12: =COUNTIFS(Backlog!$C$2:$C$300,A12,Backlog!$AD$2:$AD$300,"Done") | I12: =IF(G12=0,0,SUMIFS(Backlog!$U$2:$U$300,Backlog!$C$2:$C$300,A12,Backlog!$AD$2:$AD$300,"Done")/G12)
A13: LS-EPIC-12 | B13: CI/CD and Release Readiness | C13: Branching, CI, release docs | D13: P1–P8 | E13: Repeatable delivery | F13: =COUNTIF(Backlog!$C$2:$C$300,A13) | G13: =SUMIF(Backlog!$C$2:$C$300,A13,Backlog!$U$2:$U$300) | H13: =COUNTIFS(Backlog!$C$2:$C$300,A13,Backlog!$AD$2:$AD$300,"Done") | I13: =IF(G13=0,0,SUMIFS(Backlog!$U$2:$U$300,Backlog!$C$2:$C$300,A13,Backlog!$AD$2:$AD$300,"Done")/G13)
... A16: LS-EPIC-15 | B16: Maintainability and Configuration | C16: No hardcoding, central config, how-to-change docs | D16: P2–P8 | E16: Cheap future changes | F16: =COUNTIF(Backlog!$C$2:$C$300,A16) | G16: =SUMIF(Backlog!$C$2:$C$300,A16,Backlog!$U$2:$U$300) | H16: =COUNTIFS(Backlog!$C$2:$C$300,A16,Backlog!$AD$2:$AD$300,"Done") | I16: =IF(G16=0,0,SUMIFS(Backlog!$U$2:$U$300,Backlog!$C$2:$C$300,A16,Backlog!$AD$2:$AD$300,"Done")/G16)

Sheet Roadmap
A1: Phase | B1: Name | C1: Goal | D1: Key Deliverables | E1: Entry Criteria | F1: Exit Criteria | G1: Approval Gate | H1: Tickets | I1: Story Points | J1: Done
A2: P0 | B2: Discovery | C2: Read-only repo, toolchain and design audit | D2: Discovery report; design inventory (done from design pack) | E2: Session start | F2: Report delivered | G2: Approval A | H2: =COUNTIF(Backlog!$J$2:$J$300,A2) | I2: =SUMIF(Backlog!$J$2:$J$300,A2,Backlog!$U$2:$U$300) | J2: =COUNTIFS(Backlog!$J$2:$J$300,A2,Backlog!$AD$2:$AD$300,"Done")
A3: P1 | B3: Requirements & planning | C3: Requirements, ADRs, backlog, prompts, agent instructions | D3: docs/, backlog workbook, prompts/, CLAUDE.md, copilot-instructions.md | E3: Approval A | F3: Docs approved | G3: Approval B | H3: =COUNTIF(Backlog!$J$2:$J$300,A3) | I3: =SUMIF(Backlog!$J$2:$J$300,A3,Backlog!$U$2:$U$300) | J3: =COUNTIFS(Backlog!$J$2:$J$300,A3,Backlog!$AD$2:$AD$300,"Done")
A4: P2 | B4: Foundation, design system & localization foundation | C4: Build, modules, tokens, components, l10n infra, mock data, CI | D4: Buildable app shell with tokens, components, EN/KN infra | E4: Approval C | F4: Build + tests + lint green | G4: Approval C per ticket | H4: =COUNTIF(Backlog!$J$2:$J$300,A4) | I4: =SUMIF(Backlog!$J$2:$J$300,A4,Backlog!$U$2:$U$300) | J4: =COUNTIFS(Backlog!$J$2:$J$300,A4,Backlog!$AD$2:$AD$300,"Done")
A5: P3 | B5: App shell, navigation & onboarding | C5: Nav graph, splash, onboarding, setup, profiles persistence | D5: First-run journey A working EN/KN | E5: P2 merged | F5: Journey A verified | G5: PR review | H5: =COUNTIF(Backlog!$J$2:$J$300,A5) | I5: =SUMIF(Backlog!$J$2:$J$300,A5,Backlog!$U$2:$U$300) | J5: =COUNTIFS(Backlog!$J$2:$J$300,A5,Backlog!$AD$2:$AD$300,"Done")
A6: P4 | B6: Home, discovery & creation | C6: Home, Discover, Category, Detail, Create, Generating, Ready | D6: Journeys B & C working | E6: P3 merged | F6: Journeys B, C verified | G6: PR review | H6: =COUNTIF(Backlog!$J$2:$J$300,A6) | I6: =SUMIF(Backlog!$J$2:$J$300,A6,Backlog!$U$2:$U$300) | J6: =COUNTIFS(Backlog!$J$2:$J$300,A6,Backlog!$AD$2:$AD$300,"Done")
A7: P5 | B7: Reader, player & library | C7: Reader, simulated player, sleep timer, My Stories, progress | D7: Journeys D & F working | E7: P4 contracts merged | F7: Journeys D, F verified | G7: PR review | H7: =COUNTIF(Backlog!$J$2:$J$300,A7) | I7: =SUMIF(Backlog!$J$2:$J$300,A7,Backlog!$U$2:$U$300) | J7: =COUNTIFS(Backlog!$J$2:$J$300,A7,Backlog!$AD$2:$AD$300,"Done")
A8: P6 | B8: Parent & supporting screens | C8: Settings hub, profiles, reminders, notifications, downloads, subscription, language prefs, privacy, help | D8: Journeys E & G working | E8: P3 merged | F8: Journeys E, G verified | G8: PR review | H8: =COUNTIF(Backlog!$J$2:$J$300,A8) | I8: =SUMIF(Backlog!$J$2:$J$300,A8,Backlog!$U$2:$U$300) | J8: =COUNTIFS(Backlog!$J$2:$J$300,A8,Backlog!$AD$2:$AD$300,"Done")
A9: P7 | B9: Quality hardening | C9: E2E, screenshots EN/KN, a11y, security, maintainability, native Kannada review | D9: Evidence pack; defects fixed | E9: P3–P6 merged | F9: All Must tests pass | G9: PR review | H9: =COUNTIF(Backlog!$J$2:$J$300,A9) | I9: =SUMIF(Backlog!$J$2:$J$300,A9,Backlog!$U$2:$U$300) | J9: =COUNTIFS(Backlog!$J$2:$J$300,A9,Backlog!$AD$2:$AD$300,"Done")
A10: P8 | B10: Release readiness | C10: CI stable, release docs, backend plan, readiness report | D10: Release-readiness report | E10: P7 done | F10: Owner sign-off | G10: Approval F | H10: =COUNTIF(Backlog!$J$2:$J$300,A10) | I10: =SUMIF(Backlog!$J$2:$J$300,A10,Backlog!$U$2:$U$300) | J10: =COUNTIFS(Backlog!$J$2:$J$300,A10,Backlog!$AD$2:$AD$300,"Done")

Sheet Screens
A1: Design Preview | B1: Screen ID | C1: Screen Name | D1: Figma Source (Make screen) | E1: Screenshot File(s) | F1: Design Details | G1: Main Entry Point | H1: Exit Paths | I1: Components | J1: States | K1: Data Requirements | L1: Accessibility Notes | M1: Localization Notes | N1: Screenshot Test Required | O1: Related Ticket Keys | P1: Design Status | Q1: Implementation Status | R1: Review Status | S1: Open Questions
B2: SCR-01 | C2: Onboarding (3 slides) | D2: Figma Make · Mobile App UI Prototype · screen 'onboarding' | E2: 01-onboarding-1-every-day-has-a-story.jpg 02-onboarding-2-your-child-the-hero.jpg 03-onboarding-3-listen-dream-repeat.jpg | F2: Night canvas #17152F. Sheet: eyebrow 'LITTLE STORIES. BIG IMAGINATION.' → title 29/1.12 Manrope → body 15/1.55 muted → pager (active dot 24px, others 7px) → button. Slide 1 'Every Day Has a Story'; 2 'Your Child, the Hero'; 3 'Listen, Dream, Repeat' (button 'Get Started'). Scene identical on all slides. No swipe and no back control in prototype. | G2: First launch | H2: Setup (Continue on slide 3 / Get Started / Skip) | I2: Brand mark (light), Skip text button, night scene illustration (moon, clouds, twinkling stars, child reading), cream bottom sheet 32dp top radius, eyebrow, title, body, pager dots, primary button | J2: Slide 1, Slide 2, Slide 3 | K2: Static copy only | L2: Pager must announce 'slide n of 3'; twinkle animation must respect reduced motion; Skip ≥48dp | M2: 3 titles/bodies; body min-height 70px may grow in Kannada | N2: EN + KN | O2: LS-014, LS-060 | P2: Design Ready | Q2: Not started | R2: Not reviewed | S2: Should slides support swipe and back? (not in prototype)
B3: SCR-02 | C3: Setup – Child profile | D3: Figma Make · Mobile App UI Prototype · screen 'setup' | E3: 04-setup-profile.jpg | F3: Badge 'Private & parent-managed' (green). Title 'Let’s make stories feel like home.' Fields: Parent name (Meera), Child’s name (Aarav), avatar row (3 faces + dashed +), Age 3–12 (6), Language (English), interests Animals/Cricket/Adventure/Space/Nature/Music (3 preselected, 'Optional'), duration 5/10/15 min (10). CTA 'Create {child}’s profile'. | G3: Onboarding; Child Profiles (Add/Edit); Profile → Account settings | H3: Home (CTA or 'Skip for now') | I3: TopBar with brand + 'Skip for now', trust badge, form card (text fields, avatar picker, age select, language select, interest chips multi-select, segmented duration), sticky CTA | J3: Default, editing, validation (name required – decision), saving | K3: ChildProfile (parent name, child name, avatar, age 3–12, language, interests, default duration) | L3: Labels bound to fields; chips expose selected state; select fields operable by TalkBack | M3: Language list must come from SupportedLanguage registry (EN, ಕನ್ನಡ) – design shows 7 languages | N3: EN + KN | O3: LS-016, LS-045, LS-061, LS-062 | P3: Design Ready | Q3: Not started | R3: Not reviewed | S3: Is parent name needed (data minimisation)? Required-field rules? Avatar '+' behaviour?
B4: SCR-03 | C4: Home | D4: Figma Make · Mobile App UI Prototype · screen 'home' | E4: 05-home.jpg | F4: Header 'Good evening' 12sp muted / 'Stories for Aarav' 21sp. Hero #35256F radius 26: kicker 'TONIGHT’S ADVENTURE', 'Tonight, anything is possible.', body, '+ Create a Story'. Continue card: '8 MIN · 42% COMPLETE', progress lavender, 'Resume story'. Categories: Bedtime, Animals, Adventure, Friendship, Indian Tales (pastel tiles). Culture banner #F5DFC0 'ROOTED IN WONDER / Stories from every corner of India'. | G4: Setup; bottom nav | H4: Notifications, Child Profiles, Create, Player, Discover, Category, Story Detail | I4: Greeting header + bell + avatar, indigo hero card with illustration and white button, SectionHeader, ContinueCard, category tiles row, StoryCard row with heart toggle, culture banner, BottomNav | J4: Populated; no continue-listening item (decision); empty 'Made for' (decision) | K4: Active child, recently played + progress, categories, recommended stories, favourites | L4: Hero image decorative; story cards announce title, category, duration, favourite state | M4: 'Stories for {child}', 'Made for {child}' – name inside string must use format args | N4: EN + KN | O4: LS-014, LS-018, LS-070, LS-091 | P4: Design Ready | Q4: Not started | R4: Not reviewed | S4: Greeting only shows 'Good evening' – time-of-day logic? Empty states for new user not designed
B5: SCR-04a | C5: Discover | D5: Figma Make · Mobile App UI Prototype · screen 'discover' | E5: 06-discover.jpg | F5: Search placeholder 'Search stories, themes, or characters'. Featured #242044: 'FEATURED THIS WEEK', 'The Little Elephant Who Shared', 'Listen now ▷'. Chips: All, Animals, Adventure, Friendship, Kindness, Nature, Space, Science, Panchatantra, Indian Folk Tales, Festivals, Learning. Sections 'Popular right now' (+View all) and 'Bedtime favourites'. | G5: Bottom nav; Home 'See all' | H5: Story Detail, Category, Notifications | I5: TopBar brand+title+bell, search field with clear, dark featured card, horizontal filter chips, 2-column grid, horizontal row | J5: Default, searching (featured hidden, title 'Results for …'), filtered by chip | K5: Catalog, categories, favourites | L5: Search field labelled; chip selection announced | M5: Search must work for Kannada titles (locale-aware lowercase/contains) | N5: EN + KN | O5: LS-014, LS-016, LS-018, LS-071 | P5: Design Ready | Q5: Not started | R5: Not reviewed | S5: Featured card 'Listen now' goes to Detail in prototype – should it open Player?
B6: SCR-04b | C6: Discover – No results (empty state) | D6: Figma Make · Mobile App UI Prototype · screen 'discover (empty)' | E6: 06-discover.jpg | F6: 'No stories found' / 'Try a different title or explore one of our story collections.' / 'Clear search' (resets query and chip to All). Described in design spec; not separately captured as screenshot. | G6: Search with no match | H6: Clear search → Discover default | I6: Empty state (icon tile, title, body, secondary button) | J6: Empty | K6: None | L6: Empty state title announced as heading | M6: – | N6: EN + KN | O6: LS-017, LS-072 | P6: Design Ready (spec only) | Q6: Not started | R6: Not reviewed | S6: No separate screenshot – confirm visual
B7: SCR-05 | C7: Category (Indian Tales) | D7: Figma Make · Mobile App UI Prototype · screen 'category' | E7: 21-category-indian-tales.jpg | F7: Hero 220px indigo: '18 STORIES', 'Indian Tales', description. 'Stories for curious minds' + sort pill. Rows: art 78×91, eyebrow category, title, 'Ages 4–7 · 6 min', green 'Available offline', heart. | G7: Home category tile / culture banner; Discover 'View all' | H7: Story Detail; back → Discover | I7: TopBar with back + title, indigo category hero with arch illustration, sort select, ListStoryRow with heart | J7: Populated; sort Recommended/Shortest first/Newest | K7: Category, stories in category, downloaded flag, favourites | L7: Sort control labelled; rows announce offline availability | M7: '{n} stories' needs plurals | N7: EN + KN | O7: LS-018, LS-073 | P7: Design Ready | Q7: Not started | R7: Not reviewed | S7: Prototype hard-codes Indian Tales – generic per category? Hero art per category?
B8: SCR-06 | C8: Story Detail | D8: Figma Make · Mobile App UI Prototype · screen 'detail' | E8: 22-story-detail.jpg | F8: Cover 355px. Pill category, title 27sp, metadata Ages 4–7 · 6 min · EN, synopsis 14/1.65, lesson panel #FFF4E8 with peach tile, 'Narrated story – Warm, expressive voice · English – ✓ Available'. Sticky: 'Listen to Story' (primary) + 'Read Story' (secondary). | G8: Story cards/rows anywhere | H8: Player (Listen), Reader (Read), back | I8: Full-bleed cover with floating back/favourite/download, white body sheet, pill, metadata row, synopsis, 'A little lesson' panel, narration row, sticky dual CTA | J8: Favourite on/off, downloaded on/off | K8: Story (title, category, ages, minutes, language, synopsis, lesson, narration) | L8: Cover decorative; metadata read as one phrase | M8: Language tag 'EN' must reflect story language (EN/ಕನ್ನಡ) | N8: EN + KN | O8: LS-018, LS-044, LS-074 | P8: Design Ready | Q8: Not started | R8: Not reviewed | S8: –
B9: SCR-07 | C9: Create a Story | D9: Figma Make · Mobile App UI Prototype · screen 'create' | E9: 07-create-story.jpg 08-create-story-more-options-and-error.jpg | F9: Textarea label 'What happened today?', counter n/500. Suggestions: A day at school, A family adventure, Something funny happened, I learned something new, An act of kindness. Hero select (Aarav, Ananya). Themes: Adventure*, Bedtime, Animals, Friendship, Fantasy, Learning, Indian folklore. More options: Mood Calm/Funny/Magical*/Adventurous; Duration 5/8*/10/15 minutes; Story language. Error 'Tell us one little moment to begin the story.' CTA 'Create My Story ✦'. | G9: Home hero CTA; bottom nav Create | H9: Generating (valid submit) | I9: TopBar title + 'Parent guided' label, intro orb, textarea with counter, suggestion chips, story-hero selector, theme chips, collapsible 'More options' (mood, duration, story language), safety note, primary CTA, error banner | J9: Default, more options expanded, validation error, typing clears error | K9: Child profiles, StoryCreationRequest | L9: Error must be announced (live region); counter readable; chips single-select semantics | M9: Placeholder is gendered ('helped his friend') – needs neutral, translatable copy; counter uses format args | N9: EN + KN | O9: LS-016, LS-080, LS-081 | P9: Design Ready | Q9: Not started | R9: Not reviewed | S9: Story language list must be EN/KN only; gendered placeholder copy
B10: SCR-08 | C10: Generating + Paused | D10: Figma Make · Mobile App UI Prototype · screen 'generating' | E10: 09-generating.jpg | F10: Eyebrow 'A STORY FOR AARAV', 'Creating your little adventure…', 'We’re weaving today’s moments into something wonderful.' Bar lavender→yellow. Stages: Imagining the adventure / Writing the story / Preparing the narration. Footnote 'This usually takes less than a minute.' Paused: 'Story creation paused', 'Your idea is still here. Continue whenever you’re ready.', Try again / Back to your idea. Prototype: +4% every 120ms. | G10: Create submit | H10: Story Ready (auto at 100%); Paused → Try again / Back to your idea | I10: Night gradient, close button, twinkling stars, magic book, eyebrow, title, gradient progress bar + %, 3-stage list, footnote; paused state with icon + 2 buttons | J10: Progress (stages <38% / <76% / ≥76%), paused (cancelled) | K10: Simulated generation job | L10: Progress announced politely (not every tick); close button labelled; reduced motion | M10: 'A story for {CHILD}' uppercase via style, not string | N10: EN + KN | O10: LS-017, LS-082, LS-083 | P10: Design Ready | Q10: Not started | R10: Not reviewed | S10: Paused state not captured as screenshot
B11: SCR-09 | C11: Story Ready | D11: Figma Make · Mobile App UI Prototype · screen 'generated' | E11: 10-story-ready.jpg | F11: Ribbon #E9F6EE '✓ Your story is ready'. Cover 385px, badge 'Made for Aarav'. 'A MAGICAL ADVENTURE', title 28sp, English · 8 min · Ages 5–9. 'A little peek inside' quote with lavender rule. Listen Now / Read Story. Row 'Saved to My Stories – Find it anytime in Created by Me'. | G11: Generating complete; notification | H11: Player, Reader, My Stories (Created by Me) | I11: Success ribbon, cover with back/favourite/download + 'Made for' badge, body sheet, eyebrow, title, metadata, synopsis, pull-quote, dual buttons, 'Saved to My Stories' row | J11: Ready | K11: Generated story | L11: Ribbon announced on arrival | M11: Story content must be in selected story language | N11: EN + KN | O11: LS-018, LS-044, LS-082, LS-084 | P11: Design Ready | Q11: Not started | R11: Not reviewed | S11: –
B12: SCR-10 | C12: Reader | D12: Figma Make · Mobile App UI Prototype · screen 'reader' | E12: 11-reader.jpg | F12: Background #FFFAF2. '1 of 5'. Paragraph Manrope 16/1.95 #393348, scalable in 0.1 steps. Reader nav: ghost Previous, round indigo play 54px, ghost Next. | G12: Detail 'Read Story', Story Ready, Player 'Story text' | H12: Player (narration button), back | I12: TopBar 'Reading' + back + favourite, page indicator, A−/A+ buttons, 3dp reading progress, title, cover (page 1), paragraph, flourish, bottom bar Previous / play / Next | J12: Page 1..n, first (Previous disabled), last (Next disabled), text scale 0.9–1.3 | K12: Story pages, reading progress, text-size preference | L12: A−/A+ labelled 'Decrease/Increase text size'; text must also respect system font scale | M12: Kannada paragraphs need larger line height; page indicator uses format args | N12: EN + KN | O12: LS-018, LS-044, LS-090, LS-091 | P12: Design Ready | Q12: Not started | R12: Not reviewed | S12: Persist text size per child or app-wide?
